Workbook
Name MY_FUNCTION1: LAMBDA(SUMPRODUCT(--(range="color")))

Sheet ID Location
A1: ID | B1: Cabinet Location | C1: Binder # | D1: IPAD
A2: DBS-0044 | B2: 1 | C2: 6 | D2: 2 ENGLISH
A3: DBS-0053 | B3: 1 | C3: 7 | D3: 1 SPANISH
A4: DBS-0219 | B4: 2 | C4: 11 | D4: 2 SPANISH
A5: DBS-0349 | B5: 2 | C5: 17 | D5: 1 SPANISH
A6: DBS-0008 | B6: 1 | C6: 3 | D6: 1 SPANISH
A7: DBS-0299 | B7: 2 | C7: 15 | D7: 1 SPANISH
A8: DBS-0360 | B8: 3 | C8: 28 | D8: 1 SPANISH
A9: DBS-0322 | B9: 1 | C9: 9 | D9: 1 SPANISH
A10: DBS-0382 | B10: 2 | C10: 18 | D10: 1 SPANISH
A11: DBS-0432 | B11: 5 | C11: 47 | D11: 1 ENGLISH
A12: DBS-0221 | B12: 3 | C12: 19 | D12: 1 SPANISH
A13: DBS-0404 | B13: 3 | C13: 28 | D13: 2 SPANISH
... A28: DBS-0169 | B28: 3 | C28: 19 | D28: 2 SPANISH
A29: DBS-0108 | B29: 2 | C29: 13
A30: DBS-0450 | B30: 3 | C30: 24 | D30: 1 SPANISH
A31: DBS-0379 | B31: 3 | C31: 25 | D31: 2 SPANISH
A32: DBS-0414 | B32: 3 | C32: 25 | D32: 1 SPANISH
A33: DBS-0055 | B33: 5 | C33: 47 | D33: 1 SPANISH
A34: DBS-0586 | B34: 3 | C34: 27 | D34: 1 SPANISH
A35: DBS-0569 | B35: 6 | C35: 55 | D35: 1 SPANISH
A36: DBS-0028 | B36: 1 | C36: 2 | D36: 1 SPANISH (2024) and 2 SPANISH (2024,2025)
A37: DBS-0268 | B37: 2 | C37: 15
A38: DBS-0429 | B38: 3 | C38: 22 | D38: 1 SPANISH
A39: DBS-0499 | B39: 2 | C39: 14 | D39: 1 SPANISH
A40: DBS-0658 | B40: 4 | C40: 31 | D40: 2 SPANISH
A41: DBS-0498 | B41: 3 | C41: 20 | D41: 2 SPANISH
A42: DBS-0216 | B42: 3 | C42: 22 | D42: 2 SPANISH
A43: DBS-0418 | B43: 2 | C43: 12 | D43: 2 SPANISH
A44: DBS-0620 | B44: 4 | C44: 29 | D44: 2 SPANISH
A45: DBS-0502 | B45: 2 | C45: 10 | D45: 2 SPANISH
A46: DBS-0199 | B46: 2 | C46: 14 | D46: 2 ENGLISH
A47: DBS-0745 | B47: 6 | C47: 57 | D47: 2 ENGLISH
A48: DBS-0657 | B48: 4 | C48: 29 | D48: 1 SPANISH
A49: DBS-0884 | B49: 6 | C49: 50 | D49: 2 SPANISH | E49: 562-250-6793 new number starting June. Cell ending in 7879 will no longer be in service after may
A50: DBS-0542 | B50: 4 | C50: 36
A51: DBS-0705 | B51: 6 | C51: 57
A52: DBS-0597 | B52: 3 | C52: 20 | D52: 2 SPANISH
A53: DBS-0800 | B53: 5 | C53: 39 | D53: 2 SPANISH
A54: DBS-0741 | B54: 6 | C54: 56 | D54: 2 SPANISH
A55: DBS-0676 | B55: 7 | C55: 60 | D55: 1 ENGLISH
A56: DBS-0790 | B56: 5 | C56: 41 | D56: 1 ENGLISH
A57: DBS-0772 | B57: 4 | C57: 33 | D57: 2 SPANISH
A58: DBS-0693 | B58: 5 | C58: 40 | D58: 1 SPANISH
A59: DBS-0715 | B59: 6 | C59: 56 | D59: 1 SPANISH
A60: DBS-0924 | B60: 8 | C60: 72 | D60: 2 ENGLISH
A61: DBS-0808 | B61: 4 | C61: 34
A62: DBS-0587 | B62: 7 | C62: 60 | D62: 1 SPANISH
A63: DBS-0599 | B63: 6 | C63: 55 | D63: 1 SPANISH
A64: DBS-0822 | B64: 6 | C64: 51 | D64: 1 ENGLISH
A65: DBS-0757 | B65: 4 | C65: 31 | D65: 1 SPANISH (2024) and 2 SPANISH (2024)
A66: DBS-0763 | B66: 4 | C66: 34 | D66: 1 SPANISH
A67: DBS-0935 | B67: 7 | C67: 62 | D67: 1 SPANISH
A68: DBS-0613 | B68: 6 | C68: 53 | D68: 2 SPANISH
A69: DBS-0771 | B69: 5 | C69: 41 | D69: 2 ENGLISH
A70: DBS-0879 | B70: 5 | C70: 40 | D70: 1 SPANISH/ 1 ENGLISH | E70: MJ 02/18/26: did eng np in baseline and esp np in 2nd yr,,pt feels more comfortable in eng
A71: DBS-0805 | B71: 4 | C71: 37 | D71: 1 SPANISH
A72: DBS-0781 | B72: 5 | C72: 43 | D72: 2 spanish- under 0617
A73: DBS-0756 | B73: 4 | C73: 35 | D73: 1 ENGLISH
A74: DBS-0442 | B74: 3 | C74: 21 | D74: 1 ENGLISH
A75: DBS-1016 | B75: 7 | C75: 64 | D75: 1 SPANISH
A76: DBS-0824 | B76: 6 | C76: 54 | D76: 1 SPANISH
A77: DBS-0789 | B77: 6 | C77: 49 | D77: 2 SPANISH
A78: DBS-0770 | B78: 5 | C78: 46 | D78: 2 SPANISH
A79: DBS-0956 | B79: 7 | C79: 62 | D79: 2 SPANISH
A80: DBS-0855 | B80: 4 | C80: 35 | D80: 1 SPANISH
A81: DBS-0830 | B81: 5 | C81: 43 | D81: 1 SPANISH
A82: DBS-1039 | B82: 6 | C82: 58 | D82: 2 SPANISH
... A87: DBS-0901 | B87: 6 | C87: 49 | D87: 2 SPANISH
A88: DBS-1032 | B88: 7 | C88: 67
A89: DBS-0652 | B89: 5 | C89: 48 | D89: 2 SPANISH
A90: DBS-0617 | B90: 6 | C90: 51 | D90: 1 SPANISH (2024) and (error 2 SPANISH(2024): wrong ID)
A91: DBS-0978 | B91: 4 | C91: 32 | D91: 1 SPANISH
A92: DBS-0876 | B92: 4 | C92: 32 | D92: 2 SPANISH
A93: DBS-0908 | B93: 5 | C93: 45 | D93: 2 SPANISH
A94: DBS-0918 | B94: 8 | C94: 74 | D94: 2 SPANISH
A95: DBS-1096 | B95: 7 | C95: 65
A96: DBS-0878 | B96: 6 | C96: 52 | D96: 2 ENGLISH
A97: DBS-0818 | B97: 5 | C97: 44 | D97: 1 SPANISH
A98: DBS-0982 | B98: 5 | C98: 42 | D98: 2 SPANISH
A99: DBS-1019 | B99: 8 | C99: 69 | D99: 1 SPANISH
A100: DBS-0940 | B100: 6 | C100: 58 | D100: 1 SPANISH
A101: DBS-0971 | B101: 7 | C101: 63 | D101: 2 SPANISH
A102: DBS-0969 | B102: 6 | C102: 54 | D102: 1 SPANISH
A103: DBS-0798 | B103: 4 | C103: 38 | D103: 2 SPANISH
A104: DBS-1071 | B104: 8 | C104: 71 | D104: 2 SPANISH
A105: DBS-1092 | B105: 7 | C105: 66
A106: DBS-0838 | B106: 4 | C106: 37 | D106: 1 SPANISH
A107: DBS-1008 | B107: 8 | C107: 68 | D107: 2 SPANISH
A108: DBS-1047 | B108: 8 | C108: 68 | D108: 1 SPANISH
A109: DBS-0843 | B109: 4 | C109: 30 | D109: 2 SPANISH
A110: DBS-1106 | B110: 8 | C110: 72 | D110: 1 ENGLISH
A111: DBS-1012 | B111: 7 | C111: 66 | D111: 1 ENGLISH
A112: DBS-1085 | B112: 8 | C112: 75 | D112: 1 ENGLISH
A113: DBS-0653 | B113: 4 | C113: 33 | D113: 1 SPANISH
A114: DBS-1392 | B114: 10 | C114: 96 | D114: 2 SPANISH
A115: DBS-1000 | B115: 8 | C115: 71 | D115: 1 SPANISH
A116: DBS-0985 | B116: 8 | C116: 70
A117: DBS-0987 | B117: 8 | C117: 69 | D117: 2 SPANISH
A118: DBS-1076 | B118: 7 | C118: 65 | D118: 1 ENGLISH
...

Sheet Completed Visits
A1: SECOND YEAR | G1: THIRD YEAR | H1: last verified 10/14 | I1: important to stick to 2yr mri protocol | K1: FOURTH YEAR | L1: last verified: 10/14 | M1: important to document np date for a 1yr gap | O1: COMPLETED
A2: ID | B2: Participant Assigned to | C2: Scheduling Month | D2: Notes | E2: Diabetes Status | G2: ID | H2: Scheduling Month | I2: Notes | K2: ID | L2: Scheduling Month | M2: Notes | O2: ID | P2: Month/ Year | Q2: Notes
A3: DBS-0007 | B3: GT | C3: 45413 | E3: D | G3: DBS-0382 | H3: 45778 | K3: DBS-0044 | L3: 46143 | O3: DBS-0007 | P3: 46143
A4: DBS-0008 | B4: LC | C4: 45413 | D4: LP pending | E4: D | G4: DBS-0322 | H4: 45778 | K4: DBS-0322 | L4: 46143 | O4: DBS-0044 | P4: 46143
A5: DBS-0028 | B5: GT | C5: 45413 | D5: LP Pending | E5: D | G5: DBS-0183 | H5: 45778 | K5: DBS-0007 | L5: 46143 | O5: DBS-0322 | P5: 46143
A6: DBS-0044 | B6: LC | C6: 45413 | E6: D | G6: DBS-0180 | H6: 45778 | K6: DBS-0053 | L6: 46143 | O6: DBS-0073 | P6: 46143
A7: DBS-0053 | B7: LC | C7: 45413 | E7: D | G7: DBS-0053 | H7: 45778 | K7: DBS-0169 | L7: 46143 | O7: DBS-0169 | P7: 46143
A8: DBS-0139 | B8: GT | C8: 45413 | E8: ND | G8: DBS-0044 | H8: 45778 | K8: DBS-0073 | L8: 46143 | O8: DBS-0360 | P8: 46174
A9: DBS-0180 | B9: LC | C9: 45413 | D9: LP Pending | E9: D | G9: DBS-0007 | H9: 45778 | K9: DBS-0360 | L9: 46174 | O9: DBS-0008 | P9: 46174
A10: DBS-0183 | B10: GT | C10: 45413 | E10: D | G10: DBS-0419 | H10: 45809 | K10: DBS-0054 | L10: 46174 | O10: DBS-0054 | P10: 46174
A11: DBS-0219 | B11: LC | C11: 45413 | E11: D | G11: DBS-0404 | H11: 45809 | K11: DBS-0154 | L11: 46174 | O11: DBS-0053 | P11: 46174
A12: DBS-0268 | B12: LC | C12: 45413 | E12: D | G12: DBS-0381 | H12: 45809 | K12: DBS-0221 | L12: 46174 | O12: DBS-0299 | P12: 46174
A13: DBS-0322 | B13: GT | C13: 45413 | E13: D | G13: DBS-0360 | H13: 45809 | K13: DBS-0008 | L13: 46174 | O13: DBS-0063 | P13: 46174
A14: DBS-0352 | B14: LC | C14: 45413 | E14: ND | G14: DBS-0352 | H14: 45809 | K14: DBS-0235 | L14: 46174 | O14: DBS-0235 | P14: 46174
A15: DBS-0382 | B15: LC | C15: 45413 | E15: ND | G15: DBS-0299 | H15: 45809 | K15: DBS-0299 | L15: 46174 | O15: DBS-0154 | P15: 46174
A16: DBS-0404 | B16: GT | C16: 45413 | E16: ND | G16: DBS-0235 | H16: 45809 | K16: DBS-0063 | L16: 46174 | O16: DBS-0221 | P16: 46174
A17: DBS-0013 | B17: GT | C17: 45444 | E17: D | G17: DBS-0221 | H17: 45809 | K17: DBS-0180 | L17: 46204 | O17: DBS-0180 | P17: 46204
A18: DBS-0054 | B18: GT | C18: 45444 | E18: D | G18: DBS-0169 | H18: 45809 | K18: DBS-0028 | L18: 46204 | O18: DBS-0349 | P18: 46204
A19: DBS-0063 | B19: LC | C19: 45444 | E19: D | G19: DBS-0154 | H19: 45809 | K19: DBS-0349 | L19: 46204 | O19: DBS-0430 | P19: 46204
A20: DBS-0073 | B20: LC | C20: 45444 | E20: D | G20: DBS-0139 | H20: 45809 | K20: DBS-0430 | L20: 46204 | O20: DBS-0586 | P20: 46204
A21: DBS-0108 | B21: LC | C21: 45444 | D21: LP Pending | E21: ND | G21: DBS-0073 | H21: 45809 | K21: DBS-0502 | L21: 46241 | O21: DBS-0432 | P21: 46235
A22: DBS-0154 | B22: LC | C22: 45444 | E22: D | G22: DBS-0063 | H22: 45809 | K22: DBS-0442 | L22: 46235 | O22: DBS-0499 | P22: 46235
A23: DBS-0169 | B23: LC | C23: 45444 | E23: D | G23: DBS-0054 | H23: 45809 | K23: DBS-0199 | L23: 46235 | O23: DBS-0429 | P23: 46235
A24: DBS-0221 | B24: GT | C24: 45444 | E24: ND | G24: DBS-0008 | H24: 45809 | K24: DBS-0429 | L24: 46235 | O24: DBS-0512 | P24: 46235
A25: DBS-0235 | B25: LC | C25: 45444 | E25: D | G25: DBS-0430 | H25: 45839 | K25: DBS-0381 | L25: 46235 | M25: *have him sign front page of DE4 consent | O25: DBS-0139 | P25: 46235
A26: DBS-0299 | B26: GT | C26: 45444 | E26: D | G26: DBS-0414 | H26: 45839 | K26: DBS-0450 | L26: 46235 | O26: DBS-0404 | P26: 46235
A27: DBS-0381 | B27: LC | C27: 45444 | E27: ND | G27: DBS-0379 | H27: 45839 | K27: DBS-0586 | L27: 46235 | O27: DBS-0381 | P27: 46235
A28: DBS-0419 | B28: LC | C28: 45444 | E28: ND | G28: DBS-0349 | H28: 45839 | K28: DBS-0499 | L28: 46235 | O28: DBS-0199 | P28: 46235
A29: DBS-0360 | B29: GT | C29: 45445 | E29: ND | G29: DBS-0028 | H29: 45839 | K29: DBS-0139 | L29: 46235 | O29: DBS-0502 | P29: 46235
A30: DBS-0055 | B30: GT | C30: 45474 | D30: LP Pending | E30: ND | G30: DBS-0586 | H30: 45870 | K30: DBS-0404 | L30: 46235 | O30: DBS-0450 | P30: 46235
A31: DBS-0349 | B31: LC | C31: 45474 | E31: D | G31: DBS-0512 | H31: 45870 | K31: DBS-0512 | L31: 46235 | O31: DBS-0772 | P31: 46266
A32: DBS-0379 | B32: GT | C32: 45474 | E32: ND | G32: DBS-0502 | H32: 45870 | K32: DBS-0432* | L32: 46235 | O32: DBS-0676 | P32: 46266
A33: DBS-0414 | B33: GT | C33: 45474 | E33: ND | G33: DBS-0499 | H33: 45870 | K33: DBS-0676 | L33: 46266 | O33: DBS-0613 | P33: 46296
A34: DBS-0430 | B34: LC | C34: 45474 | D34: LP Pending | E34: D | G34: DBS-0450 | H34: 45870 | K34: DBS-0772 | L34: 46266 | O34: DBS-0830 | P34: 46296
A35: DBS-0432* | B35: GT | C35: 45474 | D35: LP pending | E35: D | G35: DBS-0442 | H35: 45870 | K35: DBS-0830 | L35: 46266 | M35: skipped a year- never came in for 2nd year | O35: DBS-0569 | P35: 46296
A36: DBS-0199 | B36: GT | C36: 45505 | E36: D | G36: DBS-0432* | H36: 45870 | K36: DBS-0613 | L36: 46296 | O36: DBS-0055 | P36: 46296
A37: DBS-0418 | B37: LC | C37: 45505 | D37: LP Pending | E37: D | G37: DBS-0429 | H37: 45870 | K37: DBS-0620 | L37: 46296
A38: DBS-0429 | B38: GT | C38: 45505 | E38: D | G38: DBS-0199 | H38: 45870 | K38: DBS-0055 | L38: 46296
A39: DBS-0450 | B39: GT | C39: 45505 | E39: D | G39: DBS-0013 | H39: 45870 | K39: DBS-0569 | L39: 46296
A40: DBS-0499 | B40: LC | C40: 45505 | D40: LP Pending | E40: D | G40: DBS-0676 | H40: 45901 | K40: DBS-0745 | L40: 46296
A41: DBS-0502 | B41: GT | C41: 45505 | E41: D | G41: DBS-0620 | H41: 45901 | K41: DBS-0587 | L41: 46296
A42: DBS-0512 | B42: GT | C42: 45505 | D42: LP Pending | E42: D | G42: DBS-0613 | H42: 45901 | K42: DBS-0599 | L42: 46296
A43: DBS-0586 | B43: GT | C43: 45505 | D43: LP Pending | E43: ND | G43: DBS-0772 | H43: 45931 | K43: DBS-0657 | L43: 46296
A44: DBS-0442 | B44: LC | C44: 45536 | E44: ND | G44: DBS-0757 | H44: 45931 | K44: DBS-0741 | L44: 46327
A45: DBS-0613 | B45: LC | C45: 45536 | E45: ND | G45: DBS-0745 | H45: 45931 | I45: *stool | K45: DBS-0216 | L45: 46327
A46: DBS-0620 | B46: LC | C46: 45536 | E46: ND | G46: DBS-0599 | H46: 45931 | K46: DBS-0693 | L46: 46327
A47: DBS-0676 | B47: LC | C47: 45536 | D47: LP failed | E47: D | G47: DBS-0216 | H47: 45931 | K47: DBS-0418 | L47: 46327
A48: DBS-0216 | B48: GT | C48: 45566 | E48: ND | G48: DBS-0055 | H48: 45931 | K48: DBS-0790 | L48: 46327
A49: DBS-0498 | B49: LC | C49: 45566 | E49: ND | G49: DBS-0418 | H49: 45931 | I49: PSQI uncompleted | K49: DBS-0658 | L49: 46327
A50: DBS-0542 | B50: GT | C50: 45566 | E50: D | G50: DBS-0587 | H50: 45931 | K50: DBS-0652 | L50: 46327
A51: DBS-0569 | B51: GT | C51: 45566 | E51: ND | G51: DBS-0569 | H51: 45931 | K51: DBS-0855 | L51: 46327
A52: DBS-0587 | B52: LC | C52: 45566 | E52: ND | G52: DBS-0597 | H52: 45931 | K52: DBS-0805 | L52: 46357 | M52: MRI and BD are in Jan 2026
A53: DBS-0597 | B53: LC | C53: 45566 | E53: ND | G53: DBS-0657 | H53: 45931 | K53: DBS-0824 | L53: 46357
A54: DBS-0599 | B54: GT | C54: 45566 | E54: D | G54: DBS-0219 | H54: 45931 | K54: DBS-0818 | L54: 46357
A55: DBS-0657 | B55: GT | C55: 45566 | E55: ND | G55: DBS-0498 | H55: 45931 | I55: MRI in oct- do np,cv,bd ~ in dec/jan, came 10 months late | K55: DBS-0614 | L55: 46357
A56: DBS-0658 | B56: GT | C56: 45566 | E56: D | G56: DBS-0658 | H56: 45962 | K56: DBS-0653 | L56: 46357
A57: DBS-0705 | B57: LC | C57: 45566 | E57: D | G57: DBS-0741 | H57: 45962 | K57: DBS-0800 | L57: 46357
A58: DBS-0745 | B58: GT | C58: 45566 | E58: D | G58: DBS-0652 | H58: 45962 | K58: DBS-0884 | L58: 46357 | M58: SP completed in person. Missing questionairre.
A59: DBS-0757 | B59: GT | C59: 45566 | E59: D | G59: DBS-0855 | H59: 45962 | K59: DBS-0981 | L59: 46388
A60: DBS-0772 | B60: GT | C60: 45566 | E60: ND | G60: DBS-0790 | H60: 45962 | I60: *stool | K60: DBS-0987 | L60: 46388
A61: DBS-0614 | B61: GT | C61: 45597 | E61: ND | G61: DBS-0800 | H61: 45962 | K61: DBS-0617 | L61: 46388
A62: DBS-0652 | B62: LC | C62: 45597 | E62: D | G62: DBS-0693 | H62: 45962 | K62: DBS-1016 | L62: 46388
A63: DBS-0693 | B63: LC | C63: 45597 | E63: D | G63: DBS-0614 | H63: 45962 | K63: DBS-0924 | L63: 46388 | M63: MRI on Nov 2025
A64: DBS-0715 | B64: GT | C64: 45597 | E64: ND | G64: DBS-0715 | H64: 45962 | I64: missed cv, couldnt come back, no changes filled it out | K64: DBS-0498 | L64: 46388
A65: DBS-0741 | B65: LC | C65: 45597 | E65: D | G65: DBS-0763 | H65: 45992 | K65: DBS-0838 | L65: 46388
A66: DBS-0756 | B66: GT | C66: 45597 | E66: ND | G66: DBS-0617 | H66: 45992 | K66: DBS-0935 | L66: 46388
A67: DBS-0771 | B67: GT | C67: 45597 | E67: ND | G67: DBS-0653 | H67: 45992 | I67: *stool | K67: DBS-0956 | L67: 46388 | M67: Might get a new phone # - email to get in touch or house mail if you are not able to reach
A68: DBS-0790 | B68: GT | C68: 45597 | E68: ND | G68: DBS-0781 | H68: 45992 | K68: DBS-0978 | L68: 46388 | M68: 908 wife
A69: DBS-0800 | B69: GT | C69: 45597 | E69: ND | G69: DBS-0805 | H69: 45992 | I69: *stool | K69: DBS-0763 | L69: 46388
A70: DBS-0855 | B70: GT | C70: 45597 | E70: D | G70: DBS-0818 | H70: 45992 | I70: *stool | K70: DBS-0878 | L70: 46388
A71: DBS-0617 | B71: LC | C71: 45627 | E71: ND | G71: DBS-0824 | H71: 45992 | I71: *stool | K71: DBS-0771 | L71: 46388
A72: DBS-0653 | B72: GT | C72: 45627 | D72: Might want to do LP... | E72: ND | G72: DBS-0879 | H72: 45992 | I72: *stool | K72: DBS-0789 | L72: 46419
A73: DBS-0763 | B73: LC | C73: 45627 | E73: ND | G73: DBS-0884 | H73: 45992 | I73: *stool | K73: DBS-0879 | L73: 46419 | M73: NP in feb & MRI in jan
A74: DBS-0781 | B74: GT | C74: 45627 | E74: ND | G74: DBS-0756 | H74: 45992 | I74: *stool | K74: DBS-1019 | L74: 46419
A75: DBS-0805 | B75: LC | C75: 45627 | E75: D | G75: DBS-0770 | H75: 46023 | I75: *stool | K75: DBS-0971 | L75: 46419
A76: DBS-0818 | B76: GT | C76: 45627 | E76: D | G76: DBS-0916 | H76: 46023 | I76: *stool | K76: DBS-0982 | L76: 46419
A77: DBS-0822 | B77: LC | C77: 45627 | E77: ND | G77: DBS-0935 | H77: 46023 | I77: *stool | K77: DBS-0756 | L77: 46419 | M77: very difficult might not come back
A78: DBS-0824 | B78: LC | C78: 45627 | E78: ND | G78: DBS-0956 | H78: 46023 | I78: *stool | K78: DBS-0597 | L78: 46420 | M78: Might leave to mex at the end of the year. Willing to come in before dec to complete 4th year
A79: DBS-0830 | B79: LC | C79: 45627 | E79: ND | G79: DBS-0981 | H79: 46023 | I79: *stool | K79: DBS-1039 | L79: 46420
A80: DBS-0838 | B80: GT | C80: 45627 | E80: ND | G80: DBS-0843 | H80: 46023 | I80: *stool | K80: DBS-0715 | L80: 46447
A81: DBS-0879 | B81: LC | C81: 45627 | D81: LP pending | E81: D | G81: DBS-0838 | H81: 46023 | I81: *stool | K81: DBS-1047 | L81: 46447
A82: DBS-0884 | B82: LC | C82: 45627 | E82: ND | G82: DBS-0918 | H82: 46023 | I82: *stool | K82: DBS-1008 | L82: 46447
A83: DBS-0770 | B83: LC | C83: 45658 | E83: ND | G83: DBS-0878 | H83: 46023 | I83: *stool | K83: DBS-0940 | L83: 46447
A84: DBS-0789 | B84: LC | C84: 45658 | E84: ND | G84: DBS-0924 | H84: 46023 | I84: -needs to fill out reproductive form, *stool | K84: DBS-0770 | L84: 46447
A85: DBS-0808 | B85: GT | C85: 45658 | E85: ND | G85: DBS-0789 | H85: 46023 | I85: *stool | K85: DBS-0908 | L85: 46447 | M85: 978 husband
A86: DBS-0878 | B86: LC | C86: 45658 | E86: ND | G86: DBS-0987 | H86: 46056 | I86: *stool | K86: DBS-1071 | L86: 46447
A87: DBS-0908 | B87: LC | C87: 45658 | E87: ND | G87: DBS-1016 | H87: 46056 | I87: *Stool | K87: DBS-1152 | L87: 46478
A88: DBS-0916 | B88: LC | C88: 45658 | E88: ND | G88: DBS-0982 | H88: 46056 | I88: *stool | K88: DBS-1076 | L88: 46478
A89: DBS-0918 | B89: LC | C89: 45658 | E89: ND | G89: DBS-0971 | H89: 46056 | I89: *Stool | K89: DBS-1000 | L89: 46478
A90: DBS-0924 | B90: GT | C90: 45658 | D90: LP pending | E90: D | G90: DBS-0901 | H90: 46056 | I90: *stool | K90: DBS-0969 | L90: 46478 | M90: MRI done on 06/02/26
A91: DBS-0935 | B91: LC | C91: 45658 | E91: D | G91: DBS-0771 | H91: 46056 | I91: *stool | K91: DBS-1106 | L91: 46478
A92: DBS-0956 | B92: GT | C92: 45658 | E92: D | G92: DBS-0798 | H92: 46054 | I92: *Stool | K92: DBS-1119 | L92: 46478
A93: DBS-0978 | B93: GT | C93: 45658 | E93: ND | G93: DBS-0978 | H93: 46054 | K93: DBS-0822 | L93: 46478
A94: DBS-0981 | B94: GT | C94: 45658 | E94: ND | G94: DBS-0908 | H94: 46054 | K94: DBS-1134 | L94: 46478
A95: DBS-0843 | B95: LC | C95: 45659 | E95: D | G95: DBS-1019 | H95: 46054 | I95: *stool | K95: DBS-0918 | L95: 46478
A96: DBS-0901 | B96: GT | C96: 45689 | E96: ND | G96: DBS-1039 | H96: 46054 | I96: *stool | K96: DBS-1263 | L96: 46478
A97: DBS-0982 | B97: LC | C97: 45689 | E97: ND | G97: DBS-1030 | H97: 46054 | I97: *Stool | K97: DBS-1030 | L97: 46479
A98: DBS-0987 | B98: GT | C98: 45689 | E98: ND | G98: DBS-1071 | H98: 46082 | I98: *Stool | K98: DBS-1143 | L98: 46480
A99: DBS-1016 | B99: GT | C99: 45689 | E99: ND | G99: DBS-0876 | H99: 46082 | I99: *Stool | K99: DBS-1246 | L99: 46508
A100: DBS-1032 | B100: GT | C100: 45689 | E100: ND | G100: DBS-0940 | H100: 46082 | I100: *stool | K100: DBS-1167 | L100: 46508
...

Sheet MRI Dates Available
A1: Month | B1: MRI Dates | C1: MRI Times | J1: SCAN COST | K1: 720
A2: May '25 | B2: 45793 | C2: Scan: 8am-9am | D2: Cancelled. Kat out of office. | G2: scheduled/ taken
B3: 45793 | C3: Scan: 11am-12pm | D3: Ghost date. Slot not filled. | G3: pending
B4: 45796 | C4: Scan: 11am-12pm | G4: cancelled
B5: 45796 | C5: Scan: 8am-9am | G5: came in but did not comnplete scan - rescheduled
B6: 45798 | C6: Scan: 8am-9am | D6: Ghost date. Slot not filled.
B7: 45799 | C7: Scan: 8am-9am
B8: 45804 | C8: Scan: 8am-9am | D8: Cancelled. Not filled.
A9: June '25 | B9: 45810 | C9: Scan: 8am-9am | D9: Cancelled. Participant drop out.
B10: 45810 | C10: Scan: 10am-11am | D10: Participant rescheduled.
B11: 45811 | C11: Scan: 8am-9am
B12: 45812 | C12: Scan: 9:30am-10:30am
B13: 45813 | C13: Scan: 8am-9am
B14: 45814 | C14: Scan: 8am-9am
B15: 45814 | C15: Scan: 9:30am-10:30am
B16: 45817 | C16: Scan: 8am-9am | D16: Cancelled ahead of time. Not filled.
B17: 45817 | C17: Scan: 9:30am-10:30am
B18: 45818 | C18: Scan: 8am-9am
B19: 45819 | C19: Scan: 8am-9am
B20: 45819 | C20: Scan: 9:30am-10:30am | D20: July
B21: 45821 | C21: Scan: 8am-9am | D21: Cancelled ahead of time. Ghost date -not filled.
A22: July '25 | B22: 45847 | C22: Scan: 8am-9am | D22: June Participatn cancelled ahead of time.
B23: 45847 | C23: Scan: 9:30am-10:30am | D23: June Participatn cancelled ahead of time.
B24: 45848 | C24: Scan: 8am-9am | D24: May
B25: 45852 | C25: Scan: 8:30am-9:30am | D25: 0028 came in but did not start scan - rescheduled for 7/21/26
B26: 45859 | C26: Scan: 10:30am-11:30am
B27: 45861 | C27: Scan: 8:00am-9:00am | D27: June
B28: 45866 | C28: Scan: 8:30am-9:30am | D28: May Participatn cancelled ahead of time.
B29: 45866 | C29: Scan: 8:30am-9:30am | D29: August
B30: 45868 | C30: Scan: 9:00am-10:00am | D30: August
A31: August '25 | B31: 45870 | C31: Scan: 9:00am-10:00am
B32: 45873 | C32: Scan: 10am-11am | D32: June pt - 0169 came in but did not start scan.
B33: 45873 | C33: Scan: 11:30am-12:30pm | D33: June pt - 0073 came in but did not start scan.
B34: 45877 | C34: Scan:8:00am-9:00am
B35: 45880 | C35: Scan:8:00am-9:00am
B36: 45880 | C36: Scan: 9:30am-10:30am | D36: July
B37: 45882 | C37: Scan: 9:00am-10:00am scan rescheduled bc kat out
B38: 45882 | C38: Scan: 10:30am-11:30am scan rescheduled bc kat out
B39: 45889 | C39: Scan:8:00am-9:00am
B40: 45889 | C40: Scan: 9:30am-10:30am
B41: 45890 | C41: Scan:8:00am-9:00am | D41: Cancelled by Kat
B42: 45891 | C42: Scan: 10:00am-11:00am
B43: 45891 | C43: Scan: 8:30am-9:30am
B44: 45894 | C44: Scan: 8:30am-9:30am
B45: 45896 | C45: Scan:8:00am-9:00am Participant no-showed
A46: September '25 | B46: 45904 | C46: Scan:8:00am-9:00am Blocked out by Kat. Cancelled due to funding
B47: 45908 | C47: Scan:8:00am-9:00am pending funding Cancelled due to funding | D47: June
B48: 45908 | C48: Scan: 9:30am-10:30am pending funding Cancelled due to funding | D48: June
B49: 45909 | C49: Scan:8:00am-9:00am pending funding Cancelled due to funding
B50: 45930 | C50: Scan:8:00am-9:00am *
A51: October '25 | B51: 45943 | C51: Scan:8:00am-9:00am * | D51: $40,000 added to our acct
B52: 45944 | C52: Scan:8:00am-9:00am *
B53: 45946 | C53: Scan:8:00am-9:00am *
B54: 45951 | C54: Scan:8:00am-9:00am *
B55: 45953 | C55: Scan:8:00am-9:00am *
B56: 45957 | C56: Scan:8:00am-9:00am ... | D56: double booked 9:30
B57: 45958 | C57: Scan:8:00am-9:00am * | D57: Participant cancelled last min
B58: 45958 | C58: Scan:9:30am-10:30am *
A59: November '25 | B59: 45965 | C59: Scan:8:00am-9:00am * | D59: Sceduled for 0657. Filled by 0924
B60: 45968 | C60: Scan:8:00am-9:00am *
B61: 45968 | C61: Scan:9:30am-10:30am *
B62: 45971 | C62: Scan:8:00am-9:00am
B63: 45972 | C63: Scan:9:00am-10am
B64: 45972 | C64: Scan:1:00pm-2:00pm
B65: 45978 | C65: Scan:8:00am-9:00am *
B66: 45979 | C66: Scan:8:00am-9:00am *
B67: 45979 | C67: Scan:9:30am-10:30am *
B68: 45981 | C68: Scan:8:00am-9:00am *
B69: 45985 | C69: Scan:8:00am-9:00am
B70: 45986 | C70: Scan:8:00am-9:00am
B71: 45987 | C71: Scan:8:00am-9:00am | D71: Participant cancelled w advance notice
B72: 45987 | C72: Scan:9:30am-10:30am *
A73: December '25 | B73: 45994 | C73: Scan:8:00am-9:00am *
B74: 45994 | C74: Scan:9:30am-10:30am *
B75: 45996 | C75: Scan:8:00am-9:00am * | D75: no blood , done at keck
B76: 46002 | C76: Scan:8:30am-9:30am | D76: shifted to start at 8am
B77: 46006 | C77: Scan:9:00am-10:00am
B78: 46010 | C78: Scan:8:00am-9:00am
B79: 46010 | C79: Scan:9:30am-10:30am | D79: no blood, done at keck
B80: 46013 | C80: Scan:8:00am-9:00am | D80: no blood , done at keck
B81: 46014 | C81: Scan:8:00am-9:00am
A82: January '26 | B82: 46027 | C82: Scan:8:00am-9:00am
B83: 46028 | C83: Scan:8:00am-9:00am | D83: last min switch 0981 original to 1016 fill in
B84: 46029 | C84: Scan:8:00am-9:00am | D84: last min switch 0916 original to 0935 fill in
B85: 46030 | C85: Scan:8:00am-9:00am | D85: Participant cancelled last min no fill in available
B86: 46031 | C86: Scan:8:30am-9:30am | D86: arrived a little late, started ASAP
B87: 46034 | C87: Scan:8:30am-9:30am
B88: 46036 | C88: Scan:8:30am-9:30am | D88: Spot was not filled
B89: 46036 | C89: Scan:10:30am-11:30am
B90: 46037 | C90: Scan:8:00am-9:00am
B91: 46043 | C91: Scan:8:00am-9:00am
B92: 46043 | C92: Scan:9:30am-10:30am
B93: 46044 | C93: Scan:8:00am-9:00am
B94: 46048 | C94: Scan:8:00am-9:00am | D94: MJ 01/23: Pt DBS-0789 canceled ahead of time on 1/23/26. Removed from CIA and Perry notified.
B95: 45684 | C95: Scan:8:00am-9:00am | D95: cancelled day prior no fill in found
B96: 46052 | C96: Scan:8:00am-9:00am
B97: 46052 | C97: Scan:9:30am-10:30am | D97: MJ 1/30: pt could not complete scan,,no sequences done. ;; Started but felt claustrophobic. Did not reschedule.
A98: Febuary '26 | B98: 46055 | C98: Scan:8:00am-9:00am
B99: 46055 | C99: Scan:9:30am-10:30am
B100: 46056 | C100: Scan:8:00am-9:00am
...

Sheet 3rd Yr Scheduling Notes 
D1: MRI + BD Visits | I1: NP + CV Visits | M1: Old Scheduling Notes
A2: Month | B2: ID | D2: MRI/BD Scheduling Notes | E2: MRI Date | F2: BD Date | G2: MRI Scan Time | I2: NP/CV Scheduling Notes | J2: NP Date | K2: CV Date | M2: MRI Scheduling Notes | N2: BD Notes | O2: CV Scheduling Notes | Q2: Completed
A3: May | B3: DBS-0382 | D3: DROPPED JULY 2025 ;; Responded to email. He is in mex and does not anticipate returning till 3-4 yrs from now. No longer able to participate. 7/23/25 JE ;; No answer. 7/14/25 JE ;; LC 04/03: Out of country. F/u in 3 months | M3: Left vm and sent email 7/23/25 JE ;; Left vm and sent text. 7/14/25 JE ;; Was able to leave vm. 7/3/25 JE ;; Operator message, "subscriber not in service." Will try again 6/2/25 JE ;; LC 04/03: Out of country. F/u in 3 months
A4: May | B4: DBS-0322 | E4: 45796 | F4: 45796 | G4: Scan: 8am-9am | I4: Would like to combine visits if possible. Schedule a bit complicated but she is flexible. -JE 4/16/25 | J4: 45792 | K4: 45792 | N4: BD needed to be moved to MRI date bc labs need to be reordered. 5/15/25 -JE ;; IV 5/2: needs uber LC 04/03: Call back tomorrow
A5: May | B5: DBS-0053 | E5: 45930 | F5: 45778 | G5: Scan: 8am-9am | J5: 45778 | K5: 45778 | M5: Participant is back. Apt is pending atm. CIA showing as insufficent funding att. but dbs grant was approved. Will follow up. 9/4/25 JE ;; Let me know that she had to go out of country for an emergency and that she will reach back out when she is back to rescheduled. Cancelled scan for 7/28/25 on 7/23/25 JE ;; Asked to reschedule again bc she broke a toe and cant walk. Was scheduled for June 9th at 8 am. New date for July. 5/30/25 JE ;; Asked to change originally set date of may 27th to june 9th instead. 5/2/25 -JE ;; Left vm and sent text 4/17/25 -JE ;; LC 04/03: Schedule MRI for end of month
A6: May | B6: DBS-0044 | E6: 45796 | F6: 45790 | G6: Scan: 11am-12pm | J6: 45790 | K6: 45796 | N6: LC 04/03: Left vm | O6: IV 5/13: moved to mri day bc it was missed
A7: May | B7: DBS-0183 | D7: DROPPED MAY 2025 ;; Letter mailed out. All forms of contact exhausted. No answer 5/15/25 JE | M7: Left vm and sent text. 7/3/35 JE ;; Mailed out letter. 5/15/25 -JE ;; No answer. 5/6/25 -JE ;; Left vm and sent email.5/1/25 -JE ;; Left vm. 4/24/25 -JE ;; No answer. Sent text.4/16/25 -JE | N7: IV 5/2: left vm, sent text LC 04/03: Left vm
A8: May | B8: DBS-0180 | E8: 45848 | F8: 45810 | G8: Scan: 8am-9am | J8: 45810 | K8: 45819 | M8: Able to schedule over the phone during his NP visit 6/2/25 -JE ;; MJ 05/22:Would like to reschedule for a wk after CV on 06/11/25 ;; Called to reschedule bc Kat will be out Fri (5/16/25). No answer, left vm. New date TBD. 5/14/25 -JE ;; No answer. Sent text. 4/16/25 -JE | N8: MJ 05/22: Uber needed MJ 05/21: Left VM + sent text & email IV 5/2: left vm, sent text LC 04/03: Left vm
A9: May | B9: DBS-0007 | E9: 45799 | F9: 45796 | G9: Scan: 8am-9am | J9: 45796 | K9: 45796 | Q9: 5
A10: June | B10: DBS-0419 | D10: DROPPED MAY 2025 ;; Lead messaged that she is moving to mexico and is no longer able to continue with study. Was supposed to come in on 06/08/25. 5/28/25 -JE | G10: Scan: 8am-9am | M10: Lead messaged that she is moving to mexico and is no longer able to continue with study. 5/28/25 -JE | N10: MJ 05/21: Uber needed
A11: June | B11: DBS-0404 | D11: Sent checkin message. 8/4/25 JE ;; Husband will reach out when ready. Check in in aug. 7/21/25 JE ;; Let IV know they need to cancel, needs reschedule... 7/8/25 JE ;; IV 7/1: rescheduled bd other day | E11: 45889 | F11: 45897 | G11: Scan: 9:30am-10:30am | I11: IV and JE tag teaming on MRI day. 8/4/25 JE ;; See MRI note. 7/8/25 JE ;; Husband wife duo. Would like to combine all visits if possible. -JE 4/28/25 | J11: 45889 | K11: 45897 | M11: Husband wife duo. Needs new date. Was originally scheduled for 7/9/25. Urgent matter had to be cancelled. MRI and NP and CV together 7/8/25 JE ;; Open conversation through text re schdeuleding for him and partner. 4/25/25 -JE ;; Sent text.4/24/25 -JE ;; Left vm 4/17/25 -JE | N11: Husband said he has a surgery and will reach back out when ready to reschedule. 7/21/25 JE ;; Will complete NP day of the MRI. Wife jusband duo. 6/30/25 JE ;; IV 6/17: couldnt make it, app for surgery end of july IV 6/12: will drive
A12: June | B12: DBS-0381 | D12: Can't do Tuesday or Friday. And needs morning appointments. 8/20/25 JE ;; IV 7/30: had to reschedule again , doctors visits 7/22/25 MRI got moved up to 7:30am and had to move NP to CV day bc he has a doc visit tomorrow. He mentioned that that he got an extension on PT. His apointments are Tue and Fri's. Confirmed that visit on the 31st still works ok. JE ;; IV 7/1: wanted to add np tp mri day and cv+bd other day Would like to schedule for July. Was in a car accident and has a neck brace at the moment. 6/2/25 -JE | E12: 45861 | F12: 45890 | G12: Scan: 8:00am-9:00am | I12: See schdeuling notes. JE ;; Same day as MRI | J12: 45890 | K12: 45890 | M12: Same day but time moved up. 7/22/25 JE ;; New date for July 23rd. 6/2/25 JE ;; Participant canceled needs to reschedule. Car accident w/ neck brace at the moment. 5/30/25 JE ;; Has surgery 28th of April. Still open to scheduling for June. 4/17/25 -JE | N12: IV 6/23: left vm sent text IV 5/29: left vm, sent text
A13: June | B13: DBS-0360 | E13: 45812 | F13: 45813 | G13: Scan: 9:30am-10:30am | J13: 45812 | K13: 45812 | N13: IV 5/29: Np, cv same as mri day, bd other day will drive
A14: June | B14: DBS-0352 | D14: DROPPED JAN 2026 ;; No answer to calls or text 1/29/26 ;; No answer. Sent text. 1/27/26 JE ;; Checking in. No answer. Left vm. 12/2/25 JE ;; IV 5/29: had an accident, asked to be removed bc she has alot of physical therapy andrecovery process, maybe contact in a few months | I14: Would like to combine all visits if possible. -JE 4/17/25 | M14: Had an accident but should be better by June. 4/17/25 -JE
A15: June | B15: DBS-0299 | E15: 45818 | F15: 45820 | G15: Scan: 8am-9am | J15: 45820 | K15: 45820 | N15: IV 5/29: will drive
A16: June | B16: DBS-0235 | D16: Tuesdays or Friday (days off) | E16: 45814 | F16: 45825 | G16: Scan: 9:30am-10:30am | J16: 45825 | K16: 45825 | M16: Open conversation through text re scheduling. 4/25/25 -JE ;; Sent text. 4/24/25 -JE ;; Left vm 4/17/25 -JE | N16: IV 5/29: will call me back today
A17: June | B17: DBS-0221 | E17: 45819 | F17: 45818 | G17: Scan: 8am-9am | J17: 45818 | K17: 45818 | M17: Date confirmed. 4/23/25 -JE ;; Lead called back. Confirmation pending for 6/11 @7:30 am. Would drive. 4/21/25 -JE ;; Left vm 4/17/25 -JE | N17: IV 5/29: will drive
A18: June | B18: DBS-0169 | E18: 45994 | F18: 45807 | G18: Scan: 8am-9am | J18: 45807 | K18: 45807 | M18: Needs to reschedule. Moved from oct 28 to first week of dec. 10/6/25 JE ;; Tentative apt. set 9/17/25 JE ;; MRI TBD due to funding. Husband was notified and will let wife know. Reschedule as soon as able to book scans again. 9/2/25 JE ;; Ventura couple. Was scheduled for 8/4/25 and came in but had breakfast so could not scan. New date for Sept 8th. 8/4/25 pending (funding not available att). Follow up on cia. JE ;; Scheduled for Aug. -JE 4/24/25 ;; Left vm -JE 4/17/25 | N18: IV 5/22: will drive, with wife Couple from Ventura. Will be out of country June-July. -JE 4/24/25
A19: June | B19: DBS-0154 | E19: 45813 | F19: 45819 | G19: Scan: 8am-9am | J19: 45819 | K19: 45819 | N19: IV 5/29: will drive
A20: June | B20: DBS-0139 | E20: 45889 | F20: 45897 | G20: Scan: 8am-9am | I20: IV and JE tag teaming on MRI day. 8/4/25 JE ;; See MRI note on DBS-0404. 7/8/25 JE ;; Husband wife duo. Would like to combine all visits if possible. -JE 4/28/25 | J20: 45889 | K20: 45897 | M20: Wife and husband coming together. 4/28/25 - JE ;; Sent text. 4/24/25 -JE ;; Left vm 4/17/25 -JE | N20: Husband said he has a surgery and will reach back out when ready to reschedule. 7/21/25 JE ;; Will complete NP day of the MRI. Wife jusband duo. 6/30/25 JE ;; IV 6/17: couldnt make it, app for surgery end of july IV 6/12: will drive
A21: June | B21: DBS-0073 | E21: 45994 | F21: 45807 | G21: Scan: 9:30am-10:30pm | J21: 45807 | K21: 45807 | M21: Needs to reschedule. Moved from oct 28 to first week of dec. 10/6/25 JE ;; Tentative apt. set 9/17/25 JE ;; Left message with husband 9/2/25 JE ;; Ventura couple. Was scheduled for 8/4/25 and came in but had breakfast so could not scan. New date for Sept 8th. 8/4/25 JE ;; Scheduled for Aug. 4/24/25 -JE ;; Left vm 4/17/25 -JE | N21: IV 5/22: will drive, with husband Couple from Ventura. Will be out of country June-July. -JE 4/24/25
A22: June | B22: DBS-0063 | E22: 45814 | F22: 45833 | G22: Scan: 8am-9am | I22: Fridays preferred. Open to combining visits if possible. -JE 4/17/25 | J22: 45833 | K22: 45833 | N22: IV 5/22: will drive, or might need uber
A23: June | B23: DBS-0054 | E23: 45811 | F23: 45813 | G23: Scan: 8am-9am | I23: Would like to combine visits if possible. -JE 4/17/25 | J23: 45813 | K23: 45813 | N23: IV 5/22: needs uber
A24: June | B24: DBS-0008 | E24: 45817 | F24: 45824 | G24: Scan: 9:30am-10:30am | J24: 45824 | K24: 45824 | M24: Will need new clincard 4/24/25 -JE ;; Left vm 4/17/25 -JE | N24: IV 5/22: needs uber | Q24: 13
A25: July | B25: DBS-0430 | E25: 45880 | F25: 45848 | G25: Scan: 9:30am-10:30am | I25: IV 6/23: bd+np, will drive | J25: 45848 | K25: 45880 | M25: Cheking Aug dates with Kat. Green light to book back to back. New date 8/11/25. 7/14/25 JE ;; Needs new date. Waiting on call back from second MRI visit that week to possible swap dates. Otherwise will be schedueld for Aug. Was scheduled for 7/21/25. 7/11/25 -JE ;; | N25: IV 6/23: bd+np, will drive | O25: New date. Was scheduled for 7/21/25. 7/11/25 -JE ;; IV 6/23: mri+ cv, will drive
A26: July | B26: DBS-0414 | D26: DROPPED NOV 2025 ;; Waiting for reply - sent follow up group text 11/19/25 JE ;; Said she needs to talk to her sis and then will call back. 11/12/25 JE ;; Asked for more time before scheduling anything. Check back next month. 10/3/25 JE ;; Follow up in October. 0414 expressed that 0379 shared she may not want to cont. bc they have fam problems att. BUT opened to beinging contacted again in a few months... 8/4/25 JE ;; Contact 0379 to schedule they want visits to be together. 0414 is ok with any day 0379 is able to do. | M26: Shared that due to family matters no longer able to continue. And her sis either. 11/21/25 JE ;; No answer. Called back and said she might still be interested but her sis no. Will call back. 11/19/25 JE ;; Said she will call back. 11/12/25 JE ;; Asked for more time before scheduling anything. Check back next month. 10/3/25 JE ;; Asked to set up schedule with 0379 (related) to be the same day. 5/22/25 -JE
A27: July | B27: DBS-0379 | D27: DROPPED NOV 2025 ;; Waiting for reply - sent follow up group text 11/19/25 JE ;; Follow up in October. 0414 expressed that 0379 shared she may not want to cont. bc they have fam problems att. BUT opened to beinging contacted again in a few months... 8/4/25 JE ;; MJ 07/30:Will talk to sister,,texted MRI dates available Takes care of kids and will bedifficult to schedule long visits in July. Schedule for late August. Visit will be w/ sister. day 1 - MRI, NP / day 2- CV, BD 5/22/25 -JE | M27: Never answered but sis shared she will likely not cont. 11/21/25 JE ;; No answer. 11/19/25 JE ;; Left vm. 10/3/25 JE ;; Has not set up date. Left vm. 7/23/25 JE ;; Days offered are august 25, 27, 29. Asked to give her a call back. Needs to check her dates 7/3/25 JE ;; Not able to scheduel till IRB renewal is cleared. 5/22/25 -JE
A28: July | B28: DBS-0349 | D28: MJ 06/25: Driving | E28: 45819 | F28: 45853 | G28: Scan: 9:30am-10:30am | J28: 45853 | K28: 45853 | M28: No vmb. Sent text. Open conversation through text. 6/2/25 JE ;; No vmb. Will try again. 5/22/25 -JE | N28: MJ 06/25: call failed,,sent text IV 6/24: call cannot go thru
A29: July | B29: DBS-0028 | D29: MJ 06/25: May need an Uber | E29: 45859 | F29: 45845 | G29: Scan: 10:30am-11:30am | J29: 45845 | K29: 45845 | M29: New MRI date 7/21/25. Does not need to draw blood. 7/16/25 JE ;; Came in for MRI on 7/14/25 but was not able to complete scan due to feeling dizzy (blood sugar may have been low). Would like to reschedule. New date TBD. 7/14/25 JE | Q29: 3
A30: August | B30: DBS-0586 | D30: MJ 07/22: Left VM + sent text 6/25 NC Mailed Letter ;; Was on vacation but is back now and ready to schedule. JE | E30: 45891 | F30: 45882 | G30: Scan: 10:00am-11:00am | J30: 45875 | K30: 45882 | M30: Blocked out by kat for us to schedule once IRB clears. 7/3/35 JE;; Left vm and sent text. 6/24/25 JE ;; Left vm. 6/5/25 JE | N30: MJ 07/22: Uber needed
A31: August | B31: DBS-0512 | D31: IV 07/1: wanted to add cv mri day, bd+np other date Prefers Tuesdays if possible. Advance notice opens availability. JE | E31: 45868 | F31: 45897 | G31: Scan: 9:00am-10:00am | J31: 45897 | K31: 45868 | M31: Left vm. 6/5/25 JE | N31: Needs new date. Will get his schedule for September Aug 30th. New date TBD BD and NP combined. 8/14/25 JE ;; MJ 07/31: Rescheduled visit for 08/18
A32: August | B32: DBS-0502 | D32: Open to schedule. excpt will be going out of the country Aug 22 (or sooner) for about two weeks. JE | E32: 45866 | F32: 45876 | G32: Scan: 8:00am-9:00am | J32: 45876 | K32: 45876 | M32: Participant moved. Originally scheduled for 8/7. New date 7/28. 7/23/25 JE
A33: August | B33: DBS-0499 | D33: Some pain walking. Needs to move slowly. Had shoulder surgery. In rehab but should be better by August. Ok to schedule. Not working att. Open. JE | E33: 45894 | F33: 45876 | G33: Scan: 08:30am-10:30am | J33: 45876 | K33: 45876 | M33: Originally scheduled for 8/13/25 but changed to 8/25/25 due to kat being out. 7/23/25 JE ;; Left vm. 6/5/25 JE | N33: Originally schedued for aug 4 but has an appointment she forgot about. Will come in on the 7 instead. 7/31/25 JE
A34: August | B34: DBS-0450 | E34: 45891 | F34: 45883 | G34: Scan: 08:30am-10:30am | J34: 45883 | K34: 45883 | M34: Originally scheduled for 8/13/25 but changed to 8/22/25 due to kat being out. 7/23/25 JE
A35: August | B35: DBS-0442 | E35: 45870 | F35: 45884 | G35: Scan: 9:00am-10:00am | J35: 45884 | K35: 45884
A36: August | B36: DBS-0432* | D36: 6/25 NC Mailed Letter ;; Busy with church. But flexible-ish.... JE | E36: 45953 | F36: 45875 | G36: Scan: 8am-9am | J36: 45875 | K36: 45875 | M36: Kat out sick. New date needed. Funding pending... TBD... 8/20/25 JE ;; Blocked out by kat for us to schedule once IRB clears. 7/3/35 JE ;; Left vm and sent text. 6/24/25 JE ;; Left vm. 6/5/25 JE
A37: August | B37: DBS-0429 | D37: MJ 07/24: Would like a call back tomorrow to schedule | E37: 45880 | F37: 45887 | G37: Scan:8:00am-9:00am | J37: 45887 | K37: 45887
A38: August | B38: DBS-0199 | D38: Pref Friday , but open | E38: 45877 | F38: 45884 | G38: Scan:8:00am-9:00am | J38: 45884 | K38: 45884 | M38: Left vm. 6/5/25 JE
A39: August | B39: DBS-0013 | D39: DROPPED DEC 2025 ;; Lost contact. All forms of contact exhausted. No reply. 12/3/25 ;; DV 09/18: Mailed letter ;; Scheduled for 9/10/25 but has not been answering. Left vm, text and email. 9/8/25 JE ;; MJ 07/28: Left VM MJ 07/24: Left VM + sent text Would like to combine visits if possible. Needs to ask for permision at work. But flexible. | M39: Did not answer or show for MRI. Waiting to hear back. Called, sent text, and email. 8/27/25 JE ;; Originally scheduled for 8/6/25 but asked to reschedule. New date 8/27/25. JE 8/4/25 ;; | N39: MJ 09/18: St to vm,,left vm | Q39: 9
A40: September | B40: DBS-0676 | D40: IV 09/3: will drive MJ 09/02: left vm IV 8/28: left vm, sent text | E40: 45951 | F40: 45925 | G40: Scan:8:00am-9:00am | J40: 45925 | K40: 45925 | M40: Tentative apt. set 9/19/25 JE ;; Open conversation through text. 7/23/25 JE ;; Left vm 7/22/25 JE
A41: September | B41: DBS-0620 | D41: IV 9/24: needs uber MJ 09/15: Left VM + sent text MJ 09/08: Left VM + sent text IV 8/28: left vm, sent text | E41: 46010 | F41: 45933 | G41: Scan:8:00am-9:00am | J41: 45933 | K41: 45933 | M41: Call if there is a cancellation this week. Has to reschedulde nov 18. New date dec 19. 11/10/25 JE ;; Scheduled during 3rd yr visit w/ IV. 10/3/25 JE ;; Sent follow up text. 10/1/25 JE ;; Is open and ready to schedule in November. She will send over date options to coordinate. 9/26/25 JE ;; Frw to vm. Sent text. 8/4/25 JE ;; Left vm 7/22/25 JE
A42: September | B42: DBS-0613 | D42: IV 8/28: needs uber Thursday's prefered in the morning. 7/22/25 JE | E42: 45968 | F42: 45932 | G42: Scan:8:00am-9:00am | J42: 45932 | K42: 45932 | M42: IV 10/2: available Oct. 16,17,30,31, if we have any cancellations Left vm. 9/26/25 JE ;; IV 8/28: has to be after the 7th ;; Blocked for us by Kat. 7/23/25 JE | Q42: 3
A43: October | B43: DBS-0772 | D43: MJ 09/18: Left VM + sent text | E43: 45946 | F43: 45930 | G43: Scan:8:00am-9:00am | J43: 45930 | K43: 45930 | M43: Changed from 13 and 16
A44: October | B44: DBS-0757 | D44: DROPPPED NOV 2025 ;; Spouse called in after receiving letter. Informed that participant passed Dec 2024 11/10/25 JE ;; Letter mailed out. All forms of contact exhausted. No answer 11/4/25 JE ;; MJ 10/28: Left VM + sent text IV 10/3: left vm, sent text IV 9/23: left vm, sent text | M44: Straight to vm. Left message and notified of letter going out in mail. 10/31/25 JE ;; Again to vm. No response to text. Sent email to one on file and w edit. 10/22/25 JE ;; Straight to vm again. Left vm and sent text. 10/15/25 JE ;; Stright to vm. Left vm. 10/1/25 JE
A45: October | B45: DBS-0745 | D45: MJ 09/18: Left VM + could not send text | E45: 45943 | F45: 45939 | G45: Scan:8:00am-9:00am | J45: 45939 | K45: 45939 | M45: Got a new phone. Reminder of her other visits. MRI also set. 10/1/25 JE
A46: October | B46: DBS-0599 | D46: IV 9/24: needs uber MJ 09/18: Would like a call back later, Called, no answer, left text message asking to confirm for 10/20 CTS. (Confirmed 10/17) -CTS | E46: 45979 | F46: 45950 | G46: Scan: 9:30am-10:30am | J46: 45950 | K46: 45950 | M46: Needs after 8am bc drops off kids at school. Not able to do Fridays. 10/3/25 JE ;; IV 9/24: mentioned she's kind of scared of MRI, recently had bad experience
A47: October | B47: DBS-0216 | D47: MJ 09/19: Could not leave VM + sent text | E47: 46006 | F47: 45971 | G47: Scan:9:00am-10:00am | J47: 45971 | K47: 45971 | M47: Answered but is busy att and wants to look at dates to plan around husbands dc apt. Will call back. 10/22/25 JE ;; Left vm and sent text. 10/15/25 JE ;; Straight to vm, box full. 10/3/25 JE
A48: October | B48: DBS-0055 | D48: lives near MJ 09/19: Left VM + sent text | E48: 45968 | F48: 45933 | G48: Scan: 9:30am-10:30am | J48: 45933 | K48: 45933 | M48: Called to see if she could fill in but na. Keeps original date 10/28/25 JE ;; Left vm. Ended up schdeuling in person. 10/3/25 JE
A49: October | B49: DBS-0418 | D49: MJ 09/19: work bad hours,, off of work at 2:30 pm,,cannot do Mondays AM | E49: 46034 | F49: 45953 | G49: Scan:8:30am-9:30am | J49: 45978 | K49: 45978 | M49: Scehduled for jan , update cia with id number 11/17/25 IV ;; Left vm. 11/12/25 JE ;; Interested in december to request day off. 10/23/25 IV ;; Sent text to try and coordinate date. 10/15/25 JE ;; MJ 09/19: work bad hours,, off of work at 2:30 pm,,cannot do Mondays AM | O49: IV 10/23: confirmed MJ 09/19: Pending date w/ Dr Harrington
A50: October | B50: DBS-0587 | D50: IV:needs uber, new date confirmed 10/10: needs to reschedulem had to work IV 9/23: left vm, sent text , answered | E50: 45978 | F50: 45946 | G50: Scan:8:00am-9:00am | J50: 45946 | K50: 45946 | M50: Called to see if avai for fill in but na. 11/4/25 JE ;; Not availabe wednesdays. 10/3/25 JE
A51: October | B51: DBS-0569 | D51: IV 9/23: will drive | E51: 45987 | F51: 45937 | G51: Scan: 9:30am-10:30am | J51: 45937 | K51: 45937
A52: October | B52: DBS-0597 | D52: Answered - needs wednesdays. 12/18/25 JE ;; Not answering. Sent follow up text. Responded not ready yet...11/19/25 ;; Seemed more open but would like more time. Call after nov 5th 10/22/25 JE ;; IV 9/23: not comfortable coming rn, immigration, call back in a month | E52: 46071 | F52: 46071 | G52: Scan:8:00am-9:00am | I52: Needs Uber. 1/14/26 JE | J52: 46078 | K52: 46078 | M52: Needs wednesdays. 12/18/25 JE ;; Sent check in text. 12/1/25 JE ;; Sent to vm. Followed up with text. Responded that she did not feel safe to come in yet. I offered scheduling out for Jan. She said she will be in touch. 11/19/25 JE ;; Left vm. 11/12/25 JE ;; Seemed more open but would like more time. Call after nov 5th 10/22/25 JE ;; IV 9/23: not comfortable coming rn, immigration, call back in a month
A53: October | B53: DBS-0657 | D53: IV 10/14: moved to 10/21, rescheduling due to rain IV 9/23: will drive | E53: 45979 | F53: 45951 | G53: Scan:8:00am-9:00am | J53: 45951 | K53: 45951 | M53: Avai this fri makeup 11/10/25 JE ;; Cancelled last min bacuse she had high temp fever. New date TBD.11/4/25 JE ;; Left vm. Called back. Needs Tuesdays. 10/3/25 JE
A54: October | B54: DBS-0219 | D54: DROPPED DEC 2025 ;; All forms of contact exhausted. No answer. 12/3/2025 ;; Letter mailed out. All forms of contact exhausted. No answer. 11/4/25 JE ;; MJ 10/21: left vm + sent text IV 10/03: left vm sent text IV 9/23: left vm, sent text | M54: Left vm and notified of card going out in mail. 10/31/25 JE ;; Straight to vm. No reply to text. Sent email. 10/22/25 JE ;; Straight to oppperator. Left vm and sent text. 10/15/25 JE ;; Left vm. 10/3/25 JE
A55: October | B55: DBS-0498 | D55: IV 10/14: prefers to wait to january Will be traveling end of october till mid-end of december ;; MRI in oct - do np,cv,bd ~ in dec/jan, came 10 months late | E55: 45944 | F55: 46045 | G55: Scan:8:00am-9:00am | J55: 46045 | K55: 46045 | N55: regular bd no h or extra tubes
A56: October | B56: DBS-0830 | D56: came yr late, treat as a 3rd year | E56: 45972 | F56: 45995 | G56: Scan:8:30am-9:30am | J56: 45930 | K56: 45931 | M56: Sent text. Open convo. Veterans day may work. 10/15/25 JE ;; Busy at work. Complicated scheduled. Will call back. 10/6/25 JE Canceled BD on 11/26/25, will call back. CTS | Q56: 12
A57: 45962 | B57: DBS-0658 | D57: MJ 10/21: uber needed | E57: 45981 | F57: 45972 | G57: Scan:8:00am-9:00am | J57: 45972 | K57: 45972 | M57: Avail lun martes, or fri nov 7th. Not avai today 11/4/25 JE
A58: 45962 | B58: DBS-0741 | D58: MJ 10/21: Uber needed from home address //Left VM + sent text | E58: 45958 | F58: 45971 | G58: Scan: 9:30am-10:30am | I58: *omit logical memory, gets emotional | J58: 45971 | K58: 45971 | M58: Needs uber (home address) 10/6/25 JE
A59: 45962 | B59: DBS-0652 | D59: Works. Only availabe Fridays. 10/6/25 JE | E59: 45996 | F59: 45996 | G59: Scan:8:00am-9:00am | J59: 45986 | K59: 45986 | M59: Need Fridays. 10/6/25 JE
A60: 45962 | B60: DBS-0855 | D60: MJ 11/07: Will give me a call back,,she was at work and busy all day Works three part time jobs 7 days. | E60: 45972 | F60: 45981 | G60: Scan:1:00pm-2:00pm | J60: 45986 | K60: 45986 | M60: Left vm and sent text. Paerticipant reponded. Is very busy. She requested to come in pm even though it is fasting. 10/15/25 JE ;; Left vm. 10/6/25 JE
A61: 45962 | B61: DBS-0790 | D61: MJ 10/22: Would like a call back in 30 minutes | E61: 45985 | F61: 45978 | G61: Scan:8:00am-9:00am | J61: 45978 | K61: 45978 | M61: Cancelled short notice bc not feeling well. New day tbd. 10/28/25 JE
A62: 45962 | B62: DBS-0800 | D62: MJ 11/25: Would like a call back in 15 min MJ 10/22: could not leave vm + text sent Open to schedule but will be traveling to mex. Dates tbd around nov 20th 10/7/25 JE | E62: 46002 | F62: 46014 | G62: Scan:8:00am-9:00am | J62: 46014 | K62: 46014 | M62: Vmb full. Participant sent text to text instead. Asked for availability tomorrow or nov. Open convo. 10/6/25
A63: 45962 | B63: DBS-0693 | D63: Works every other friday has oct 17 off and so forth | E63: 45971 | F63: 45975 | G63: Scan:8:00am-9:00am | J63: 45975 | K63: 45975 | M63: Did intro. Call suddenly ended. Sent follow up text to call back. 10/15/25 JE ;; No ring, no vm. Phoen temp unavai. 10/6/25 JE
A64: 45962 | B64: DBS-0614 | D64: MJ 10/28: Left VM + sent text She is a teacher and would like to come in dec if possible closer to holiday | E64: 46014 | F64: 46010 | G64: Scan:8:00am-9:00am | J64: 46010 | K64: 46010 | M64: Nov may not work. She is a teacher and would like to come in dec instead. Open convo through text. 10/9/25 JE ;; Driving. Follow up with a text to confirm. 10/6/25 JE
A65: 45962 | B65: DBS-0715 | D65: MJ 11/25: Scheduled 01/12/26 MJ 10/22: left vm + sent text Needs Mondays time 10am preferred. Book MRI as soon as possible | E65: 45957 | F65: 46083 | G65: Scan:9:30am-10:30am | I65: Left vm. Called back and scheduled. Needs Mondays. 2/6/26 JE ;; Cancelled again feb 2nd. Said she needed to take husband to doc. New date TBD. 2/1/26 ;; Cancelled jan 12. New date set 1/9/25 JE | J65: 46083 | K65: 46083 | M65: Left vm and sent text. Participant called back but did not answer on time. Will try again. 10/15/25 JE ;; Left vm. 10/3/25 | N65: Participant called in to cancel. Needs new date. Available Mondays. Emailed MJ to update 11/12/25 JE | Q65: 9
A66: 45992 | B66: DBS-0763 | D66: IV 12/9: will do everything mri day, needed to reschdule IV 11/25: np,cv, will drive | E66: 46052 | F66: 46052 | G66: Scan:8:00am-9:00am | J66: 46052 | K66: 46052 | M66: Responded to text that he was in mex. Still interested and open to schedule. Open text convo. Avai 2,9,16,23,30 of Jan 11/7/25 JE ;; Vmb not set up. No respod to text. Sent email. 11/5/25 JE ;; Same operator message. Sent text. 10/31/25 JE ;; Vmb not set up. Will try again. 10/24/25 JE | N66: bd on mri day
A67: 45992 | B67: DBS-0617 | D67: No answer. Sent text. Available to come in Jan for other visits. 12/17/25 JE ;; MJ 12/02: Could not leave vm,, sent text New phone update on redcap. MRI scheduled for feb but may be able to come to other visits sooner. 12/1/25 JE ;; IV 12/1: left vm, sent text & email MJ 11/25: Couldnt leave vm + sent text | E67: 46043 | F67: 46043 | G67: Scan:9:30am-10:30am | J67: 46043 | K67: 46043 | M67: Shared new num preference - update on redcap. Needs 9am apt bc she does school am drop off. Call if cancelation on wed pref 12/1/25 JE ;; No answer. No vm. 11/19/25 JE ;; Left vm, sent text and email. 11/12/25 JE ;; Straight to vm. Sent text. 10/31/25 JE ;; Left vm. 10/24/25 JE
A68: 45992 | B68: DBS-0653 | D68: IV 12/1: doing everything in one day, needs uber IV 11/24: will call me back, Started a new job about a month ago. Goes in at 7am-4pm. Has the week off dec 22nd off. 10/24/25 JE | E68: 46013 | F68: 46013 | G68: Scan:8:00am-9:00am | J68: 46013 | K68: 46013 | M68: Started a new job about a month ago. Goes in at 7am-4pm. 10/24/25 JE
A69: 45992 | B69: DBS-0781 | D69: DROPPED DEC 2025 ;; MJ 12/02: Text message sent bc he's at work. Messaged he is moving to OK- no longer able to cont. MJ 11/26: (pronounced Nahoom) will give me a call back on his lunch break Wednesdays day off. Works. Call around 5pm | G69: Scan:10:30am-11:30am | M69: Busy again. Will call back...Gets home late. Requested 10am apt.10/31/25 JE ;; Busy at work. Will call back 10/24/25 JE
A70: 45992 | B70: DBS-0805 | D70: MJ 11/25: Offered 12/10 Left VM,,sent text | E70: 46027 | F70: 46027 | G70: Scan:8:00am-9:00am | I70: pending time | J70: 46001 | K70: 46001 | M70: She responded to text. Open convo through text 11/08/25 JE ;; Followed up 11/5/25 JE ;; Vmb full. Sent text...Replied. Open covo. 10/31/25 JE ;; Left vm. 10/24/25 JE | N70: bd on mri day
A71: 45992 | B71: DBS-0818 | D71: IV 11/24: will drive Fridays day off. Arrived at 8:30am, did MRI first then everything else. CTS 01/9/26 | E71: 46031 | F71: 46031 | G71: Scan:8:30am-9:30am | J71: 46010 | K71: 46010 | M71: Available fridays. Open to fill in if any cancellations. 10/31/25 JE ;; Vmb full. 10/28/25 JE | N71: bd on mri day
A72: 45992 | B72: DBS-0824 | D72: IV 12/1: seemed like call dropped, sent text, responded with a date, will drive MJ 11/25: Left VM and sent text | E72: 45986 | F72: 46003 | G72: Scan:8:00am-9:00am | J72: 46003 | K72: 46003 | M72: Left vm. Lead called back and scheduled for nov. Call if there is a cancellation. 10/28/25 JE
A73: 45992 | B73: DBS-0879 | D73: MJ 12/10: texted to rescheduled bc she is sick MJ 11/25: Driving to visit,,off on Thursday and Fridays | E73: 46036 | F73: 46036 | G73: Scan:10:30am-11:30am | I73: MJ 02/04: Pt went to urgent care and needed to reschedule MJ 2/2: Scheduled for 2/4 MJ 1/27: Follow up | J73: 46071 | K73: 46037 | M73: Participant cancelled due to cough. Moved to jan. 12/18/25 JE ;; New date dec 19. 11/21/25 ;; Reminder text sent. Participant said she needs to reschedule. Needs Thursday or Friday. New day TBD. 11/20/25 JE
A74: 45992 | B74: DBS-0884 | D74: MJ 12/17: uber needed Answered letter. Called in and let us know he got a new num. Updated redcap. 12/4/25 JE ;; Letter mailed out. 12/2/25 JE ;; MJ 11/25: Left VM + sent text No answer since oct. No email on red cap | E74: 46010 | F74: 46010 | G74: Scan:9:30am-10:30am | J74: 46013 | K74: 46013 | M74: Filled in last min for scan tomorrow. 12/18/25 JE ;; Called in after receiving letter. Date TBD. 12/4/25 JE ;; Left vm and sent text. 12/1/25 JE ;; Answers and hangs up. 11/19/25 JE ;; Straight to vm. Sent text. 11/12/25 JE ;; Answered but hung up. When I called back, was sent to vm. Left vm adn sent text. 11/5/25 JE ;; Left vm and sent text. 10/31/25 JE ;; Left vm. 10/28/25 JE
A75: 45992 | B75: DBS-0756 | D75: IV 2/6: needs uber IV 2/3: left vm, sent text, will schedule friday IV 1/30: left vm IV 1/23: CALL AFTER TUESDAY went over visits & compensation, interested, follow up after trip. JE He expressed dissatisfaction with compensation and may not cont. 10/31/25 JE | E75: 46077 | F75: 46077 | G75: Scan:8:00am-9:00am | J75: 46077 | K75: 46077 | M75: Will call back if he decides to cont? 10/31/25 JE ;; Left vm and sent text. 10/31/25 JE ;; Left vm. 10/28/25 JE | Q75: 9
A76: 46023 | B76: DBS-0770 | D76: MJ 02/04: booked for open space on feb 12 CTS 01/26 Wants to reschedule MRI IV 12/22: will drive MJ 12/11: Left VM + sent text | E76: 46065 | F76: 46065 | G76: Scan:8:00am-9:00am | I76: IV Was originally scheduled for jan 26 new date tbd | J76: 46086 | K76: 46086 | M76: Left vm and sent email. 11/19/25 JE ;; Straight to vm again. Sent text. 11/12/25 JE ;; Straight to vm. Left message. 11/5/25 JE | N76: bd on MRI day
A77: 46023 | B77: DBS-0916 | D77: Called in to request sooner date. Moved from the 22nd of may to the 6th 4/30/36 JE ;; All day requested. Schedueld for may 22nd. 4/22/26 JE ;; Left vm. 3/31/26 JE ;; CTS 03/26: Cancelled morning of due to car troubles; will reschedule CTS 03/10: Texted reminder. CTS 02/20: Texted to ask for reschedule for March. CTS 02/19 Texted back to cancel, wants to come in March MJ 12/17: Left VM + sent text; Texted back to cancel; needs to be rescheduled for 01/15/26 if possible CTS 01/6/26 Called, sent to voicemail - CTS 01/13/26. MRI originally scheduled for jan 7th; Scheduled for February | E77: 46148 | F77: 46148 | G77: Scan:8:00am-9:00am | I77: Called in to request sooner date. Moved from the 22nd of may to the 6th 4/30/36 JE ;; Left vm to check in. 3/31/26 JE ;; Carina notified that participant cancelled. New date pending... 3/26/26 JE ;; IV 2/3: left vm sent text, wants to do evrythign same day IV 1/5: left vm, confirming mri visit and if she wnats to add np/cv | J77: 46148 | K77: 46148 | M77: Called in to request sooner date. Moved from the 22nd of may to the 6th 4/30/36 JE ;; CTS 02/19 Called, texted, replied back needing to cancel due to work constrains CTS 01/14/26 Send MRI availability for February. Straight to vm. left message and sent text. Lead responded 11/12/25 JE ;; Followed up through text. 11/5/25 JE ;; Called to see if fill in but na. Will follow up will check her work schedule... 11/4/25 JE | N77: bd on MRI day
A78: 46023 | B78: DBS-0935 | D78: MJ 12/17: Driving; Moved from jan 15 to jan 7th to cover cancellation CTS 01/06/27 | E78: 46029 | F78: 46029 | G78: Scan:8:00am-9:00am | J78: 46044 | K78: 46044 | M78: Pref thursdays. 11/5/25 JE ;; Called to see if fill in but na. Will follow up 11/4/25 JE Offer Stool Kit and Study oartner survey 01/07/26 CTS | N78: bd on MRI day
A79: 46023 | B79: DBS-0956 | D79: Has Obama phone so phone number may change. But he remains interested in study. Please try alternative forms of contact if no answer. 2/3/26 JE ;; Rescheduled MRI to feb 3 but still coming in for cv and np tomorrow. 1/7/26 JE ;; IV 12/10: needs uber, everything same day, got new number, emailed me from diff email, updated Redcap 12/2 Phone not in service? No response. Letter mailed out. 12/2/25 JE | E79: 46056 | F79: 46056 | G79: Scan:8:00am-9:00am | J79: 46030 | K79: 46030 | M79: Card mailed was returned today "return to sender", but IV was able to reach and schedule. 12/10/25 JE ;; Not able to reach. No response to email. 12/1/25 JE ;; Operator- "The person you have dialed is not availabe to receive calls at this time".... sent email. 11/19/25 JE ;; Operator again. Sent text. 11/12/25 JE ;; Operator. No vmb. Will try again. 11/5/25 JE
A80: 46023 | B80: DBS-0981 | D80: MJ 12/17: Driving | E80: 46044 | F80: 46044 | G80: Scan:8:00am-9:00am | J80: 46042 | K80: 46042 | N80: bd on MRI day
A81: 46023 | B81: DBS-0843 | D81: DROPPED APRIL 2026 ;; No answer. No reply to previous attempts to contact. 4/23/26 JE ;; Letter sent out. 4/1/26 JE ;; MJ 02/17:OPTED OUT OF MRI Left VM + sent text MJ 2/5: Called to schedule for feb 24,,mri available CTS 01/26/26 Called, might be available, call back at 5pm Needs to be rescheduled if she replies - CTS 01/14/26 MJ 12/17: was busy so will give a call back another day Wed or Fri avai, Cancelled last min. | I81: Letter sent out. 4/1/26 JE ;; MJ 03/11: Left VM + sent text Sent follow up text. ;; No reply to previous. 3/9/26 JE ;; Sent to vm. Left message and sent text. 3/5/26 JE ;; MJ 03/02: Left VM + sent text Sent check in text. 2/9/26 JE ;; No answer. Left vm. 1/27/26 JE ;; Was originally scheduled for jan 21 but cancelled. | L81: JE | M81: Participant communicated that she had been at the hospital. Will message to confirm avalibility. 1/16/26 JE | N81: bd on MRI day
A82: 46023 | B82: DBS-0838 | D82: MJ 12/17: Could not leave VM + sent text Uber requested | E82: 46043 | F82: 46043 | G82: Scan:8:00am-9:00am | I82: JE | J82: 46051 | K82: 46051 | N82: bd on MRI day
A83: 46023 | B83: DBS-0918 | D83: IIv 1/23: reschelued IV 1/20: cancelled bc of stomach flu MJ 12/17: Might go to MX unsure of dates,. will follow up via text after the 12/20/25 | E83: 46057 | F83: 46057 | G83: Scan:9:30am-10:30am | I83: Vm. Text convo open. Scheduled 4/1/26 JE ;; Straight to vm but vmb not set up.Followed up with text. Still interested. Will call tomorrow. 3/31/26 JE ;; Cancelled due to work. New date pending... 3.25.26 JE ;; Might need Uber. 3/16/26 JE ;; Currently in Mex. Brother is sick. Should be back in about a week. Still interested. 3/5/25 JE ;; IV 2/18: sent follow up text IV 2/11: waiting to hear back on available dates IV 1/23: a reschedule (originally for jan 21), moved to feb but dr. h wont be here, find a date for cv or??? MJ 01/05: Doing all visits in one day,, Follow up text sent | J83: 46125 | K83: 46125 | N83: bd on MRI day
A84: 46023 | B84: DBS-0878 | D84: MJ 12/17: gave dates,,may want to do all visits in one day | E84: 46052 | F84: 46052 | G84: Scan:9:30am-10:30am | I84: all visits in one day | J84: 46052 | K84: 46052 | M84: Left vm and sent text. She replied and is interested. Open convo through text... tentative jan 30...11/19/25 JE ;; Left vm. 11/12/25 | N84: bd on MRI day
A85: 46023 | B85: DBS-0924 | D85: MJ 12/17:driving | E85: 45965 | F85: 46050 | G85: Scan:8:30am-9:30am | J85: 46050 | K85: 46050 | M85: Last min fill in for 0657 11/4/25 JE
A86: 46023 | B86: DBS-0789 | D86: CTS 01/26/26 Called to schedule for tomorrow, left VM; Is scheduled for Feb. MJ 1/23: Canceled in advance was scheduled for jan 26. MJ 12/17: doing all visits in one day Left VM + sent text | E86: 46059 | F86: 46059 | G86: Scan:8:00am-9:00am | I86: Left vm. Called back to schedule. NP and CV diff days. 1/27/26 JE | J86: 46059 | K86: 46078 | M86: Vmb full. Will try again. 11/12/25 | Q86: 10
A87: 46054 | B87: DBS-0987 | D87: CTS 01/14/26 Moved up from scheduled visit on 02/06/26 | E87: 46037 | F87: 46037 | G87: Scan:8:00am-9:00am | I87: JE | J87: 46037 | K87: 46037 | M87: Left vm.Called back and scheduled. 12/16/25 JE
A88: 46055 | B88: DBS-1016 | D88: JE: May be traveling in Feb but no set date yet... | E88: 46028 | F88: 46028 | G88: Scan:8:00am-9:00am | I88: JE: May be traveling in Feb but no set date yet...IV 1/6: scheduled at mri | J88: 46050 | K88: 46050 | M88: CALL IF CANCELLATION SOONER...Left vm. Called back and scheduled. 12/16/25 JE
A89: 46056 | B89: DBS-0982 | D89: MJ | E89: 46062 | F89: 46062 | G89: Scan:8:00am-9:00am | I89: MJ 01/02: needs to confirm if her husband can bring her | J89: 46076 | K89: 46076 | M89: Left vm. Called back and scheduled. 12/16/25 JE
A90: 46057 | B90: DBS-0971 | D90: IV: Monday requested...pref following mon from MRI. Coming from bakersfield - lives there 5 days of the week. | E90: 46055 | F90: 46055 | G90: Scan:8:00am-9:00am | I90: IV 2/2: scheduled at mri, will drive IV 1/28: spoke with, will schedule day of her mri IV 1/23: left vm, V 1/5: left vm, attentping to schedule np/cv , Monday requested...pref following mon from MRI. Coming from bakersfield - lives there 5 days of the week. | J90: 46076 | K90: 46076 | M90: Needs to leave right after MRI to go back to work. Coming from bakersfield. Asked and provided with levels and weight of past years. 12/16/25 JE
A91: 46058 | B91: DBS-0901 | D91: DROPPED JAN 2026 ;; Called in to drop out. No time and too far. No longer interested. 1/14/26 JE ;; Called, left VM: CTS 01/5/26 | I91: MJ 01/13: Left VM MJ 01/02: Left VM + sent text | M91: Left vm. 12/16/25 JE
A92: 46059 | B92: DBS-0771 | D92: Called and scheduled for 02/04/26 - CTS 1/5/26 | E92: 46057 | F92: 46057 | G92: Scan: 8:00am-9:00AM | I92: IV 2/4: completed cv, except neuro exam ; IV 1/30: approved to fill out medical history forms, leave nerological exam blank, if dr. H cant see her or evalauate IV 1/5: called me wanting to do everything same day, can only do np, dr. h out, will ask if he can do virtual | J92: 46057 | K92: 46057 | M92: Left vm. 12/16/25 JE
A93: 46060 | B93: DBS-0798 | D93: Sent text to inform she is dropping out.Reason not provided. Scan scheduled for 6/16 cancelled on CIA 5/22/26 JE ;; martes y miercoles - will be in mex but open to fill in if date available next week 5/13/26 JE ;; Rescheduled due to machine maintenance. Original date for 4/28 new date 6/16. 4/23/26 JE ;; Scheduled. All all day visit. 3/18/26 JE ;; WAIT. GIVE SOME TIME. Sent check in text. 3/16/26 JE ;; CTS 03/10: Called, left VM CTS 03/04 Called, left VM, text. CALL BK IN MARCH ;; Family and work busy. Check in with her next month to plan for march visits all in one day. 1/21/26 JE ;; IV 1/20: left vm, Called, left VM: CTS 01/8/26, 01/14/26, | I93: New date. 4/23/26 JE ;; Scheduled. All all day visit. 3/18/26 JEParticipant sent hi text. Open convo... 3/17/26 JE ;; Follow up text sent. No reply to previous. 3/16/26 JE ;; Sent check in text. 3/5/26 JE ;; She would like to continue but is not sure when she will have time. Her son is in the middle of moving bk to ca. Family and work busy. Check in with her next month to plan for march visits all in one day. 1/21/26 JE ;; Left vm. 1/12/26 JE | L93: JE | M93: Left vm. 12/16/25 JE
A94: 46061 | B94: DBS-0978 | D94: Husband ;; Perry cancelled scan for the week due to scanner being down. New date set for June 11th. Scheduled with wife 4/20/26 JE Scheduled with wife. Will come in together next month. 3/9/26 JE ;; No answer. Sent check in text. 2/26/25 JE ;; MJ 02/23: Sent follow up text MJ 02/17: Left VM + sent text CTS 2/6 Was originally scheduled for feb 10th but cancelled due to accident, unable to come in the foreseeable future. Call back maybe March/April MJ 2/6: Left VM + sent text CTS 02/26 Called the wife, left VM CTS 02/5 Called, left VM Husband | E94: 46184 | F94: 46184 | G94: Scan:9:30-10:30am | I94: MJ 01/02: Wanted to schedule for Jan 2026,,uber needed | J94: 46037 | K94: 46037 | M94: Left vm. Wife answered and programed his visit. Coming in feb 12/16/25 JE
A95: 46062 | B95: DBS-0908 | D95: Wife ;; Perry cancelled scan for the week due to scanner being down. New date set for June 11th. 4/20/26 JE ;; Perry cancelled scan on 3/10. Rescheduled for 4/23. Will still come in for other visits. 3/9/26 JE | E95: 46184 | F95: 46184 | G95: Scan:8:00am-9:00am | I95: IV 2/11: wants to do everything all day IV schedule in march | J95: 46091 | K95: 46091 | M95: Traveling to tj. Will be see by docs in feb and would like to program for march instead. 12/16/25 JE
A96: 46063 | B96: DBS-1019 | D96: CTS 2/17: Requested name change | E96: 46072 | F96: 46072 | G96: Scan:8:00am-9:00am | I96: IV 1/5: everything same day | J96: 46072 | K96: 46072 | M96: Left vm. Called back. Martes oh Jueves pref. 12/17/25 JE
A97: 46064 | B97: DBS-1039 | D97: JE Called in to reschedule. Moved from feb 13 to feb 5th. 1/15/26 | E97: 46058 | F97: 46058 | G97: Scan:8:00am-9:00am | I97: MJ 01/02: Driving | J97: 46077 | K97: 46077 | M97: Request fri 12/23/25 JE ;; Left vm. 12/17/25 JE
A98: 46065 | B98: DBS-1030 | D98: Original BD: 04/13/2026 Redraw: 06/01/26 ;; CTS 05/29/26: Coming in for blood draw again; per Borzage/Harrington request MJ 02/26: Pt called in and scheduled for Apr CTS 02/26: Called, left VM, text CTS 02/19: Contacted, left vm/text to offer new dates CTS 02/16: LABS ORDERED, keep until next visit (per IV) Called, had been sick all weekend and can't make it tomorrow | E98: 46125 | F98: 46125 | G98: Scan:8:00am-9:00am | I98: MJ 02/23: Left VM + sent text MJ 01/13: Doing all in one day Uber needed MJ 01/02: Would like a call back after the 7th | J98: 46125 | K98: 46125 | M98: Uber will be needed. 12/17/25 | Q98: 10
A99: 46082 | B99: DBS-1071 | D99: IV 1/5: confirm whether shes driving or ubering | E99: 46083 | F99: 46083 | G99: Scan:8:00am-9:00am | I99: IV 1/5: doing np, cv diff day | J99: 46092 | K99: 46092 | M99: IV 1/6: will do mri/bd its own day | P99: Email out jan
A100: 46082 | B100: DBS-0876 | D100: DROPPED JAN 2026 ;; No answer. No reply to text. 1/29/26 JE ;; Did not reply to my last text. Left vm. 1/27/26 JE ;; Left vm and sent text. Replied that she wants an open MRI... may drop out :( convo open trhough text... 1/21/26 JE ;; Left vm. 1/14/26 JE | I100: JE | M100: JE
...

Sheet 4th Yr Scheduling Notes
D1: NP + CV + BD Visits | J1: Thank you cards prepped up to 8/21/26 : NC
A2: Month | B2: ID | D2: NP/CV Scheduling Notes | E2: NP Date | F2: CV Date | G2: BD Date | I2: Thank you Card?
A3: 46143 | B3: DBS-0044 | C3: MJ | D3: MJ 04/06: Left VM + sent text | E3: 46154 | F3: 46154 | G3: 46154 | H3: IV 4/1: sent
A4: 46143 | B4: DBS-0322 | C4: MJ | D4: MJ 05/04: New dates pending,,pt had to reschedule MJ 04/15: uber needed, new address on red cap MJ 04/06: Left VM + sent text | E4: 46160 | F4: 46160 | G4: 46160
A5: 46143 | B5: DBS-0007 | C5: IV | D5: IV 5/4: needs uber, pending confirmation with dr. h | E5: 46150 | F5: 46150 | G5: 46150
A6: 46143 | B6: DBS-0053 | C6: JE | D6: Returns from mex tomorrow. Set for all visits in one day. 5/19/26 JE ;; Left vm. 5/13/26 JE ;; Out of the country. Requested call back in about two weeks. 4/23/26 JE | E6: 46181 | F6: 46181 | G6: 46181 | I6: TRUE
A7: 46143 | B7: DBS-0169 | C7: IV | D7: husband - Scheduled with his wife. Coming in same day/time. 4/23/26 JE | E7: 46169 | F7: 46169 | G7: 46169 | I7: TRUE
A8: 46143 | B8: DBS-0073 | C8: JE | D8: wife - Coming in with husband same day/time. 4/23/26 JE | E8: 46169 | F8: 46169 | G8: 46169 | I8: TRUE
A9: 46174 | B9: DBS-0360 | C9: MJ | D9: MJ 05/05:Driving | E9: 46174 | F9: 46174 | G9: 46174 | H9: MJ 5/5:Sent | I9: TRUE
A10: 46174 | B10: DBS-0054 | C10: MJ | D10: MJ 05/05: Uber needed | E10: 46177 | F10: 46177 | G10: 46177 | I10: TRUE
A11: 46174 | B11: DBS-0154 | C11: MJ | D11: Dr.H cancelled CV. Pt notified and offered full reschedule or to return for CV another day. She would like to keep BD and NP and schedule a new date for CV. Let her know that MJ will be in touch. 6/12/26 JE ;; MJ 05/05: Left vm + sent text | E11: 46189 | F11: 46202 | G11: 46189 | I11: TRUE
A12: 46174 | B12: DBS-0221 | C12: MJ | D12: MJ 05/11: Driving MJ 05/05: Left vm + sent text | E12: 46196 | F12: 46196 | G12: 46196
A13: 46174 | B13: DBS-0008 | C13: JE | D13: Will need Uber. 4/29/26 JE ;; Left vm. 4/23/26 JE | E13: 46176 | F13: 46176 | G13: 46176 | I13: TRUE
A14: 46174 | B14: DBS-0235 | C14: JE | D14: Reminder text sent. Participant cancelled - asked for Saturdays. Let him know only mon-fri. Only other day he can come in is next week the 11th. 5/29/26 JE ;; Coming from th OC. 4/23/26 JE | E14: 46184 | F14: 46184 | G14: 46184 | I14: TRUE
A15: 46174 | B15: DBS-0299 | C15: JE | D15: Will drive. 4/23/26 JE | E15: 46182 | F15: 46182 | G15: 46182 | I15: TRUE
A16: 46174 | B16: DBS-0063 | C16: JE | D16: Left vm. 4/23/26 JE | E16: 46183 | F16: 46183 | G16: 46183 | I16: TRUE
A17: 46204 | B17: DBS-0180 | C17: MJ | D17: MJ 07/08: Pt had to reschedule his BD & CV MJ 06/22:uber needed, doing NP one day and then CV/BD the followng wk MJ 06/02: Left VM + sent text | E17: 46210 | F17: 46231 | G17: 46231 | H17: MJ 6/2: Sent | I17: TRUE
A18: 46204 | B18: DBS-0028 | C18: MJ | D18: IV 9/16: sent follow up , left vm IV 9/9: sent follow up to confirm lunes as early as possible... 8:30am?... Tentative date set up - I let him know I would confirm w/ MJ to make sure date/time work ok. Needs follow up text with confirmation details 8/28/26 JE ;; He answered and shared he is still interested just very busy with work but will call back to set up new date. 8/24/26 JE ;; MJ 08/05: Letter sent via mail No answer. Sent text. 8/4/26 JE ;; No answer. 7/29 JE ;; MJ 07/13: Pt no showed,,unresponsive to texts + calls MJ 06/22: pt had to reschedule,,moved it to 07/13 MJ 06/02: May or may not need uber | E18: 46286 | F18: 46286 | G18: 46286 | I18: TRUE
A19: 46204 | B19: DBS-0349 | C19: JE | D19: Rescheduled. Will be seen July 24th instead. 7/13/26 JE ;; Had lost his phone. Still intrested. Scheduled all visits one day. 6/25/26 JE ;; Could not leave vm, sent text + email,,response pending. MJ 06/22 ;; No answer. Sent text. 6/15/26 JE ;; No answer. No vm. WIll try again. 6/12/26 JE | E19: 46227 | F19: 46227 | G19: 46227 | I19: TRUE
A20: 46204 | B20: DBS-0430 | C20: JE | D20: No show on 7/15/26 but answered call and rescheduled JE ;; Texted back saying she has to go out of country for emergency but will be back Monday night. Rescheduling 7/9 visit to 7/15. 7/6/26 JE ;; Left message w/ sister. 6/12/26 JE | E20: 46230 | F20: 46230 | G20: 46230 | I20: TRUE
A21: 46241 | B21: DBS-0502 | C21: IV | D21: IV 8/6: traveling, reserving potential date, call 8/17 to confirm if still possible IV 7/22: left vm, sent text, followed up via text, date pending | E21: 46258 | F21: 46258 | G21: 46258 | H21: MJ 7/1: Sent | I21: TRUE
A22: 46235 | B22: DBS-0442 | C22: IV | D22: IV 9/25: rescheduled IV 8/13: rescheduled, IV 7/22: will drive | E22: 46311 | F22: 46311 | G22: 46311 | I22: TRUE
A23: 46235 | B23: DBS-0199 | C23: IV | D23: IV 7/22: will drive | E23: 46255 | F23: 46255 | G23: 46255 | I23: TRUE
A24: 46235 | B24: DBS-0429 | C24: IV | D24: IV 7/13: rescheduled Dr. H unavailableIV 7/22: will drive | E24: 46245 | F24: 46245 | G24: 46245 | I24: TRUE
A25: 46235 | B25: DBS-0381 | C25: IV | D25: IV 8/14: needs to reschedule due to dr. app, IV 7/21: needs uber, all in 1 day | E25: 46253 | F25: 46253 | G25: 46253 | H25: *have him sign front page of DE4 consent | I25: TRUE
A26: 46235 | B26: DBS-0450 | C26: JE | D26: Will need Uber. 7/9/26 JE ;; Left vm. 7/7/26 JE | E26: 46261 | F26: 46261 | G26: 46261 | I26: TRUE
A27: 46235 | B27: DBS-0586 | C27: JE | D27: All day visit. Needs uber. De4 pt. 7/7/26 JE | E27: 46234 | F27: 46234 | G27: 46234 | I27: TRUE
A28: 46235 | B28: DBS-0499 | C28: JE | D28: Wants erliest visit. 7/7/26 JE | E28: 46240 | F28: 46240 | G28: 46240 | I28: TRUE
A29: 46235 | B29: DBS-0139 | C29: MJ | D29: MJ 08/04: Sent text MJ 07/07: Call couldn't go through + sent text | E29: 46252 | F29: 46252 | G29: 46252 | I29: TRUE
A30: 46235 | B30: DBS-0404 | C30: IV | D30: MJ 08/04: Left VM +sent text MJ 07/07: Left VM + sent text | E30: 46252 | F30: 46252 | G30: 46252 | I30: TRUE
A31: 46235 | B31: DBS-0512 | C31: MJ | D31: MJ 07/07: Driving | E31: 46245 | F31: 46245 | G31: 46245 | I31: TRUE
A32: 46235 | B32: DBS-0432* | C32: MJ | D32: MJ 07/07: Left VM + sent text | E32: 46237 | F32: 46216 | G32: 46237 | I32: TRUE
A33: 46266 | B33: DBS-0676 | C33: IV | D33: IV 9/3: will drive | E33: 46294 | F33: 46294 | G33: 46294 | H33: MJ 8/4: Sent | I33: TRUE
A34: 46266 | B34: DBS-0772 | C34: IV | D34: IV 9/3: called back,needs uber left vm, sent text | E34: 46289 | F34: 46282 | G34: 46282 | I34: TRUE
A35: 46266 | B35: DBS-0830 | C35: IV | D35: IV 9/3: will drive | E35: 46300 | F35: 46300 | G35: 46300 | I35: TRUE
A36: 46296 | B36: DBS-0613 | C36: IV | D36: IV 9/16: needs uber | E36: 46296 | F36: 46296 | G36: 46296 | H36: IV 9/4: Sent | I36: TRUE
A37: 46296 | B37: DBS-0620 | C37: IV | D37: IV 9/16: left vm, sent text | I37: FALSE
A38: 46296 | B38: DBS-0055 | C38: IV | D38: IV 9/17: needs uber IV 9/16: wants a call back later | E38: 46303 | F38: 46303 | G38: 46303 | I38: TRUE
A39: 46296 | B39: DBS-0569 | C39: IV | D39: IV 9/16: will drive | E39: 46301 | F39: 46301 | G39: 46301 | I39: TRUE
A40: 46296 | B40: DBS-0745 | C40: IV | D40: IV 9/16: will drive | E40: 46321 | F40: 46321 | G40: 46321 | I40: FALSE
A41: 46296 | B41: DBS-0587 | C41: IV | D41: IV 9/16: needs uber | E41: 46314 | F41: 46314 | G41: 46314 | I41: FALSE
A42: 46296 | B42: DBS-0599 | C42: IV | D42: IV 9/16: couldnt leave vm, sent text | I42: FALSE
A43: 46296 | B43: DBS-0657 | C43: IV | D43: IV 9/16: will drive | E43: 46322 | F43: 46322 | G43: 46322 | I43: FALSE
A44: 46327 | B44: DBS-0741
A45: 46327 | B45: DBS-0216
A46: 46327 | B46: DBS-0693
A47: 46327 | B47: DBS-0418
A48: 46327 | B48: DBS-0790
A49: 46327 | B49: DBS-0658
A50: 46327 | B50: DBS-0652
A51: 46327 | B51: DBS-0855
A52: 46357 | B52: DBS-0805
A53: 46357 | B53: DBS-0824
A54: 46357 | B54: DBS-0818
A55: 46357 | B55: DBS-0614
... A58: 46357 | B58: DBS-0884
A106: 46113 | B106: DBS-1085 | D106: IV
A107: 46114 | B107: DBS-1059 | D107: IV
A108: 46115 | B108: DBS-0969 | D108: MJ
A109: 46116 | B109: DBS-1076 | D109: MJ
A110: 46117 | B110: DBS-1143 | D110: JE
A111: 46118 | B111: DBS-1142 | D111: JE
A112: 46119 | B112: DBS-1152 | D112: JE
A113: 46120 | B113: DBS-1119 | D113: MJ
A114: 46121 | B114: DBS-1106 | D114: JE
A115: 46122 | B115: DBS-1134 | D115: IV

Sheet LabsMRNs
A1: DBS-ID | C1: MRN | D1: LAB DATE | E1: LABS YEAR | F1: LABS EMAILED/Texted | G1: LABS PRINTED | H1: MRI HCT | I1: notes
A2: DBS-0044 | B2: Yr 3 | C2: 004642687 | D2: 5/19/25 (MRI) 5/13/25 (Full Blood Panel) | E2: 3 | F2: 7/1 TB | G2: 6/30 NC | L2: last extract batch (to keckCap + eden HCT): 07/16/26 CTS/NC
A3: DBS-0007 | C3: 004636389 | D3: 5/22/25 (MRI) 5/19/25 (Full Blood Panel) | E3: 3 | F3: 7/1 TB | G3: 6/30 NC | L3: last extract batch: 9/2/26 NC
A4: DBS-0073 | C4: 004644039 | D4: 45807 | E4: 3 | F4: 7/1 TB | G4: 7/14 NC | H4: 45994 | I4: IV: won't find by name, search MRN for labs | L4: last batch sent to choo phei: 05/12/26 IV
A5: DBS-0169 | C5: 004644045 | D5: 45807 | E5: 3 | F5: 7/1 IV | G5: 7/14 NC | H5: 45994
A6: DBS-0053 | C6: 004638839 | D6: 45778 | E6: 3 | F6: 7/1 TB | G6: 7/14 NC
A7: DBS-0322 | C7: 004656098 | D7: 45796 | E7: 3 | F7: 7/1 TB | G7: 6/30 NC
A8: DBS-0180 | C8: 004637725 | D8: 45810 | E8: 3 | F8: 7/1 TB | G8: 7/14 NC | I8: homo missing
A9: DBS-0360 | C9: 004679104 | D9: 45813 | E9: 3 | F9: 7/1 TB | G9: 6/30 NC
A10: DBS-0054 | C10: 004650371 | D10: 6/3/25 (MRI) 6/5/25 (Full Blood Panel) | E10: 3 | F10: 7/1 TB | G10: 6/30 NC
A11: DBS-0221 | C11: 004645187 | D11: 45818 | E11: 3 | F11: 7/1 TB | G11: 6/30 NC
A12: DBS-0154 | C12: 004645753 | D12: 45819 | E12: 3 | F12: 7/1 IV | G12: 6/30 NC
A13: DBS-0008 | C13: 004650185 | D13: 45824 | E13: 3 | F13: 7/1 TB | G13: 6/30 NC
A14: DBS-0235 | C14: 004687102 | D14: 45825 | E14: 3 | F14: 7/1 TB | G14: 6/30 NC
A15: DBS-0299 | C15: 004645198 | D15: 45826 | E15: 3 | F15: 7/1 TB | G15: 6/30 NC
A16: DBS-0063 | C16: 004642697 | D16: 45833 | E16: 3 | F16: 7/1 IV | G16: 6/30 NC
A17: DBS-0430 | C17: 004706666 | D17: 45848 | E17: 3 | F17: 7/14 NC | G17: 7/14 NC
A18: DBS-0028 | C18: 004673009 | D18: 45845 | E18: 3 | F18: 8/19 IV | G18: 8/26 NC
A19: DBS-0349 | C19: 004714516 | D19: 45853 | E19: 3 | F19: 8/19 IV | G19: 8/26 NC
A20: DBS-0432 | C20: 004701973 | D20: 45875 | E20: 3 | F20: 8/19 IV | G20: 8/26 NC | H20: 45953
A21: DBS-0502 | C21: 004917321 | D21: 45876 | E21: 3 | F21: 8/19 IV | G21: 8/26 NC
A22: DBS-0499 | C22: 004909760 | D22: 45876 | E22: 3 | F22: 8/19 IV | G22: 8/26 NC
A23: DBS-0586 | C23: 004908823 | D23: 45882 | E23: 3 | F23: 8/19 IV | G23: 8/26 NC
A24: DBS-0450 | C24: 004708391 | D24: 45883 | E24: 3 | F24: 8/19 IV | G24: 8/26 NC
A25: DBS-0442 | C25: 004915910 | D25: 45884 | E25: 3 | F25: 8/19 IV | G25: 8/26 NC
A26: DBS-0199 | C26: 004707670 | D26: 45884 | E26: 3 | F26: 8/19 IV | G26: 8/26 NC
A27: DBS-0429 | C27: 004908818 | D27: 45887 | E27: 3 | F27: 8/19 IV | G27: 8/26 NC
A28: DBS-0381 | C28: 004703184 | D28: 45890 | E28: 3 | F28: 10/7 IV | G28: 10/9 CT/IV
A29: DBS-0404 | C29: 004679101 | D29: 45897 | E29: 3 | F29: 10/7 IV | G29: 10/9 CT/IV
A30: DBS-0139 | C30: 004668960 | D30: 45897 | E30: 3 | F30: 10/7 IV | G30: 10/9 CT/IV
A31: DBS-0512 | C31: 004715631 | D31: 45897 | E31: 3 | F31: 10/7 IV | G31: 10/9 CT/IV | I31: homo missing
A32: DBS-0676 | C32: 004931245 | D32: 45925 | E32: 3 | F32: 9/25 IV | G32: 10/9 CT/IV | H32: 45951
A33: DBS-0772 | C33: 004943202 | D33: 45930 | E33: 3 | F33: 10/1 IV | G33: 10/9 CT/IV | H33: 45946
A34: DBS-0613 | C34: 004924505 | D34: 45932 | E34: 3 | F34: 10/7 IV | G34: 10/9 CT/IV | H34: 45968
A35: DBS-0620 | C35: 004921829 | D35: 45933 | E35: 3 | F35: 10/7 IV | G35: 10/9 CT/IV | H35: 45980
A36: DBS-0055 | C36: 004701983 | D36: 45933 | E36: 3 | F36: 10/7 IV | G36: 10/9 CT/IV | H36: 11/7/1015
A37: DBS-0745 | C37: 004937176 | D37: 45939 | E37: 3 | F37: 10/9 IV | G37: 10/9 CT/IV | H37: 45943
A38: DBS-0498 | C38: 004921821 | D38: 46045 | E38: 3 | F38: 2/23 IV | H38: 45944
A39: DBS-0587 | C39: 004926644 | D39: 45946 | E39: 3 | F39: 11/6 AM | G39: 10/24 CT | H39: 45978
A40: DBS-0599 | C40: 004933057 | D40: 45950 | E40: 3 | F40: 11/6 AM | G40: 10/24 CT | H40: 45979
A41: DBS-0657 | C41: 004934448 | D41: 45951 | E41: 3 | F41: 11/6 AM | G41: 10/24 CT | H41: 45979
A42: DBS-0715 | C42: 004940134 | D42: 46083 | E42: 3 | H42: 45957
A43: DBS-0741 | C43: 004940118 | D43: 45971 | E43: 3 | F43: 2/20 CTS | G43: 1/16/26 NC | H43: 45958 | I43: CTS 02/20/26: email bounced back
A44: DBS-0924 | C44: 004970268 | D44: 46050 | E44: 3 | H44: 45965
A45: DBS-0693 | C45: 004942470 | D45: 45975 | E45: 3 | F45: 12/2 IV | G45: 1/16/26 NC | H45: 45971
A46: DBS- 0216 | C46: 004905244 | D46: 45971 | E46: 3 | F46: 02/20 CTS | G46: 1/16/26 NC | H46: 46006
A47: DBS-0830 | C47: 004958233 | D47: 45995 | E47: 3 | F47: 2/23 IV | G47: 1/16/26 NC | H47: 45972
A48: DBS-0855 | C48: 004956010 | D48: 45981 | E48: 3 | F48: 2/23 IV | G48: 1/16/26 NC | H48: 45972
A49: DBS-0658 | C49: 004936174 | D49: 45972 | E49: 3 | F49: 2/23 IV | G49: 1/16/26 NC | H49: 45981
A50: DBS-0790 | B50: Yr 3 | C50: 004954565 | D50: 45978 | E50: 3 | F50: 12/17 IV | G50: 1/16/26 NC | H50: 45985
A51: DBS-0824 | B51: Yr 3 | C51: 004966059 | D51: 46003 | E51: 3 | F51: 12/17 IV | G51: 1/16/26 NC | H51: 45985
A52: DBS-0652 | B52: Yr 3 | C52: 004949617 | D52: 45996 | E52: 3 | F52: 2/23 IV | G52: 1/16/26 NC | H52: 45996 | I52: missing hct, accession didnt include
A53: DBS-0800 | B53: Yr 3 | C53: 004953196 | D53: 46014 | F53: 2/23 IV | G53: 1/16/26 NC | H53: 46002
A54: DBS-0884 | B54: Yr 3 | C54: 004962959 | D54: 46010 | E54: 3 | F54: need to text | G54: 1/16/26 NC | H54: 46010 | I54: MJ: he would like his results mailed
A55: DBS-0653 | B55: Yr 3 | C55: 004949596 | D55: 46013 | E55: 3 | F55: 2/23 IV | G55: 1/16/26 NC | H55: 46013
A56: DBS-0614 | B56: Yr 3 | C56: 004914276 | D56: 46010 | F56: 2/23 IV | G56: 1/16/26 NC | H56: 46013
A57: DBS-0805 | B57: Yr 3 | C57: 004963046 004949596 | D57: 46027 | F57: 2/23 IV | G57: 1/16/26 NC | H57: 46027
A58: DBS-1016 | B58: Yr 3 | C58: 004990125 | D58: 45663 | F58: 1/13 IV :sent via text | G58: 1/16/26 NC | H58: 45663
A59: DBS-0935 | B59: Yr 3 | C59: 004978021 | D59: 46029 | F59: 2/23 IV | G59: 1/16/26 NC | H59: 46029
A60: DBS-0818 | B60: Yr 3 | C60: 004965602 | D60: 46031 | F60: 2/23 IV | G60: 1/16/26 NC | H60: 46031 | I60: Would like his results mailed (Lab results and CD)
A61: DBS-0418 | B61: Yr 3 | C61: 004702846 | D61: 46034 | F61: 2/23 IV | G61: 1/16/26 NC | H61: 46034 | I61: duplicate got full bd done twice 10/23/25
A62: DBS-0879 | B62: Yr 3 | C62: 004962321 | D62: 46036 | F62: 2/23 IV | G62: 1/16/26 NC | H62: 46036 | I62: wants mri cd
A63: DBS-0987 | B63: Yr 3 | C63: 004987460 | D63: 46037 | F63: 2/23 IV | G63: 1/16/26 NC | H63: 46037
A64: DBS-0838 | B64: Yr 3 | C64: 004963006 | D64: 46043 | F64: 2/23 IV | G64: 02/20/26 CTS | H64: 46043
A65: DBS-0617 | B65: Yr 3 | C65: 004961390 | D65: 46043 | F65: 2/23 IV | G65: 02/20/26 CTS | H65: 46043
A66: DBS-0763 | B66: Yr 3 | C66: 004957431 | D66: 46052 | F66: 2/23 IV | G66: 02/20/26 CTS | H66: 46052
A67: DBS-0971 | B67: Yr 3 | C67: 004995961 | D67: 46055 | F67: 2/23 IV | G67: 02/20/26 CTS | H67: 46055
A68: DBS-1000 | B68: Yr 3 | C68: 004994468 | D68: 46055 | F68: 2/23 IV | G68: 02/20/26 CTS | H68: 46055 | I68: Wants MRI CD
A69: DBS-0956 | B69: Yr 3 | C69: 004978855 | D69: 46056 | F69: 2/23 IV | G69: 02/20/26 CTS | H69: 46056
A70: DBS-0771 | B70: Yr 3 | C70: 004941608 | D70: 46057 | F70: 2/23 IV | G70: 02/20/26 CTS | H70: 46057 | I70: Wants MRI CD for Baseline and Y3
A71: DBS-0918 | B71: Yr 3 | C71: 004968944 | D71: 46057 | F71: 2/23 IV | G71: 02/20/26 CTS | H71: 46057
A72: DBS-1039 | B72: Yr 3 | C72: 004993544 | D72: 46058 | F72: 2/23 IV | G72: 02/20/26 CTS | H72: 46058
A73: DBS-0789 | B73: Yr 3 | C73: 004964518 | D73: 46059 | F73: 2/23 IV | G73: 02/20/26 CTS | H73: 46059 | I73: Wants MRI CD,,will give results + MRI CD at next visit 02/25/26
A74: DBS-0770 | B74: Yr 3 | C74: 004965035 | D74: 46065 | F74: 2/23 IV | G74: 02/20/26 CTS | H74: 46065 | I74: Would like lab results through email,,Gave MRI CD
A75: DBS-0597 | B75: Yr 3 | C75: 004917580 | D75: 46071 | F75: 02/20 CTS: Sent via text | G75: 02/20/26 CTS | H75: 46071 | I75: Would like lab results through text, gave MRI CD at visit. CTS 02/18/26
A76: DBS-1019 | B76: Yr 3 | C76: 004990112 | D76: 46072 | F76: 2/23 IV | G76: 02/20/26 CTS | H76: 46072
A77: DBS-0982 | B77: Yr 3 | C77: 004982131 | D77: 46062 | F77: 2/23 IV | G77: 03/04/26 CTS | H77: 46062 | I77: Would like lab results texted
A78: DBS-0756 | B78: Yr 3 | C78: 004949610 | D78: 46077 | F78: 03/13 CTS | G78: 03/04/26 CTS
A79: DBS-1071 | B79: Yr 3 | C79: 005008512 | D79: 46083 | F79: 3/11 IV | G79: 03/04/26 CTS | H79: 46083 | I79: Would like lab results through text,,Gave MRI CD
A80: DBS-1008 | B80: Yr 3 | C80: 004990118 | D80: 46084 | F80: 03/13 CTS | G80: 03/04/26 CTS | H80: 46084 | I80: Would like lab results through email ,,Gave MRI CD
A81: DBS-1047 | B81: Yr 3 | C81: 004990123 | D81: 46084 | F81: 03/13 CTS | G81: 03/04/26 CTS | H81: 46084 | I81: Would like lab results through email,Gave MRI CD
A82: DBS-0940 | B82: Yr 3 | C82: 004993538 | D82: 46085 | F82: 05/18 CTS | G82: 04/29 CTS | H82: 46085 | I82: Would like lab results through text
A83: DBS-0981 | B83: Yr 3 | C83: 004981164 | D83: 46044 | F83: 05/18 CTS | G83: 04/29 CTS | H83: 46044 | I83: never added
A84: DBS-0569 | B84: Yr 3 | C84: 004928979 | D84: 45937 | F84: 05/18 CTS | G84: 04/29 CTS | H84: 45987 | I84: never added
A85: DBS-0878 | B85: Yr 3 | C85: 004972534 | D85: 46052 | F85: 05/18 CTS | G85: 04/29 CTS | H85: 46052
A86: DBS-1076 | B86: Yr 3 | C86: 005000165 | D86: 46113 | F86: 05/18 CTS | G86: 04/29 CTS | H86: 46113
A87: DBS-1119 | B87: Yr 3 | C87: 005012500 | D87: 46119 | F87: 05/18 CTS | G87: 04/29 CTS | H87: 46119 | I87: No MRI done
A88: DBS-1152 | B88: Yr 3 | C88: 005015777 | D88: 46120 | F88: 05/18 CTS | G88: 04/29 CTS | H88: 46120
A89: DBS-0822 | B89: Yr 3 | C89: 004962597 | D89: 46121 | F89: 05/18 CTS | G89: 04/29 CTS | H89: 46121 | I89: Would like lab results emailed; Would like MRI CD mailed as well CTS 04/09/26
A90: DBS-1030 | B90: Yr 3 | C90: 004994085 | D90: 06/01/26 04/13/26 | F90: 06/05/26 CTS | G90: 04/29 CTS | H90: 46125 | I90: CTS 05/29: Labs to be done again 06/01/26 Would like lab results through email//new email on Redcap ,CTS will mail out MRI disc
A91: DBS-1106 | B91: Yr 3 | C91: 005009558 | D91: 46120 | F91: 05/18 CTS | G91: 04/29 CTS | H91: 46120 | I91: MRI Completed 05/18 CTS; was never added,,mri not completed
A92: DBS-1134 | B92: Yr 3 | C92: 005016186 | D92: 46127 | F92: 05/18 CTS | G92: 04/29 CTS | H92: 46127
A93: DBS-1263 | B93: Yr 3 | C93: 005040451 | D93: 46142 | F93: 05/18 CTS | G93: 05/14/26 CTS | H93: 46142 | I93: hemolyzed no homo, K+
A94: DBS-1246 | B94: Yr 3 | C94: 005031988 | D94: 46143 | F94: 05/18 CTS | G94: 05/14/26 CTS | H94: 46143
A95: DBS-1167 | B95: Yr 3 | C95: 005022129 | D95: 46146 | F95: 05/18 CTS | G95: 05/14/26 CTS | H95: 46146 | I95: Would like labs and scans - CTS 05/04/26
A96: DBS-1276 | B96: Yr 3 | C96: 005039652 | D96: 46147 | F96: 05/18 CTS | G96: 05/14/26 CTS | H96: 46147 | I96: Would like labs and scans - CTS 05/04/26
A97: DBS-0916 | B97: Yr 3 | C97: 004972713 | D97: 46148 | F97: 05/18 CTS | G97: 05/14/26 CTS | H97: 46148
A98: DBS-1079 | B98: Yr 3 | C98: 005005747 | D98: 46148 | F98: 05/18 CTS | G98: 05/14/26 CTS | H98: 46148 | I98: No MRI done,,would like results via email-MJ
A99: DBS-1190 | B99: Yr 3 | C99: 005028791 | D99: 46149 | F99: 05/18 CTS | G99: 05/14/26 CTS | H99: 46149 | I99: MRI disc will be mailed bc Perry is out of CDs atm,,would like blood results
A100: DBS-0007 | B100: Yr 4 | C100: 004636389 | D100: 46150 | F100: 05/29/26 CTS | G100: 05/14/26 CTS
...

Sheet ClinCard
A1: Note: Baseline/2nd yr columns hidden, click + above to view | E1: Baseline | S1: Year 2 | W1: Year 3 | AD1: Year 4
A2: ID | B2: Card Number/Token # | C2: Expiration Date | E2: Date Requested | F2: Staff Requesting | G2: General Notes | H2: Participant Registered on ClinCard? (Y/N) | I2: Card Registered on ClinCard? (Y/N) | J2: Mailed or Given? Date? | K2: Screening Visit | L2: BD Credited? | M2: MRI Credited? | N2: NP Credited? | O2: LP Credited? (optional) | P2: CV Credited? | Q2: Travel Expense Mileage Rate = Roundtrip Miles * 0.70 Mileage cutoff for $50 is 38 miles (oneway) or 76 miles (roundtrip) | S2: Year 2 CV | T2: Year 2 NP | U2: Travel Expense Mileage Rate = Roundtrip Miles * 0.725 Mileage cutoff for $50 is 38 miles (oneway) or 76 miles (roundtrip) | W2: Year 3 BD | X2: Year 3 CV | Y2: Year 3 NP | Z2: Year 3 MRI | AA2: Travel Expense Mileage Rate = Roundtrip Miles * 0.725 Mileage cutoff for $50 is 38 miles (oneway) or 76 miles (roundtrip) | AB2: Notes | AD2: Year 4 BD | AE2: Year 4 CV | AF2: Year 4 NP | AG2: Travel Expense Mileage Rate = Roundtrip Miles * 0.725 Mileage cutoff for $50 is 38 miles (oneway) or 76 miles (roundtrip) | AH2: Notes
A3: DBS-0075 | B3: 5462689027584952 | C3: 45284 | E3: 44932 | F3: LC | H3: Y | I3: Y | J3: Given | K3: 25 | AJ3: Mileage Compensation Calculator
A4: DBS-0073 | B4: NEW: 15039498 14854855; 5462689024367617 | C4: 45774 | E4: 44937 | F4: LC | G4: GT 9/18: Informed $150 added to card for MRI +gas; GT 6/12: Participant informed $100 added for NP&CV | H4: Y | I4: Y | J4: Given | K4: 25 | L4: 25 | M4: 100 | N4: 50 | O4: Opt Out | P4: 50 | Q4: 50 - 4 (09/08/23) | S4: 50 | T4: 50 | U4: 50 - (06/28/24) | W4: 25 | X4: 50 | Y4: 50 | Z4: 100 | AA4: 50 (12/03/25) | AD4: 25 | AE4: 50 | AF4: 50 | AG4: 50 (5/27/26) | AJ4: Enter Miles One-way : | AK4: 14
A5: DBS-0008 | B5: NEW:45641655 NEW: 55015318 5462 6890 2414 4115: new card: 14297481 | C5: 04/27 6/24; 11/25 | E5: 44943 | F5: LC | G5: GT 5/25: Participant informed $100 included for NP & CV;LC 02/27: Participant lost her clincard. Will provide a new one in next visit scheduled for 03/21 | H5: Y | I5: Y | J5: Given | K5: 25 | L5: 25 | M5: 100 | N5: 50 | O5: 100 | P5: 50 | S5: 50 | T5: 50 | W5: 25 | X5: 50 | Y5: 50 | Z5: 100 | AA5: Uber | AB5: new card | AD5: 25 | AE5: 50 | AF5: 50 | AH5: uber/ new card | AJ5: Total Compensation: | AK5: =IF(AK4="","",ROUND(AK4*2*0.725,2)) -> 20.3
A6: DBS-0154 | B6: NEW: 95641903 5462689024430894; new card: 94302271 | C6: 10/28; 6/24; 11/25 | E6: 44946 | F6: LC | G6: GT 8/1: Informed $100 added for MRI; GT 6/6: Participant informed $100 included for NP & CV; LC 02/27: Participant lost her clincard. Will email new clinicard to home adress | H6: Y | I6: Y | J6: Given | K6: 25 | L6: 25 | M6: 100 | N6: 50 | O6: Opt Out | P6: 50 | Q6: 30.13 (06/06/23) | S6: 50 | T6: 50 | U6: 30.82 (06/17/24) | W6: 25 | X6: 50 | Y6: 50 | Z6: 100 | AA6: 30.82 (6/11/25) | AD6: 25 | AE6: 50 | AF6: 50 | AG6: 34.37 (6/29/26)
A7: DBS-0063 | B7: new card: 75046327 5462689024384497; 85028913 | C7: 6/24/2023; 04/27 | E7: 44949 | F7: LC | G7: 8/1 GT: Informed $150 added for NP & LP; 7/31 GT: Informed $147.16 added for MRI + gas | H7: Y | I7: Y | J7: Given | K7: 25 | L7: 25 | M7: 100 | N7: 50 | O7: 100 | P7: 25 | Q7: 47.16 - (07/31/23) | S7: 50 | T7: 50 | U7: $48.24 (6/06/24) | W7: 25 | X7: 50 | Y7: 50 | Z7: 100 | AA7: 50 (6/25/25) | AD7: 25 | AE7: 50 | AF7: 50 | AG7: 50 (6/10/26) | AJ7: NOT PAID
A8: DBS-0139 | B8: 55025512 64878310 | C8: 45774 | E8: 44965 | F8: GT | G8: GT 8/24: New card given, $106.68 added for MRI +gas; GT 5/8: New card given, informed active | H8: Y | I8: Y | J8: Given | K8: 25 | L8: 25 | M8: 100 | N8: 50 | O8: Opt Out | P8: 50 | Q8: 6.68 - (8/24/23) | S8: 50 | T8: 50 | U8: 6.83 (06/19/24) | W8: 25 | X8: 50 | Y8: 50 | Z8: 100 | AA8: 6.83 (8/20/25) | AD8: 25 | AE8: 50 | AF8: 50 | AG8: 7.25 (8/18/26) | AJ8: PAID
A9: DBS-0044 | B9: NEW : 74999471 5462689024244485 | C9: 45743 | E9: 44966 | F9: LC | G9: GT 6/8: Participant informed $100 included for MRI; LC 04/21: Can we re-compensate for BD since they dispatched the first one? | H9: Y | I9: Y | J9: Given | K9: 25 | L9: 25 | M9: 100 | N9: 50 | O9: Opt Out | P9: 50 | S9: 25 | T9: 50 | W9: 25 | X9: 50 | Y9: 50 | Z9: 100 | AB9: new card | AD9: 25 | AE9: 50 | AF9: 50 | AH9: UBER | AJ9: UNSURE
A10: DBS-0119 | B10: 5462 6890 2348 6988 | C10: 45101 | E10: 44970 | F10: LC | G10: LC 03/27: Participant came to initial visit but decided to no longer continue. Asked about clincard but declined compensation. | H10: N | I10: N | J10: Given | K10: 25 | AJ10: NEEDS ATTENTION
A11: DBS-0183 | B11: 5462689027601913 | C11: 45284 | E11: 44973 | F11: GT | H11: Y | I11: Y | J11: Given | K11: 25 | L11: 25 | M11: 100 | N11: 50 | O11: Opt Out | P11: 50 | S11: 25 | T11: 50
A12: DBS-0028 | B12: 94318240 | C12: 45255 | E12: 44974 | F12: GT | G12: GT 9/29: Informed $124.89 added for MRI & gas; GT 5/4: Replaced previous card | H12: Y | I12: Y | J12: Given | K12: 25 | L12: 25 | M12: 100 | N12: 50 | O12: Opt Out | P12: 50 | Q12: 24.89 (9/29/23) | S12: 50 | T12: 50 | W12: 25 | X12: 50 | Y12: 50 | Z12: 100 | AJ12: Pre-Screening (Full) | AK12: 50
A13: DBS-0131 | B13: 5462689024198988 | C13: 45101 | E13: 44987 | F13: GT | H13: Y | I13: Y | J13: Given | K13: 25 | L13: 25 | S13: 50 | T13: 50 | AJ13: Pre-Screening (Short) | AK13: 25
A14: DBS-0007 | B14: NEW Card: 35650368 64308753 | C14: 46323 | E14: 45040 | F14: GT | G14: 7/28 GT: Informed 100 for MRI; 5/12 GT informed of money from LP and NP ( Has card 84313418 in case cant find original) 4/24: Card given during CV; Card not given. Waiting for DBS clincards to come in | H14: Y | I14: Y | J14: Given | K14: 25 | L14: 25 | M14: 100 | N14: 50 | O14: 100 | P14: 25 | S14: 25 | T14: 50 | W14: 25 | X14: 50 | Y14: 50 | Z14: 100 | AD14: 25 | AE14: 50 | AF14: 50 | AH14: uber/ new card | AJ14: Baseline Medical Exam | AK14: 25
A15: DBS-0180 | B15: NEW: 75647106 NEW CARD:64996574 5462689026916569 | C15: 45284 | E15: 44992 | F15: LC | G15: GT 8/16: Informed $100 added for MRI; GT 6/22: Participant informed $75 added for CV and gas; GT 5/31: Participant informed $150 added for NP & LP | H15: Y | I15: Y | J15: Given | K15: 25 | L15: 25 | M15: 100 | N15: 50 | O15: 100 | P15: 25 | Q15: 50 - (03/07/23) | S15: 50 | T15: 50 | W15: 25 | X15: 50 | Y15: 50 | Z15: 100 | AA15: New Card:64996574/MAILED OUT ON 06/05/25 | AD15: 25 | AE15: 50 | AF15: 50 | AH15: Uber/new card | AJ15: Baseline NP | AK15: 50
A16: DBS-0053 | B16: 5462689026984930 New CARD: 95027635 NEW CARD: 35494987 | C16: 4/24/2025 05/28 | E16: 44995 | F16: LC | G16: 9/30/25 JE: Participant informed total balance $214. New card given in person. ;; 6/12 GT: Participant informed $100 added for MRI; 5/19 GT: Participant informed $75 added for NP & CV | H16: Y | I16: Y | J16: Given | K16: 25 | L16: 25 | M16: 100 | N16: 50 | O16: Opt Out | P16: 25 | S16: 25 | T16: 50 | W16: 25 | X16: 50 | Y16: 50 | Z16: 100 | AA16: NEW CARD: 35494987 | AD16: 25 | AE16: 50 | AF16: 50 | AH16: Uber | AJ16: Baseline Blood Draw | AK16: 25
A17: DBS-0212 | B17: 5462688013090693 | C17: 45255 | E17: 45001 | F17: LC | H17: Y | I17: Y | J17: Given | K17: 25 | AJ17: Baseline MRI | AK17: 100
A18: DBS-0242 | B18: 5462688013271103 | C18: 45255 | E18: 44999 | F18: GT | H18: Y | I18: Y | J18: Given | K18: 25 | AJ18: Baseline LP (Optional) | AK18: 100
A19: DBS-0128 | B19: 14317300 | C19: 45255 | E19: 45002 | F19: LC | H19: Y | I19: Y | J19: Given | K19: 25 | Q19: 50 - Lead no longer answered phone
A20: DBS-0169 | B20: NEW: 75015660 74850904; 44308551 | C20: 45774 | E20: 45005 | F20: LC | G20: GT 9/18: Informed $150 added to card for MRI +gas; GT 6/12: Participant informed $100 added for NP&CV | H20: Y | I20: Y | J20: Given | K20: 25 | L20: 25 | M20: 100 | N20: 50 | O20: Opt Out | P20: 50 | Q20: 50 - 3 (09/08/23) | S20: 50 | T20: 50 | U20: 50 - (06/28/24) | W20: 25 | X20: 50 | Y20: 50 | Z20: 100 | AA20: 50 (12/03/25) | AD20: 25 | AE20: 50 | AF20: 50 | AG20: 50 (5/27/26)
A21: DBS-0221 | B21: New card: 45016282; 94306214 | C21: 45255 | E21: 45007 | F21: GT | G21: Participant informed $100 added for LP; GT 5/31: Participant informed $125 added for NP,BD, and CV | H21: Y | I21: Y | J21: Given | K21: 25 | L21: 25 | M21: 100 | N21: 50 | O21: 100 | P21: 50 | Q21: 13.10 - (5/31/23) | S21: 50 | T21: 50 | U21: 13.4 (6/25/24) | W21: 25 | X21: 50 | Y21: 50 | Z21: 100 | AA21: 17.71 (06/11/25) | AB21: new card | AD21: 25 | AE21: 50 | AF21: 50 | AG21: 21.46 (06/23/26)
A22: DBS-0219 | B22: new card: 44852062; 14310870 | C22: 45255 | E22: 45008 | F22: LC | G22: GT 7/7: Participant informed $100 added for MRI; GT 5/10: Participant informed $75 added for NP &CV | H22: Y | I22: Y | J22: Given | K22: 25 | L22: 25 | M22: 100 | N22: 50 | O22: Opt Out | P22: 25 | S22: 50 | T22: 50 | U22: 37.52 (10/29/24) | V22: new card
A23: DBS-0061 | B23: 04292948 | C23: 45255 | E23: 45012 | F23: GT | H23: Y | I23: Y | J23: Given | K23: 25
A24: DBS-0299 | B24: NEW: 05630936 04297318 | C24: 45255 | E24: 45014 | F24: GT | G24: GT 6/9: Participant informed $125 added for NP,BD, & CV | H24: Y | I24: Y | J24: Given | K24: 25 | L24: 25 | M24: 100 | N24: 50 | O24: Opt Out | P24: 50 | Q24: 5.50 - (7/17/23) | S24: 50 | T24: 50 | U24: $6.03 (6/06/24) | W24: 50 | X24: 50 | Y24: 50 | Z24: 100 | AA24: 7.42 (6/10/25) | AD24: 25 | AE24: 50 | AF24: 50 | AG24: 7.69 (6/09/26) | AH24: New card
A25: DBS-0268 | B25: 64312498 | C25: 45255 | E25: 45015 | F25: LC | G25: GT 10/2: Informed $100 added for MRI; GT 5/10: Participant informed $50 added for NP | H25: Y | I25: Y | J25: Given | K25: 25 | L25: 25 | M25: 100 | N25: 50 | O25: Opt Out | P25: 50
A26: DBS-0054 | B26: 84306353 | C26: 45255 | E26: 45019 | F26: GT | H26: Y | I26: Y | J26: Given | K26: 25 | L26: 25 | M26: 100 | N26: 50 | O26: Opt Out | P26: 50 | S26: 50 | T26: 50 | W26: 25 | X26: 50 | Y26: 50 | Z26: 100 | AA26: Uber | AD26: 25 | AE26: 50 | AF26: 50 | AG26: Uber
A27: DBS-0322 | B27: NEW: 85654380 85037531 24287358 54863241 | C27: 46323 | E27: 45028 | F27: GT | G27: GT 7/19: Participant informed $100 added for MRI; GT 5/17: Participant informed $125 added for NP, BD, and CV | H27: Y | I27: Y | J27: Given | K27: 25 | L27: 25 | M27: 100 | N27: 50 | O27: 100 | P27: 50 | Q27: 19.65 - (4/12/23) | S27: 25 | T27: 50 | W27: 25 | X27: 50 | Y27: 50 | Z27: 100 | AB27: new card | AD27: 25 | AE27: 50 | AF27: 50 | AH27: new card
A28: DBS-0294 | B28: 64284516 | C28: 45255 | E28: 45035 | F28: GT | H28: Y | I28: Y | J28: Given | K28: 25
A29: DBS-0108 | B29: 34319219 | C29: 45255 | E29: 45037 | F29: LC | G29: GT 9/12: Participant informed $120.96 added for MRI and gas; GT 7/14: Participant informed $120.96 added for LP and gas; GT 6/23: Participant informed $141.92 added for NP,BD, & CV and gas | H29: Y | I29: Y | J29: Given | K29: 25 | L29: 25 | M29: 100 | N29: 50 | O29: 100 | P29: 25 | Q29: 20.96 (09/12/23)
A30: DBS-0010 | B30: 94305169 | C30: 45255 | E30: 45042 | F30: GT | H30: Y | I30: Y | J30: Given | K30: 25 | Q30: 3.93 - (4/26/23)
A31: DBS-0352 | B31: 34318060 | C31: 45255 | E31: 45048 | F31: LC | G31: GT 5/30: Participant informed $100 added for NP,BD, and CV; GT 5/10: Participant informed card active | H31: Y | I31: Y | J31: Given | K31: 25 | L31: 25 | M31: 100 | N31: 50 | O31: Opt Out | P31: 25 | Q31: 12.31 (10/30/23) | S31: 50 | T31: 50 | U31: 13.40 (06/03/24)
A32: DBS-0382 | B32: 34308135 | C32: 45255 | E32: 45050 | F32: LC | G32: GT 7/24: Participant informed $100 added for MRI; GT 5/19: Participant informed $100 added for NP,BD, and CV; GT 5/4: Participant informed card active | H32: Y | I32: Y | J32: Given | K32: 25 | L32: 25 | M32: 100 | N32: 50 | O32: Opt Out | P32: 25 | S32: 25 | T32: 50
A33: DBS-0013 | B33: New: 64870590 74302037 | C33: 45255 | E33: 45044 | F33: GT | G33: GT 8/8: Informed $102.62 added for MRI + gas; GT 6/14: Participant informed $125 added for NP,BD, and CV; GT 5/17: Participant informed $25 added for BD; GT 5/11 Need to send new card | H33: Y | I33: Y | J33: Given | K33: 25 | L33: 25 | M33: 100 | N33: 50 | O33: Opt Out | P33: 50 | Q33: 2.62 (8/8/23) | S33: 50 | T33: 50 | U33: 2.68 (08/12/24)
A34: DBS-0404 | B34: NEW: 75648458 74855396 | C34: 46323 | E34: 45056 | F34: GT | G34: GT 5/30: Participant informed $125 added for NP,BD, and CV; GT 5/10: Participant informed card active | H34: Y | I34: Y | J34: Given | K34: 25 | L34: 25 | M34: 100 | N34: 50 | O34: Opt Out | P34: 50 | Q34: 6.68 - (5/30/23) | S34: 50 | T34: 50 | U34: 6.83 (06/19/24) | W34: 25 | X34: 50 | Y34: 50 | Z34: 100 | AA34: 6.83 (8/28/25) | AD34: 25 | AE34: 50 | AF34: 50 | AG34: 7.25 (08/18/26) | AH34: new card
A35: DBS-0360 | B35: NEW: 95659693 74319160 | C35: 45255 | E35: 45056 | F35: GT | G35: GT 7/18: Participant informed $100 added for MRI; GT 6/1: Participant informed $150 added for NP&LP; GT 5/25: Participant informed $75 included for BD & CV; GT 5/10: Participant informed card active | H35: Y | I35: Y | J35: Given | K35: 25 | L35: 25 | M35: 100 | N35: 50 | O35: 100 | P35: 50 | S35: 50 | T35: 50 | W35: 25 | X35: 50 | Y35: 50 | Z35: 100 | AA35: 16.80 (6/5/25) | AD35: 25 | AE35: 50 | AF35: 50 | AG35: 16.80 (6/1/26)
A36: DBS-0235 | B36: 34864930; 04285594 | C36: 45255 | E36: 45069 | F36: LC | G36: GT 9/12: Informed $100 added for MRI; GT 6/19: Participant informed $100 added for BD, NP &CV; GT 5/24: Participant informed card active & $25 included for SV | H36: Y | I36: Y | J36: Given | K36: 25 | L36: 25 | M36: 100 | N36: 50 | O36: Opt Out | P36: 25 | S36: 50 | T36: 50 | W36: 25 | X36: 50 | Y36: 50 | Z36: 100 | AA36: Uber | AD36: 25 | AE36: 50 | AF36: 50 | AG36: Uber
A37: DBS-0339 | B37: 24291508 | C37: 45255 | E37: 45076 | F37: LC | G37: GT 5/30: Participant informed card active and $25 added for SV | H37: Y | I37: Y | J37: Given | K37: 25
A38: DBS-0379 | B38: NEW: 44857336 74313261 | C38: 45622 | E38: 45079 | F38: GT | G38: GT 9/21: Informed $100 added for MRI: GT 7/24: Participant informed $125 added for BD, NP &CV; GT 6/2: Participant informed $25 added for SV | H38: Y | I38: Y | J38: Given | K38: 25 | L38: 25 | M38: 100 | N38: 50 | O38: Opt Out | P38: 50 | S38: 50 | T38: 50
A39: DBS-0414 | B39: NEW: 24842638 74297611 | C39: new: 11/26 11/25 | E39: 45079 | F39: GT | G39: GT 9/21: Informed $100 added for MRI; GT 7/24: Participant informed $125 added for BD, NP &CV; GT 6/2: Participant informed $25 added for SV | H39: Y | I39: Y | J39: Given | K39: 25 | L39: 25 | M39: 100 | N39: 50 | O39: Opt Out | P39: 50 | S39: 50 | T39: 50
A40: DBS-0419 | B40: 74311938 | C40: 45255 | E40: 45079 | F40: LC | G40: GT 8/3: Participant informed $100 added for MRI; GT 6/16: Participant informed $100 added for BD, NP &CV; GT 6/2: Participant informed $25 added for SV | H40: Y | I40: Y | J40: Given | K40: 25 | L40: 25 | M40: 100 | N40: 50 | O40: Opt Out | P40: 25 | Q40: 28.82 - (06/02/23) | S40: 50 | T40: 50
A41: DBS-0345 | B41: 54307516 | C41: 45255 | E41: 45083 | F41: LC | G41: GT 6/8: Participant informed $25 added for SV | H41: Y | I41: Y | J41: Given | K41: 25
A42: DBS-0432 | B42: 45492949 14314647 | C42: 05/28 11/25/2023 | E42: 45096 | F42: GT | G42: JE 10/23 Participant lost card. New card given. GT 6/19: Participant informed $75 added for SV and Gas | H42: Y | I42: Y | J42: Given | K42: 25 | L42: 25 | M42: 100 | N42: 50 | P42: 50 | Q42: 50 - 7/25/23 | S42: 50 | T42: 50 | U42: 50 (7/29/24) | W42: 25 | X42: 50 | Y42: 50 | Z42: 100 | AA42: 50 (10/23/25) | AB42: JE 10/23/25: NEW CARD ;; IV 8/21: came for mri, got cancelled, did de4 | AD42: 25 | AE42: 50 | AF42: 50 | AG42: 50 (08/03/26) | AH42: Virtual CV
A43: DBS-0055 | B43: NEW CARD: 45649749 85489668 NEW CARD: 64875190 ;54310151 | C43: 46323 | E43: 45097 | F43: GT | G43: GT 9/22: Participant informed $103.93 added for MRI and gas; GT 7/31: Participant informed $128.93 added for BD,NP,CV and gas; GT 6/20: Participant informed $28.93 added for SV and gas | H43: Y | I43: Y | J43: Given | K43: 25 | L43: 25 | M43: 100 | N43: 50 | O43: Opt Out | P43: 50 | Q43: 3.93 - 7/31/23 | S43: 50 | T43: 50 | W43: 25 | X43: 50 | Y43: 50 | Z43: 100 | AA43: Uber | AD43: 25 | AE43: 50 | AF43: 50
A44: DBS-0381 | B44: NEW: 05644335 NEW: 35654159 24298743 | C44: 46323 | E44: 45097 | F44: LC | G44: 8/16 GT: Participant informed $100 added for MRI; GT 6/23: Participant informed $125 added for NP,BD, & CV; GT 6/20: Participant informed $25 added for SV | H44: Y | I44: Y | J44: Given | K44: 25 | L44: 25 | M44: 100 | N44: 50 | O44: Opt Out | P44: 50 | S44: 50 | T44: 50 | W44: 25 | X44: 50 | Y44: 50 | Z44: 100 | AA44: Uber | AB44: MJ 06/16: Called in and needs a new card | AD44: 25 | AE44: 50 | AF44: 50
A45: DBS-0430 | B45: NEW CARDS: 65638599 14307317 | C45: 46323 | E45: 45103 | F45: LC | G45: GT 9/12: Participant informed $100 added for MRI; GT 8/11: Participant informed $100 added for LP; GT 7/19: Participant informed $100 added for NP, BD, CV; GT 6/26: Participant informed $25 added for SV | H45: Y | I45: Y | J45: Given | K45: 25 | L45: 25 | M45: 100 | N45: 50 | O45: 100 | P45: 25 | Q45: 50 - (06/26/23) | S45: 50 | T45: 50 | W45: 25 | X45: 50 | Y45: 50 | Z45: 100 | AA45: Uber (8/11/25) | AD45: 25 | AE45: 50 | AF45: 50 | AG45: Uber | AH45: New card | AI45: n
A46: DBS-0450 | B46: NEW: 04848809; 64281281 | C46: 46353 | E46: 45106 | F46: GT | G46: GT 8/14: Participant informed $50 for NP; GT 8/7: Participant informed $75 added for CV and BD; GT 6/29: Participant informed $29.45 added for SV + gas | H46: Y | I46: Y | J46: GIven | K46: 25 | L46: 25 | M46: 100 | N46: 50 | O46: Opt Out | P46: 50 | Q46: 4.45 - (06/29/23) | S46: 50 | T46: 50 | W46: 25 | X46: 50 | Y46: 50 | Z46: 100 | AA46: Uber//New card: 35021671 | AD46: 25 | AE46: 50 | AF46: 50 | AG46: Uber
A47: DBS-0199 | B47: 64301263 | C47: 45255 | E47: 45139 | F47: GT | G47: GT 11/30: Informed $100 aded for MRI; GT 8/1: Participant informed $161.53 added for SV, NP, BD, CV + gas | H47: Y | I47: Y | J47: GIven | K47: 25 | L47: 25 | M47: 100 | N47: 50 | O47: Opt Out | P47: 50 | Q47: 11.53 - (08/01/23) | S47: 50 | T47: 50 | U47: 12.06 (8/7/24) | W47: 25 | X47: 50 | Y47: 50 | Z47: 100 | AA47: 14.70 (08/15/25) | AD47: 25 | AE47: 50 | AF47: 50 | AG47: 15.95 (8/21/26)
A48: DBS-0254 | B48: 74307794 | C48: 45255 | E48: 45117 | F48: LC | G48: GT 8/3: Participant informed $123.58 added for LP & gas; GT 7/28: Participant informed $172.16 added for BD,NP,CV + 2 gas; GT 7/10: Participant informed $48.58 added for SV + gas | H48: Y | I48: Y | J48: Given | K48: 25 | L48: 25 | M48: 50 | N48: 50 | O48: 100 | P48: 50 | Q48: 23.58 (10/13/23)
A49: DBS-0418 | B49: NEW CARD: 75495957 45015995 ; 34300870 | C49: 45378 | E49: 45117 | F49: LC | G49: GT 10/25: Informed $128.82 added for MRI & gas; GT 10/20: Informed $128.82 added for LP & gas; GT 8/14: Participant informed $78.82 added for NP + gas; GT 7/10: Participant informed $53.82 added for SV + gas | H49: Y | I49: Y | J49: Given | K49: 25 | L49: 25 | M49: 100 | N49: 50 | O49: 100 | P49: 25 | Q49: 28.82 (10/25/23) | S49: 50 | T49: 50 | U49: 29.48 (10/30/24) | V49: new card | W49: 25 | X49: 50 | Y49: 50 | Z49: 100 | AA49: 31.90 (01/12/26)
A50: DBS-0349 | B50: NEW CARD: 95648932 14299706 | C50: 10/28 11/25/2023 | E50: 45118 | F50: LC | G50: GT 7/19: Participant informed $114.41 added for BD, NP, CV + gas; GT 7/13: Participant informed $114.41 added for MRI + gas; GT 7/11: Participant informed $39.41 added for SV + gas | H50: Y | I50: Y | J50: Given | K50: 25 | L50: 25 | M50: 100 | N50: 50 | O50: Opt Out | P50: 25 | Q50: 14.41 (07/11/23) | S50: 50 | T50: 50 | U50: 14.74 (7/2/24) | W50: 25 | X50: 50 | Y50: 50 | Z50: 100 | AA50: 16.80 (7/15/25) | AD50: 25 | AE50: 50 | AF50: 50 | AG50: 17.40 (07/24/26) | AH50: New Card: NC did 25 for CV by accident, added 25 to gas reimbursement.
A51: DBS-0512 | B51: NEW: 75642218 04303368 | C51: 46323 | E51: 45121 | F51: GT | G51: GT 8/3: Participant informed $136.27 added for BD,CV,NP and gas; GT 7/14: Participant informed $36.27 added for SV + gas | H51: Y | I51: Y | J51: Given | K51: 25 | L51: 25 | M51: 100 | N51: 50 | O51: Opt Out | P51: 50 | Q51: 11.27 (08/10/23) | S51: 50 | T51: 50 | U51: 12.32 (8/6/24) | W51: 25 | X51: 50 | Y51: 50 | Z51: 100 | AA51: 12.32 (8/28/25) | AD51: 25 | AE51: 50 | AF51: 50 | AG51: 12.62 (08/11/26) | AH51: IV 8/13: sent new card via mail
A52: DBS-0216 | B52: NEW:05008136 74318819 | C52: 45774 | E52: 45131 | F52: GT | G52: GT 10/12 Informed $140.72 added for NP,CV,BD and gas; GT 7/24: Participant informed $40.72 added for SV + gas | H52: Y | I52: Y | J52: Given | K52: 25 | L52: 25 | M52: 100 | N52: 50 | O52: Opt Out | P52: 50 | Q52: 15.72 (10/17/23) | S52: 50 | T52: 50 | U52: 25.46 (10/3/24) | W52: 25 | X52: 50 | Y52: 50 | Z52: 100 | AA52: 25.46 (12/15/25)
A53: DBS-0429 | B53: NEW: 95648896 84287602 | C53: 10/28 11/25/2023 | E53: 45140 | F53: GT | G53: GT 10/4: Informed $103.93 added for MRI & gas; GT 8/23: Informed $78.93 added for NP & CV + gas; GT 8/2: Participant informed $53.93 added for SV, BD + gas | H53: Y | I53: Y | J53: Given | K53: 25 | L53: 25 | M53: 100 | N53: 50 | O53: Opt Out | P53: 25 | Q53: 3.93 (10/4/23) | S53: 50 | T53: 50 | W53: 25 | X53: 50 | Y53: 50 | Z53: 100 | AA53: Uber (08/18/25) | AD53: 25 | AE53: 50 | AF53: 50 | AG53: 9.28 (8/11/26)
A54: DBS-0586 | B54: NEW: 15664027 54997031 14852278 74318199 | C54: 10/28 4/27/2025 | E54: 45140 | F54: GT | G54: GT 9/22: Informed $100 added for MRI; GT 8/11: Participant informed $75 added for CV & BD;GT 8/9: Participant informed $50 added for NP;GT 8/2: Participant informed $25 added for SV | H54: Y | I54: Y | J54: Given | K54: 25 | L54: 25 | M54: 100 | N54: 50 | O54: Opt Out | P54: 50 | S54: 50 | T54: 50 | U54: (new card) | W54: 25 | X54: 50 | Y54: 50 | Z54: 100 | AD54: 25 | AE54: 50 | AF54: 50 | AG54: Uber | AH54: New Card
A55: DBS-0499 | B55: NEW: 35621323 84843864 84301160 | C55: 10/28 11/26/2023 | E55: 45141 | F55: LC | G55: GT 10/10: Informed $100 added for MRI; GT 9/22: Participant informed $109.56 added for LP + gas;GT 8/9: Participant informed $109.56 added for BD,CV,NP + gas; GT 8/3: Participant informed $34.56 added for SV + gas | H55: Y | I55: Y | J55: Given | K55: 25 | L55: 25 | M55: 100 | N55: 50 | O55: 100 | P55: 25 | Q55: 9.56 (10/05/23) | S55: 50 | T55: 50 | U55: 9.72 (08/22/24) | V55: (new card) | W55: 25 | X55: 50 | Y55: 50 | Z55: 100 | AA55: 9.72 (8/7/25) | AD55: 25 | AE55: 50 | AF55: 50 | AG55: 10.73 (8/6/26) | AH55: New Card
A56: DBS-0545 | B56: 74305710 | C56: 45255 | E56: 45148 | F56: LC | G56: GT 8/10: Participant informed $32.07 added for SV + gas | H56: Y | I56: Y | J56: Given | K56: 25 | Q56: 7.07 (08/10/23)
A57: DBS-0539 | B57: 54302221 | C57: 45255 | E57: 45152 | F57: LC | G57: GT 9/22: Informed $100 added for LP; GT 8/23: Informed $100 added for IV,BD,NP,CV; GT 8/14: Informed $25 added for SV | H57: Y | I57: Y | J57: Given | K57: 25 | L57: 25 | N57: 50 | O57: 100 | P57: 25
A58: DBS-0614 | B58: NEW CARD: 75658815 74308726 | C58: 45255 | E58: 45153 | F58: GT | G58: GT 11/22: Informed $165.61 added for BD,NP,CV +gas; GT 8/15: Informed $65.61 added for SV + gass | H58: Y | I58: Y | J58: Given | K58: 25 | L58: 25 | M58: 100 | N58: 50 | O58: Opt Out | P58: 50 | Q58: 41.54 (03/22/24) | S58: 50 | T58: 50 | U58: 41.54 (11/26/24) | W58: 25 | X58: 50 | Y58: 50 | Z58: 100 | AA58: 44.24(12/23/25)
A59: DBS-0612 | B59: 94294671 | C59: 45255 | E59: 45154 | F59: MJ | G59: GT 8/16: Informed $75 added for SV + gass | H59: Y | I59: Y | J59: Given | K59: 25 | Q59: 50.00 (08/16/23)
A60: DBS-0085 | B60: 04304189 | C60: 45255 | E60: 45155 | F60: GT | G60: GT 8/30: Informed $120.96 added for BD,NP,CV + gas;GT 8/17: Informed $45.96 added for SV + gas | H60: Y | I60: Y | J60: Given | K60: 25 | L60: 25 | N60: 50 | P60: 25 | Q60: 20.96 (08/30/23)
A61: DBS-0442 | B61: NEW: 15627838 24310877 | C61: 46323 | E61: 45156 | F61: LC | G61: GT 2/16: Informed $114.74 added for MIR+gas; GT 9/22: Participant informed $114.41 added for BD,CV,NP + gas;GT 8/18: Informed $39.41 added for SV + gas | H61: Y | I61: Y | J61: Given | K61: 25 | L61: 25 | M61: 100 | N61: 50 | O61: Opt Out | P61: 25 | Q61: 14.74 (2/16/24) | S61: 50 | T61: 50 | U61: 14.74 (8/16/24 | W61: 25 | X61: 50 | Y61: 50 | Z61: 100 | AA61: 14.74 (8/15/25) | AB61: New card 6/22/26 sent out
A62: DBS-0502 | B62: 04301606 | C62: 45255 | E62: 45160 | F62: GT | G62: GT 11/28: Informed $100 added for MRI; GT 8/22: Informed $43.34 added for SV + gas | H62: Y | I62: Y | J62: Given | K62: 25 | L62: 25 | M62: 100 | N62: 50 | O62: Opt Out | P62: 25 | Q62: 18.34 (08/22/23) | S62: 50 | T62: 50 | W62: 25 | X62: 50 | Y62: 50 | Z62: 100 | AD62: 25 | AE62: 50 | AF62: 50
A63: DBS-0597 | B63: 45643658 94300012 | C63: 10/28 11/25/2023 | E63: 45161 | F63: LC | G63: GT 12/18: Informed $100 added for MRI; GT 8/23: Informed $25 added for SV | H63: Y | I63: Y | J63: Given | K63: 25 | L63: 25 | M63: 100 | N63: 50 | O63: Opt Out | P63: 50 | S63: 50 | T63: 50 | W63: 25 | X63: 50 | Y63: 50 | Z63: 100 | AA63: Uber | AB63: New card 2/25/26
A64: DBS-0498 | B64: NEW:25652685 95019235 74296993 | C64: 10/28 4/27/2025 | E64: 45162 | F64: LC | G64: GT 10/12: Informed $100 added for MRI; GT 8/30: Informed $100 added for BD,NP,CV; GT 8/24: informed $25 added for SV | H64: Y | I64: Y | J64: Given | K64: 25 | L64: 25 | M64: 100 | N64: 50 | O64: Opt Out | P64: 25 | S64: 50 | T64: 50 | W64: 25 | X64: 50 | Y64: 50 | Z64: 100 | AA64: Uber
A65: DBS-0620 | B65: NEW: 05484807 14306699 | C65: 45805 | E65: 45168 | F65: LC | G65: GT 11/9: Informed $25 added for CV; GT 11/7: Informed $100 added for MRI; GT 9/28: Informed $75 added for BD&NP; GT 8/30: Informed $25 added for SV | H65: Y | I65: Y | J65: Given | K65: 25 | L65: 25 | M65: 100 | N65: 50 | O65: Opt Out | P65: 25 | S65: 50 | T65: 50 | W65: 25 | X65: 50 | Y65: 50 | Z65: 100 | AA65: Uber
A66: DBS-0613 | B66: NEW: 15647320 25498709 64301723 | C66: 10/28 5/28/2025 | E66: 45174 | F66: MJ | G66: GT 10/24: Informed $25 added; GT 9/12: Informed $25 for SV | H66: Y | I66: Y | J66: Given | K66: 25 | L66: 25 | M66: 100 | N66: 50 | O66: Opt Out | P66: 25 | Q66: 45.37 (09/26/23) | S66: 50 | T66: 50 | W66: 25 | X66: 50 | Y66: 50 | Z66: 100 | AA66: new card//uber | AD66: 25 | AE66: 50 | AF66: 50 | AG66: uber new vcard
A67: DBS-0584 | B67: 34305295 | C67: 45255 | E67: 45176 | F67: LC | G67: GT 9/12: Informed $25 for SV | H67: Y | I67: Y | J67: Given | K67: 25
A68: DBS-0676 | B68: NEW: 55644799 75491171 94871581 54309824 | C68: 45958 | E68: 45187 | F68: LC | G68: GT 1/8: Informed $117.42 added for MRI+gas; GT 11/30: Informed $125 +$17.03 added for LP,CV, gas; GT 9/25: Informed $75 +$17.03 added for NP,BD, gas; GT 9/19: Informed $42.03 for SV + gas | H68: Y | I68: Y | J68: Given | K68: 25 | L68: 25 | M68: 100 | N68: 50 | O68: 100 | P68: 25 | Q68: 17.42 (01/08/24) | S68: 50 | T68: 50 | U68: 17.42 (9/9/24) | V68: new card | W68: 25 | X68: 50 | Y68: 50 | Z68: 100 | AA68: 17.42 (10/21/25) | AD68: 25 | AE68: 50 | AF68: 50 | AG68: 20.30 (9/29/26) | AH68: new card
A69: DBS-0587 | B69: NEW: 25478681 94314335 | C69: 45805 | E69: 45188 | F69: LC | G69: GT 10/11 Informed $100 added for BD,CV,NP; GT 9/19: Informed $53.82 for SV + gas | H69: Y | I69: Y | J69: Given | K69: 25 | L69: 25 | M69: 100 | N69: 50 | O69: Opt Out | P69: 25 | Q69: 28.82 (09/19/23) | S69: 50 | T69: 50 | W69: 25 | X69: 50 | Y69: 50 | Z69: 100
A70: DBS-0569 | B70: NEW: 95652925 94316074 | C70: 11/28 11/25 | E70: 45189 | F70: MJ | G70: New card recived at MRI visit. 11/26/25 JE ;; GT 10/4: Informed $50 added for CV+BD; GT 9/20 Informed $25 added for SV | H70: Y | I70: Y | J70: Given | K70: 25 | L70: 25 | M70: 100 | N70: 50 | O70: Opt Out | P70: 25 | Q70: 50 (09/27/23) | S70: 50 | T70: 50 | U70: 50 (10/23/24) | W70: 25 | X70: 50 | Y70: 50 | Z70: 100 | AA70: 50 (11/26/25) | AB70: MJ paid for 11/26/25 visits | AD70: 25 | AE70: 50 | AF70: 50 | AG70: 50 (10/06/26)
A71: DBS-0599 | B71: NEW NEW 45633896 NEW: 75489091 64868974 74327750 | C71: 10/28 5/28/2025 | E71: 45191 | F71: MJ | G71: New card given at MRI. Lost previous card. JE 11/18/25 ;; GT 10/27: Informed $125 added for NP,BD,CV; GT 9/22: Participant informed $25 added for SV | H71: Y | I71: Y | J71: Given | K71: 25 | L71: 25 | M71: 100 | N71: 50 | O71: Opt Out | P71: 50 | S71: 50 | T71: 50 | U71: (new card) | W71: 25 | X71: 50 | Y71: 50 | Z71: 100 | AA71: Uber | AB71: New CC 11/18/25
A72: DBS-0657 | B72: NEW:05495532 44292312 | C72: 45805 | E72: 45195 | F72: GT | G72: 10/10 GT: Informed $111.79 added for gas; 9/26 GT: Participant informed $61.79 added for SV,BD, gass | H72: Y | I72: Y | J72: Given | K72: 25 | L72: 25 | M72: 100 | N72: 50 | O72: Opt Out | P72: 50 | Q72: 11.79 (12/6/23) | S72: 50 | T72: 50 | U72: 12.06 (10/24/24) | W72: 25 | X72: 50 | Y72: 50 | Z72: 100 | AA72: 25.2 (11/18/25) | AB72: new address
A73: DBS-0672 | B73: 44310524 | C73: 45255 | E73: 45196 | F73: MJ | G73: 10/18 GT: Participant informed $29.85 added for BD + gas; 9/28 GT: Participant informed $29.85 added for SV + gas | H73: Y | I73: Y | J73: Given | K73: 25 | L73: 25 | Q73: 4.85 (10/18/23)
A74: DBS-0658 | B74: NEW CARD: 75562322 34316746 | C74: 45255 | E74: 45198 | F74: LC | G74: GT 10/6: Informed $125 added for BD, CV, NP; GT 10/2: Informed $25 added for SV | H74: Y | I74: Y | J74: Given | K74: 25 | L74: 25 | M74: 100 | N74: 50 | O74: Opt Out | P74: 50 | S74: 50 | T74: 50 | W74: 25 | X74: 50 | Y74: 50 | Z74: 100 | AA74: Uber
A75: DBS-0738 | B75: 74298215 | C75: 45255 | E75: 45201 | F75: MJ | G75: GT 10/27: Informed $128.73 added for BD,CV,NP +gas; GT 10/2: Informed $43.73 added for SV +gas | H75: Y | I75: Y | J75: Given | K75: 25 | L75: 25 | N75: 50 | O75: Opt Out | P75: 25 | Q75: 18.73 (10/27/23)
A76: DBS-0705 | B76: 14322547 | C76: 45255 | E76: 45202 | F76: LC | G76: GT 10/23: Informed $125 added for BD,CV,NP; GT 10/3: Informed $25 added for SV | H76: Y | I76: Y | J76: Given | K76: 25 | L76: 25 | M76: 100 | N76: 50 | O76: Opt Out | P76: 50
A77: DBS-0542 | B77: 14303058 | C77: 45255 | E77: 45202 | F77: GT | G77: GT 12/8: Informed $120.96 added for MRI + gas; GT 10/11 informed $145.96 added for BD,NP,CV + gas GT 10/4: Informed $45.96 added for SV + gas | H77: Y | I77: Y | J77: Given | K77: 25 | L77: 25 | M77: 100 | N77: 50 | O77: 100 | P77: 50 | Q77: 20.96 (12/8/23)
A78: DBS-0745 | B78: NEW 65492560 14310771exp | C78: 05/28 11/25/2023 | E78: 45202 | F78: LC | G78: New card mailed out 10/16/25 JE ;; GT 12/4: Informed $127.51 added for MRI + gas; GT 10/20: Informed 152.51 for BD,CV<NP + gas; GT 10/4: Informed $52.51 added for SV + gas | H78: Y | I78: Y | J78: Given | K78: 25 | L78: 25 | M78: 100 | N78: 50 | O78: 100 | P78: 50 | Q78: 27.51 (12/04/23) | S78: 50 | T78: 50 | U78: 28.14 (10/01/24) | W78: 25 | X78: 50 | Y78: 50 | Z78: 100 | AA78: 50 (10/13/25) | AB78: Diff mileage on 10/13/25 bc she was staying in Redlands. Returns back to her regular home this week (30.8mi for future reference). | AJ78: New card recived 10/20/25
A79: DBS-0741 | B79: 74293610 | C79: 45255 | E79: 45210 | F79: MJ | G79: GT1/8: Informed $100 added for MRI; GT 11/17: Informed $75 added for CV,BD; GT 11/7 Informed $50 added for NP; GT 10/11: Informed $25 added for SV | H79: Y | I79: Y | J79: Given | K79: 25 | L79: 25 | M79: 100 | N79: 50 | O79: Opt Out | P79: 50 | S79: 50 | T79: 50 | W79: 25 | X79: 50 | Y79: 50 | Z79: 100 | AA79: Uber
A80: DBS-0715 | B80: NEW: 25479146 35029278 04296450 | C80: 05/28 3/27/2024 | E80: 45210 | F80: IV | G80: GT 1/16 $150 added for MRI&gas; GT 11/14: Informed $175 added for BD,CV,NP + gas; GT 10/11: Informed $75 added for SV+gas | H80: Y | I80: Y | J80: Given | K80: 25 | L80: 25 | M80: 100 | N80: 50 | O80: Opt Out | P80: 50 | Q80: 50 (11/14/23) | S80: did not do | T80: 50 | U80: 50 (3/6/2025) | V80: new card | W80: 25 | X80: 50 | Y80: 50 | Z80: 100 | AA80: 50 (3/2/2026)
A81: DBS-0742 | B81: 04317861 | C81: 45255 | E81: 45215 | F81: MJ | G81: GT 10/24: $89.41 added for NP,CV,gas; GT 10/16: $39.41 added for SV + gas | H81: Y | I81: Y | J81: Given | K81: 25 | L81: 25 | M81: 25 | N81: 50 | O81: Opt Out | P81: 25 | Q81: 14.74 (02/09/24)
A82: DBS-0771 | B82: NEW: 25657647 04312290 | C82: 46323 | E82: 45215 | F82: GT | G82: GT 10/16: $39.41 added for SV + gas | H82: Y | I82: Y | J82: Given | K82: 25 | L82: 25 | M82: 100 | N82: 50 | O82: Opt Out | P82: 50 | Q82: 14.74 (2/2/24) | S82: 50 | T82: 50 | U82: 15.4 (2/11/25) | W82: 25 | X82: 50 | Y82: 50 | Z82: 100 | AA82: 15.95 (02/04/2026)
A83: DBS-0693 | B83: NEW: 85039230 54292121 | C83: 04/27 11/25/2023 | E83: 45216 | F83: LC | G83: 11/10/25: New card given to participant, CTS 1/17: Informed $50 added for gas from MRI; 1/16 GT: Informed $100 added for MRI; 11/2 GT: Informed $150 added to card for SV,BD, 2 gas; | H83: Y | I83: Y | J83: Given | K83: 25 | L83: 25 | M83: 100 | N83: 50 | O83: Opt Out | P83: 25 | Q83: 50 (1/12/24) | S83: 50 | T83: 50 | U83: 50 (11/11/24) | W83: 25 | X83: 50 | Y83: 50 | Z83: 100 | AA83: 50 11/14/25
A84: DBS-0772 | B84: new: 15613622 74320972 | C84: 10/28 11/25 | E84: 45218 | F84: MJ | G84: 1/10 GT: Informed 100 added for MRI; 10/23: Informed $125 for BD,NP,CV; 10/19 GT: Informed $25 added for SV | H84: Y | I84: Y | J84: Given | K84: 25 | L84: 25 | M84: 100 | N84: 50 | O84: Opt Out | P84: 50 | S84: 50 | T84: 50 | W84: 25 | X84: 50 | Y84: 50 | Z84: 100 | AA84: uber | AD84: 25 | AE84: 50 | AF84: 50 | AG84: uber
A85: DBS-0652 | B85: NEW CARD: 55565041 84302942 | C85: 07/28 11/25/2023 | E85: 45222 | F85: LC | G85: 12/7 GT: $100 added for LP; 11/2 GT: $128.82 added for BD,CV,NP + gas; 10/24 GT: $53.82 added for SV+gas | H85: Y | I85: Y | J85: Given | K85: 25 | L85: 25 | M85: 100 | N85: 50 | O85: 100 | P85: 25 | Q85: 34.17 (4/04/24) | S85: 50 | T85: 50 | U85: 34.17 (11/08/24) | W85: 25 | X85: 50 | Y85: 50 | Z85: 100 | AA85: 37.66 12/05/25
A86: DBS-0757 | B86: NEW: 04858070 04327217 | C86: 45256 | E86: 45224 | F86: MJ | G86: GT 1/25 Informed $100 added for MRI; GT 10/25: Informed $25 added for SV | H86: Y | I86: Y | J86: Given | K86: 25 | L86: 25 | M86: 100 | N86: 50 | O86: Opt Out | P86: 50 | S86: 50 | T86: 50 | U86: (new card)
A87: DBS-0653 | B87: New CARD: 94987359 24840498 ;4898147 | C87: 45378 | E87: 45224 | F87: IV | G87: 1/16: Informed $50 added for NP; 12/15: Informed $50 added for BD,CV; GT 10/25: Informed $25 added for SV | H87: Y | I87: Y | J87: Given | K87: 25 | L87: 25 | M87: 100 | N87: 50 | O87: Opt Out | P87: 50 | S87: 50 | T87: 50 | U87: (new card) | W87: 25 | X87: 50 | Y87: 50 | Z87: 100 | AA87: uber
A88: DBS-0756 | B88: NEW: 95634864 74872652; 34992990; 34296377 | C88: 46323 | E88: 45224 | F88: GT | G88: 2/15 GT: Informed $100 added for MRI; 12/18: Informed $75 added for BD, NP; GT 10/25: Informed $25 added for SV | H88: Y | I88: Y | J88: Given | K88: 25 | L88: 25 | M88: 100 | N88: 50 | O88: Opt Out | P88: 50 | S88: 50 | T88: 50 | W88: 25 | X88: 50 | Y88: 50 | Z88: 100
A89: DBS-0778 | B89: 73776599 | C89: 45284 | E89: 45232 | F89: LC | G89: GT 1/8 Informed $100 added for MRI; GT 11/2: Informed $125 added for SV,BD,NP,CV | H89: Y | I89: Y | J89: Given | K89: 25 | L89: 25 | M89: 100 | N89: 50 | O89: 100 | P89: 25
A90: DBS-0800 | B90: NEW: 35560934 64313709 | C90: 45866 | E90: 45236 | F90: GT | G90: GT 12/20: Informed 131.44 for MRI +gas; GT 11/7: Informed $106.44 added for NP,CV,gas; GT 11/6: Informed $81.44 added for SV,BD,gas | H90: Y | I90: Y | J90: Given | K90: 25 | L90: 25 | M90: 100 | N90: 50 | O90: Opt Out | P90: 25 | Q90: 31.44 (12/20/23) | S90: 50 | T90: 50 | U90: 32.16 (11/26/24) | W90: 25 | X90: 50 | Y90: 50 | Z90: 100 | AA90: 32.2 (12/23/25)
A91: DBS-0790 | B91: NEW CARD: 85544156 94297333 | C91: 45255 | E91: 45236 | F91: IV | G91: 11/14 GT: Informed $100 added for BD,NP,CV;11/9 GT: Informed $25 added for SV | H91: Y | I91: Y | J91: Given | K91: 25 | L91: 25 | N91: 50 | P91: 25 | S91: 50 | T91: 50 | U91: 50 (11/15/24) | W91: 25 | X91: 50 | Y91: 50 | Z91: 100 | AA91: 50 (11/24/24)
A92: DBS-0855 | B92: 63758114 | C92: 45284 | E92: 45239 | F92: GT | G92: 3/6: Informed $134.84 added for MRI+gas; 11/21 GT: Informed $134.06 added for BD,NP,CV; 11/9 GT: Informed $84.06 added for SV,BD,Gas | H92: Y | I92: Y | J92: Given | K92: 25 | L92: 25 | M92: 100 | N92: 50 | O92: Opt Out | P92: 50 | Q92: 34.84 (3/6/24) | S92: 50 | T92: 50 | U92: 34.84 (11/13/24) | W92: 25 | X92: 50 | Y92: 50 | Z92: 100 | AA92: Uber (11/25/25)
A93: DBS-0763 | B93: NEW: 65005223 94896250 | C93: 45378 | E93: 45244 | F93: IV | G93: 1/26: Informed $255.56 added for MRI,LP,gas; 11/14 GT: Informed $25 added for SV | H93: Y | I93: Y | J93: Given | K93: 25 | L93: 25 | M93: 100 | N93: 50 | O93: 100 | P93: 50 | Q93: 22.78 (01/12/24) | S93: 50 | T93: 50 | U93: 22.78 (11/21/24) | V93: new card | W93: 25 | X93: 50 | Y93: 50 | Z93: 100 | AA93: 23.8 (1/30/26) | AB93: walked from work, drove from home parked there, went home after, comped gas
A94: DBS-0808 | B94: 34520233 | C94: 45042 | E94: 45244 | F94: MJ | G94: 1/17: Informed $75 added for NP,BD; 11/15 GT: Informed $25 added for SV | H94: Y | I94: Y | J94: Given | K94: 25 | L94: 25 | M94: 100 | N94: 50 | P94: 50
A95: DBS-0781 | B95: 74502924 | C95: 45042 | E95: 45245 | F95: GT | G95: 2/14 GT: Informed $100 added fro MRI +gass money; 12/13: Informed $100 + $26.20; 11/15 GT: Informed $76.20 added for SV,BD,gas | H95: Y | I95: Y | J95: Given | K95: 25 | L95: 25 | M95: 100 | N95: 50 | O95: Opt Out | P95: 50 | Q95: 26.80 (2/14/23) | S95: 50 | T95: 50 | U95: 50 (12/11/24) | V95: (moved to palmdale)
A96: DBS-0830 | B96: NEW: 55618177 94538981 | C96: 46323 | E96: 45245 | F96: IV | G96: 3/11 GT: Informed $120.10 added for MRI+gas; 12/15 GT: $119.65 added for BD,NP,CV+gas; 11/16 GT: Informed $44.65 added for SV+gas | H96: Y | I96: Y | J96: Given | K96: 25 | L96: 25 | M96: 100 | N96: 50 | P96: 25 | Q96: 20.10 (3/8/24) | S96: 50 | T96: 50 | U96: 29.00 (10/01/25) | W96: 25 | X96: Paid (2nd yr) | Y96: Paid (2nd yr) | Z96: 100 | AA96: 29.00 (12/4/25) | AB96: didnt get paid for mri on 11/11, paid on 12/4 | AD96: 25 | AE96: 50 | AF96: 50 | AG96: 29.00 (10/05/26) | AH96: NEW CARD
A97: DBS-0617 | B97: 34525772 | C97: 45042 | E97: 45250 | F97: LC | G97: 12/14: Informed $100 added for BD, NP, CV; 11/21 GT: Informed $25 added for SV | H97: Y | I97: Y | J97: Given | K97: 25 | L97: 25 | M97: 100 | N97: 50 | O97: Opt Out | P97: 25 | S97: 50 | T97: 50 | W97: 25 | X97: 50 | Y97: 50 | Z97: 100
A98: DBS-0879 | B98: NEW: 45546182 24517114; 84987772 | C98: 46231 | E98: 45251 | F98: IV | G98: 11/21 GT: Informed $25 added for SV | H98: Y | I98: Y | J98: Given | K98: 25 | L98: 25 | M98: 100 | N98: 50 | P98: 25 | S98: 50 | T98: 50 | W98: 25 | X98: 50 | Y98: 50 | Z98: 100 | AA98: $17.55 (2/18/26)
A99: DBS-0822 | B99: New card: 15639615 74554298 | C99: 10/28 4/26/2023 | E99: 45252 | F99: IV | G99: 11/22 GT: Informed $25 added for SV | H99: Y | I99: Y | J99: Given | K99: 25 | L99: 25 | M99: 100 | N99: 50 | O99: Opt Out | P99: 25 | Q99: 16.08 (1/24/24) | S99: 50 | T99: 50 | W99: 25 | X99: 50 | Y99: 50 | Z99: 100 | AA99: Uber
A100: DBS-0873 | B100: 54531416 | C100: 45042 | E100: 45252 | F100: LC | G100: 12/1 GT: Informed $148.58 for BD,CV,NP,gas; 11/22 GT: Informed $48.58 added for SV + gas | H100: Y | I100: Y | J100: Given | K100: 25 | L100: 25 | N100: 50 | P100: 50 | Q100: 50 (12/1/23)
...

Sheet Stool Samples
A1: ID's Eligible | B1: Status | E1: Date Given or Mailed | F1: Tracking Number if mailed | G1: Informed about Kit | H1: KIT Number | I1: Follow up notes | J1: Date Received | L1: Updated on Redcap | M1: Total Consented | N1: =SUM(N2:N6) -> 131
A2: # Complete: | B2: =COUNTIF(B3:B134,"Complete") -> 45 | M2: Completed | N2: =COUNTIF(B3:B134,"Complete") -> 45
A3: DBS-0053 | B3: Complete | C3: (i dont think they signed new consent) | D3: DBS-0715 | E3: 45210 | H3: N/A | J3: 45217 | L3: TRUE | M3: Failed to Complete | N3: =COUNTIF(B3:B134,"Failed to complete") -> 24
A4: DBS-0073 | B4: Complete | C4: (signed updated consent) | D4: DBS-1491 | E4: 45589 | F4: 1ZND00T10717112124 | G4: Y | H4: N/A | I4: 11/11 GT: Informed me he shipped it; 11/8 GT: Will try again soon, paper ripped on him so having issues collecting; 11/1 GT: Confirmed received kit, will do it soon | J4: 45609 | L4: TRUE | M4: Can still offer | N4: =COUNTIF(B3:B134,"Not offered") -> 52
A5: DBS-0169 | B5: Failed to Complete | C5: (signed updated consent) | D5: DBS-1373 | E5: 45589 | F5: 1ZND00T10716080107 | G5: Y | H5: N/A | I5: 11/1 GT: Will bring it in person day of her MRI 11/21 | L5: TRUE | M5: Declined | N5: =COUNTIF(B3:B134,"Declined") -> 2
A6: DBS-0653 | B6: Failed to Complete | D6: DBS-1492 | E6: 45589 | F6: 1ZND00T10722525106 | G6: Y | H6: N/A | I6: 11/8: Will try to send tomorrow, coming back from mammoth; 11/1 GT: Left vm | L6: TRUE | M6: Consented but dropout | N6: =COUNTIF(B3:B134,"dropout") -> 8
A7: DBS-0715 | B7: Complete | D7: DBS-1505 | E7: 45589 | F7: 1ZND00T10737439299 | G7: Y | H7: N/A | I7: 11/8 GT: Left vm, sent text; 10/31 GT: Confirmed received kit, will do it soon | L7: TRUE
A8: DBS-0745 | B8: Failed to Complete | D8: DBS-1530 | E8: 45589 | F8: 1ZND00T10718955132 | G8: Y | H8: N/A | I8: 11/8 GT: Confirmed received new kit; 11/1 GT: Didn't receive kit, sending new one to work address | K8: Send new kit 11/4 | L8: TRUE
A9: DBS-0756 | B9: Not offered | D9: DBS-1497 | E9: 45589 | F9: 1ZND00T10731141870 | G9: Y | H9: N/A | I9: 11/8 GT: Will do it by next week; 11/1 GT: Confirmed received kit, will do it soon | J9: 45611 | L9: TRUE
A10: DBS-0770 | B10: Failed to Complete | D10: DBS-1368 | E10: 45587 | F10: 1ZND00T10715920086 | G10: Y | H10: N/A | I10: 11/19 GT: Pt shipped; 11/13 GT: Called me with questions, will send kit back soon; 11/8 GT: Left vm sent text; 10/31 GT: Confirmed received kit, will do it when gets a chance | J10: 45621 | L10: TRUE
A11: DBS-0771 | B11: Complete | D11: DBS-1523 | E11: 45587 | F11: 1ZND00T10715167070 | G11: Y | H11: N/A | I11: 10/31 GT: Participant sent it back this date | J11: 45600 | L11: TRUE
A12: DBS-0789 | B12: Not offered | D12: DBS-1515 | E12: 45587 | F12: 1ZND00T10733618263 | G12: Y | H12: N/A | I12: 11/8 GT: Wasn't able to do it bc moving but will send next week; 10/31 GT: Left vm; 10/24 GT: Participant confirmed he received it | L12: TRUE
A13: DBS-0790 | B13: Not offered | D13: DBS-1521 | E13: 45587 | F13: 1ZND00T10712091095 | G13: Y | H13: N/A | I13: 11/18 UPS still has possession, waiting for delivery date; 11/14 GT: Pt sent kit back; 11/8 GT: Will do it soon; 10/31 GT: Says he will do it soon; 10/25 GT: Confirmed he received it said he'll send it back soon | J13: 45615 | L13: TRUE
A14: DBS-0798 | B14: Not offered | D14: DBS-1508 | E14: 45587 | F14: 1ZND00T10723770054 | G14: Y | H14: N/A | I14: 11/12: Pt sent kit back; 11/8 GT: Participant says he forgot will do it; 10/31 GT: Says he will do it by Monday; 10/24 GT: Participant confirmed he received it | J14: 45610 | L14: TRUE
A15: DBS-0805 | B15: Failed to Complete | D15: DBS-1315 | E15: 45772 | F15: 9405536208326289980603 | G15: Y | H15: 1 | I15: IV 6/24: sent text reminder | L15: TRUE
A16: DBS-0808 | B16: Not offered | D16: DBS-1143 | E16: 45762 | F16: 9405536208326289980689 | G16: Y | H16: 2 | J16: 45775 | L16: TRUE
A17: DBS-0818 | B17: Failed to Complete | D17: DBS-1727 | E17: 45769 | F17: 9405536208326289980740 | G17: Y | H17: 3 | J17: 45778 | L17: TRUE
A18: DBS-0822 | B18: Declined | D18: DBS-1059 | E18: 45756 | F18: 9405536208326289980818 | G18: Y | H18: 4 | J18: 45765 | L18: TRUE
A19: DBS-0824 | B19: Complete | C19: MJ 12/03: Called me to let me know that she dropped some of the liquid in the vial??Told her we will follow up if the sample is not usuable | D19: DBS-0969 | E19: 45754 | F19: 9405536208326289980863 | G19: Y | H19: 5 | I19: 4/25 GT Sent a reminder, says hasn;t been in LA but will be this weekend to do it | J19: 45776 | L19: TRUE
A20: DBS-0830 | B20: Complete | D20: DBS-1095 | E20: 45756 | F20: 9405536208326289980610 | G20: Y | H20: 6 | I20: 4/25 GT Sent reminder, will send it soon | J20: 45776 | L20: TRUE
A21: DBS-0838 | B21: Not offered | D21: DBS-1134 | E21: 45764 | F21: 9405536208326289980696 | G21: Y | H21: 7 | J21: 45771 | L21: TRUE
A22: DBS-0843 | B22: Not offered | D22: DBS-1152 | E22: 45770 | F22: 9405536208326289980771 | G22: Y | H22: 8 | J22: 45772 | L22: TRUE
A23: DBS-0876 | B23: Not offered | D23: DBS-1119 | E23: 45772 | F23: 9405536208326289980832 | G23: Y | H23: 9 | I23: IV 6/24: sent text reminder | L23: TRUE
A24: DBS-0878 | B24: Not offered | D24: DBS-1735 | E24: 45775 | F24: 9405536208326289980887 | G24: Y | H24: 10 | J24: 45779 | L24: TRUE
A25: DBS-0879 | B25: Not offered | D25: DBS-1106 | E25: 45775 | F25: 9405536208326289980634 | G25: discard, got a new one | H25: 11 | I25: IV 6/24: sent text reminder , needs new one, will stop by or ship out | L25: TRUE
A26: DBS-0884 | B26: Not offered | D26: DBS-1085 | E26: 45756 | F26: 9405536208326289980719 | G26: Y | H26: 12 | I26: IV 6/24: sent text reminder 4/25 GT sent reminder | J26: 45845 | L26: TRUE
A27: DBS-0901 | B27: Not offered | D27: DBS-1012 | E27: 45798 | F27: 9405536106193278577099 | G27: Y | H27: 13 | I27: NC 6/30: sent text reminder 6/9/25 NC sent reminder | L27: TRUE
A28: DBS-0916 | B28: Not offered | D28: DBS-0073 | E28: 45807 | F28: 9405536106193278577129 | G28: Y | H28: 14 | I28: NC 6/30 In mexico, offer in a month, left in car NC 6/30: sent text reminder 6/9/25 NC sent reminder | L28: TRUE
A29: DBS-0918 | B29: Failed to Complete | D29: DBS-0169 | E29: 45807 | F29: 9405536106193278577167 | G29: Y | H29: 15 | I29: NC 6/30 In mexico, offer in a month, left in car NC 6/30: sent text reminder 6/9/25 NC sent reminder | L29: TRUE
A30: DBS-0924 | B30: Not offered | F30: 9405536106193278577198 | H30: 16 | L30: TRUE
A31: DBS-0928 | B31: Not offered | D31: DBS-1246 | E31: 45807 | F31: 9405536106193278577211 | G31: Y | H31: 17 | I31: NC 6/30: sent text reminder 6/9/25 NC sent reminder | L31: TRUE
A32: DBS-0935 | B32: Not offered | D32: DBS-1106 | E32: 45834 | F32: 9405536106193278577105 | G32: Y | H32: 18 | I32: IV 6/26: picked up new kit IV 6/24: sent text reminder , needs new one, will stop by or ship out | J32: 45835 | L32: TRUE
A33: DBS-0940 | B33: Failed to Complete | D33: DBS-1047 | E33: 45840 | F33: 9405536106193278577136 | G33: Y | H33: 19 | I33: NC 7/30 sent reminder AG 7/23 sent follow up text | L33: TRUE
A34: DBS-0956 | B34: Complete | D34: DBS-1008 | E34: 45840 | F34: 9405536106193278577150 | G34: Y | H34: 20 | I34: NC 7/30 sent reminder AG 7/23 sent follow up text | L34: TRUE
A35: DBS-0969 | B35: Complete | D35: DBS-1156 | E35: 45852 | F35: 9405536106193278577181 | G35: Y | H35: 21 | I35: NC 7/30 sent reminder AG 7/23 sent follow up text | J35: 45873 | L35: TRUE
A36: DBS-0971 | B36: Complete | D36: DBS-1063 | E36: 45908 | F36: 9405536106193278577204 | G36: Y | H36: 22 | I36: IV 9/23: received | J36: 45923 | L36: TRUE
A37: DBS-0981 | B37: Not offered | D37: DBS:1167 Checked in through text. Pending response 5/5/26 JE ;; Reminder text sent NC 9/2 | E37: 45880 | F37: 9405536106193278577112 | G37: Y | H37: 23 | I37: Reminder text sent NC 9/2 | L37: TRUE
A38: DBS-0982 | B38: Complete | D38: DBS-1392 | E38: 45896 | F38: 9405536106193278577143 | G38: Y | H38: 24 | I38: Reminder text send NC 9/9 (responded that she sent it that day) | J38: 45910 | L38: TRUE
A39: DBS-0987 | B39: Complete | F39: 9405536106193283632813 | H39: 25 | L39: TRUE
A40: DBS-1000 | B40: Complete | D40: DBS-1480 | E40: 45923 | F40: 9405536106193283632851 | G40: Y | H40: 26 | J40: 45931 | L40: TRUE
A41: DBS-1004 | B41: Not offered | D41: DBS-1418 | E41: 45926 | F41: 9405536106193283632899 | G41: Y | H41: 27 | L41: TRUE
A42: DBS-1008 | B42: Failed to Complete | D42: DBS-0053 | E42: 45930 | F42: 9405536106193283632912 | G42: Y | H42: 28 | I42: Given in person after scan on MRI day. JE 9/30/25 | J42: 45931 | L42: TRUE
A43: DBS-1009 | B43: Complete | D43: DBS-0830 | E43: 45930 | F43: 9405536106193283632943 | G43: Y | H43: 29 | I43: 11/11/25 Brought in person day of MRI. JE ;; 10/14 Reminder text sent NC; MJ 09/30:Given in person after NP | J43: 45972 | K43: expired | L43: TRUE
A44: DBS-1012 | B44: Failed to Complete | D44: DBS-1530 | E44: 45933 | F44: 9405536106193283632837 | G44: Y | H44: 30 | I44: 10/14 Reminder text sent NC; Given in person after 2nd yr CV. JE 10/3/25 | K44: expired | L44: TRUE
A45: DBS-1016 | B45: Not offered | D45: DBS-0745 | E45: 45939 | F45: 9405536106193283632875 | G45: Y | H45: 31 | I45: Reminded to complete NC 10/21/25 Reminded to complete. JE 10/10/25 | K45: expired | L45: TRUE
A46: DBS-1019 | B46: Complete | D46: DBS-1605 | E46: 45967 | F46: 9434636106195286568037 | G46: Y | H46: 32 | I46: Recived and placed into the frezzer in 123A. 12/11/25 JE;; Reminded to complete NC 11/25/25 | J46: 46002 | K46: NEW LABELS ⬇️ | L46: TRUE
A47: DBS-1030 | B47: Complete | D47: DBS-1601 | E47: 45968 | F47: 9434636106195286568044 | G47: Y | H47: 33 | I47: Reminded to complete NC 1/23/26 Reminded to complete NC 11/25/25 | L47: TRUE
A48: DBS-1039 | B48: Complete | D48: DBS-0824 | E48: 45986 | F48: 9434636106195286568051 | G48: Y | H48: 34 | I48: Received and placed in 123A frezzer. 12/10/25 JE | J48: 46001 | L48: TRUE
A49: DBS-1047 | B49: Failed to Complete | D49: DBS-0790 | F49: 9434636106195286568082 | H49: 35 | L49: TRUE
A50: DBS-1053 | B50: Not offered | F50: 9434636106195286568099 | H50: 36 | L50: TRUE
A51: DBS-1059 | B51: Complete | D51: DBS-0073 | F51: 9434636106195298296751 | H51: 37 | I51: CTS 02/18 Got back this kit on 02/18/2026; no ID | J51: 46071 | L51: TRUE
A52: DBS-1063 | B52: Complete | D52: DBS-1335 | E52: 45995 | F52: 9434636106195298296768 | G52: Y | H52: 38 | I52: Reminded to complete NC 1/23/26 Reminded to complete NC 12/18/24 | L52: TRUE
A53: DBS-1071 | B53: Complete | F53: 9434636106195298296782 | H53: 39 | L53: TRUE
A54: DBS-1076 | B54: Complete | D54: DBS-0818 | E54: 46010 | F54: 9434636106195298296812 | G54: Y | H54: 40 | I54: Reminded to complete NC 1/23/26 | L54: TRUE
A55: DBS-1079 | B55: Complete | D55: DBS-0653 | E55: 46013 | F55: 9434636106195298296850 | G55: Y | H55: 41 | I55: Reminded to complete NC 1/23/26 | L55: TRUE
A56: DBS-1085 | B56: Complete | D56: DBS-0805 | E56: 46027 | F56: 9434636106195298296775 | H56: 42 | I56: Reminded to complete NC 1/23/26 Given day of MRI JE 1/5/26 | L56: TRUE
A57: DBS-1092 | B57: Not offered | D57: DBS-1734 | E57: 46030 | F57: 9434636106195298296805 | H57: 43 | I57: Received. Was in mailbox upstairs. 2/5/26 JE ;; Reminded to complete NC, said they sent it already 1/23/26 Given day of 2nd yr NP | J57: 46058 | L57: TRUE
A58: DBS-1095 | B58: Complete | D58: DBS-0987 | E58: 46038 | F58: 9434636106195298296836 | H58: 44 | I58: 2/6/26 Reminded to Complete NCGiven day of 3rd yr visit | J58: 46063 | K58: Dropped off in person, in fridge CTS 02/10/26 | L58: TRUE
A59: DBS-1096 | B59: Not offered | D59: DBS-1000 | E59: 46055 | F59: 9434636106196278179279 | G59: Y | H59: 45 | I59: IV 4/6:didnt collect full sample, gave her another kit Will bring in for 4/6 Visit, 3/6Reminded to complete NC; CTS 02/20 Called, left VM. Given day of 3rd yr MRI; Call, VM, and text on 02/12/26 CTS | L59: TRUE
A60: DBS-1106 | B60: Complete | D60: DBS-0971 | E60: 46055 | F60: 9434636106196278179309 | G60: Y | H60: 46 | I60: Given day of 3rd yr MRI. | J60: 46063 | L60: TRUE
A61: DBS-1119 | B61: Failed to Complete | D61: DBS-0956 | E61: 46056 | F61: 9434636106196278179323 | G61: Y | H61: 47 | I61: Given day of 3rd yr MRI; Reminded to complete 02/10/26 - CTS | J61: 46065 | L61: TRUE
A62: DBS-1133 | B62: Complete | D62: DBS-0771 | E62: 46058 | F62: 9434636106196278179330 | G62: Y | H62: 48 | I62: Given day of 3rd yr MRI; Called to remind, Dropped off in mailbox today 02/10/26 CTS | J62: 46066 | L62: TRUE
A63: DBS-1134 | B63: Complete | D63: DBS-0918 | E63: 46057 | F63: 9434636106196278179361 | G63: Y | H63: 49 | I63: 4/16/26 JE Said she completed but her son did not mail it out. And would not like to do another one. Opting out ;; 3/6 Reminded to complete NC CTS 02/20: Called and reminded to complete. Given day of 3rd yr MRI; Called to remind 02/10/2026 CTS, Sent reminder text on 02/17/26 CTS; | L63: TRUE
A64: DBS-1139 | B64: Not offered | D64: DBS-1039 | E64: 46058 | F64: 9434636106196278179286 | G64: Y | H64: 50 | I64: Given day of 3rd yr MRI; Called to remind, will send tomorrow morning 2/10/26 CTS | J64: 46066 | L64: TRUE
A65: DBS-1142 | B65: Declined | D65: DBS-0982 | E65: 46076 | F65: 9434636106196289209613 | G65: Y | H65: 51 | I65: CT: (Daughter sent out empty stool kit, expressed interest in still doing sample) MJ 03/05: Kit arrived to office,,does not seemed used CTS 03/04 Would like another stool kit. CTS 03/03 Dropped off empty box w/o sample inside. CTS 02/27 Called, left vm, text to remind. MJ 02/23: Given to pt after NP | J65: 46086 | K65: (empty box) | L65: TRUE
A66: DBS-1143 | B66: Complete | D66: DBS-1019 | E66: 46072 | F66: 9434636106196285628449 | G66: Y | H66: 52 | I66: Given day of 3rd yr visit , - replaced label good to use | J66: 46076 | L66: TRUE
A67: DBS-1152 | B67: Complete | D67: DBS-0770 | E67: 46065 | F67: NEW: 9402236206256001011282 9434636106196281858796 | G67: Y | H67: 53 | I67: MJ 03/30: Needs new label,,will email him one to use...confirmed he recived the email CTS 03/10 'Tracking number unavailable' on USPS website? 3/6 Reminded to complete NC CTS 02/27 Called, left vm, text CTS 02/20: Called, left VM MJ 02/12: given after MRI | L67: TRUE
A68: DBS-1156 | B68: Complete | D68: DBS-1071 | E68: 46083 | F68: 9434636106196292961089 | G68: Y | H68: 54 | I68: CTS 03/10 On its way back 3/6 Reminded to complete NC MJ 03/02: Given after MRI | J68: 46091 | L68: TRUE
A69: DBS-1160 | B69: Complete | D69: DBS-0982 (new one) | E69: 03/09/26 MAILED by MJ | F69: 9434636106196296927401 | G69: Y | H69: 55 | I69: - new one for 0982, being mailed out monday 3/9 | L69: TRUE
A70: DBS-1167 | B70: Failed to Complete | D70: DBS-1725 | E70: 46077 | F70: 9434636106196289209675 | G70: Y | H70: 56 | I70: 4/10 NC reminded 03/18 CTS Called to remind, still wants to send 3/13 reminded to complete 3/6 Reminded to complete NC Given day of 2nd yr visit. 2/25/26 JE | L70: TRUE
A71: DBS-1187 | B71: Not offered | D71: DBS-1703 | E71: 46098 | F71: 9434636106196300749616 | G71: Y | H71: 57 | I71: 4/10 NC reminded CTS 03/24 Called to remind. given on 3/17 | L71: TRUE
A72: DBS-1190 | B72: Failed to Complete | D72: DBS-0940 | E72: 46085 | F72: 9434636106196292961133 | G72: Y | H72: 58 | I72: 4/23 USPS sent unable to locate message | L72: TRUE
A73: DBS-1202 | B73: Not offered | D73: DBS-1076 | E73: 46113 | F73: 9434636106196308166446 | G73: Y | H73: 59 | I73: 04/17 CTS: Called; left VM reminder4/10 Reminded NC MJ 04/01: Given during 3rd yr visit | L73: TRUE
A74: DBS-1218 | B74: Complete | D74: DBS-0982 | E74: MJ 03/18: Mailed out on 03/18,,arriving to pt on 03/21/26 (tracking #:9400136106196340383984) | F74: 9434636106196302742387 | G74: Y | H74: 60 | I74: CTS 03/23 Will send on 04/06, kit arrived as she was departing for Mexico, will send upon return; -final for 0982, will be mailed out this week | J74: 46127 | L74: TRUE
A75: DBS-1231 | B75: Complete | D75: DBS-1000 | E75: 46118 | F75: 9434636106196311883163 | G75: Y | H75: 61 | I75: IV 4/6:didnt collect full sample, gave her another kit, said she'll send out tomorrow | J75: 46122 | L75: TRUE
A76: DBS-1241 | B76: Not offered | D76: DBS-1030 | E76: 46125 | F76: 9402236206256001046628 | G76: Y | I76: MJ 04/13; Given during visit MJ 04/09:Kit prepped | J76: 46132 | L76: TRUE
A77: DBS-1246 | B77: Failed to Complete | D77: DBS-1076 | E77: MJ- Mailed out on 04/21/26 | F77: 9402236206256001051783 | G77: Y | H77: 63 | I77: NC 4/24 Send reminder MJ 04/13; Given during visit MJ 04/09:Kit prepped | J77: 46140 | L77: TRUE
A78: DBS-1263 | B78: Failed to Complete | D78: DBS-1263 | E78: 46133 | F78: 9402236206256001075185 | G78: Y | H78: 64 | I78: 6/9 NC sent reminder 5/18 NC sent reminder 5/12/NC sent reminder | L78: TRUE
A79: DBS-1276 | B79: Complete | D79: DBS-1079 | E79: 46148 | F79: 9402236206256001099204 | G79: Y | H79: 65 | I79: 5/18 NC sent reminder 5/12 NC sent remindeMJ 05/06: Kit given during Year 3 visit | J79: 46160 | L79: TRUE
A80: DBS-1284 | B80: Not offered | D80: DBS-1190 | E80: 46149 | F80: 9402236206256001099211 | G80: Y | H80: 66 | I80: 6/9 NC sent reminder 5/18 NC sent reminder 5/12 NC sent reminder MJ 05/07: Kit given during Year 3 visit | L80: TRUE
A81: DBS-1315 | B81: Failed to Complete | D81: DBS-1276 | E81: 46147 | F81: 9402236206256001099334 | G81: Y | H81: 67 | I81: 5/22 arrived. 5/18 NC sent reminder said will send next day; 5/12 NC sent reminder Given day of visit. 5/5/26 -JE | J81: 46164 | K81: 46164 | L81: TRUE
A82: DBS-1318 | B82: Not offered | D82: DBS-1009 | E82: 46154 | F82: 9402236206256001140487 | H82: 68 | I82: Given day of visit 05/12/26 CTS | J82: 46156 | K82: 46156 | L82: TRUE
A83: DBS-1335 | B83: Failed to Complete | D83: DBS-1218 | E83: 46155 | F83: 9402236206256001140494 | G83: Y | H83: 69 | I83: 5/22 on the way (expected 5/26) 5/18 NC sent reminder Given day of visit 05/13/26 MJ (Replaced DBS-1160 on MRI day) | J83: 46168 | L83: TRUE
A84: DBS-1341 | B84: Not offered | D84: DBS-1160 | E84: 46162 | F84: 9402236206256001140500 | G84: Y | H84: 70 | I84: 6/16 NC sent reminder 6/9 NC sent reminder Given the day of visit. 5/20/26 JE | J84: 46198 | L84: TRUE
A85: DBS-1347 | B85: Not offered | D85: DBS-1231 | E85: 46169 | F85: 9402236206256001140517 | G85: Y | H85: 71 | I85: Given day of cv visit and recommended to bring tomorrow to MRI. 5/27/27 JE | J85: 46170 | L85: TRUE
A86: DBS-1368 | B86: Complete | D86: DBS-1133 | E86: 46178 | F86: 9402236206256001171504 | G86: Y | H86: 72 | I86: Recieved and stored 08/13/26 CTS 6/16 NC sent reminder Given day of 3yr all day visit 6/5/26 JE | J86: 46247 | L86: TRUE
A87: DBS-1373 | B87: Failed to Complete
A88: DBS-1385 | B88: Not offered
A89: DBS-1387 | B89: Not offered
A90: DBS-1388 | B90: Not offered
A91: DBS-1392 | B91: Complete
A92: DBS-1396 | B92: Not offered
A93: DBS-1415 | B93: Not offered
A94: DBS-1418 | B94: Failed to Complete
A95: DBS-1455 | B95: Not offered
A96: DBS-1462 | B96: Not offered
A97: DBS-1480 | B97: Complete
A98: DBS-1491 | B98: Complete
A99: DBS-1492 | B99: Dropout | C99: drop out
A100: DBS-1497 | B100: Complete
...

Sheet Study Partner
B1: Survey Link Sent/Mailed | C1: Completed | D1: Notes | E1: Record ID/location | F1: Complete = | G1: =COUNTIF(C3:C199,TRUE) -> 132 | L1: Buenas tardes! Soy Noelle del estudio de diabetes y memoria aqui de USC. Estoy haciendo un seguimiento con respecto a la encuesta del compañero del estudio. Como recordatorio, esto es un requisito para el estudio. Su compañero de estudio puede ser cualquier persona que le conozca lo Asegúrese de que su compañero de estudio complete su nombre donde dice el nombre del participante y su nombre donde pide el nombre del compañero de estudio.suficiente como para poder responder a las preguntas de la encuesta relacionadas con su memoria. Por favor NO llene la encuesta usted mismo. Puede acceder al enlace aquí y enviárselo a ellos. https://redcap.link/DiabetesBrainStudyPartner Gracias!
F2: Incomplete = | G2: =COUNTIF(C1:C199,false) -> 27
A3: DBS-0843 | B3: LC 02/18 Sent survey Link | D3: 6/22/26 NC sent reminder 1/26 NC Sent text 9/2 NC sent email NC 8/7 Sent text NC 7/9 Sent text NC 6/2: F/u for survey LC 04/02: F/u for survey; LC 03/12: F/u for survey; LC 02/26: F/u for survey; | I3: Not Completed
A4: DBS-0956 | B4: LC 02/18 Sent survey link | C4: FALSE | D4: 8/21/26 NC sent text 7/17/26 Email sent NC; 2/3/26 JE Reminder at MRI visit. ;; 1/26 NC Sent text (did not go through) 9/2 NC sent email NC 8/7 Sent text, not delivered. NC 7/9 Sent text NC 6/2: F/u for survey, LC 02/26: Text failed to send; | I4: Completed
A5: DBS-0916 | B5: LC 02/18 Sent Survey Link | C5: TRUE | D5: NC 6/2: F/u for survey, LC 02/26: F/u for survey; | E5: #37 | I5: Says don't have study partner
A6: DBS-0918 | B6: LC 02/18 Sent Survey Link | C6: FALSE | D6: 9/1/2026 JE Participant is out of town. Relative recently passed. Check back at a later time. ;; 8/21/26 NC sent text; 7/17/26 Email sent NC;6/22/26 NC sent reminder text 4/16/26 JE Still pending. It had been started but never complted. Explained and re shared link. Asked if calling was ok but she shared study partner has limited free time so she will talk to her and ask to complete soon.;; Following up... 2/4/26 JE Said her sis already completed it. Resent link jic. ;; 1/26 NC Sent text 9/16 sent email (invalid) 8/18 NC sent follow up text NC 7/25 Sent Text TB 6/25: Sent text NC 6/2: invalid email LC 04/02: F/u for survey; LC 03/12: F/u for survey; LC 02/26: F/u for survey;
A7: DBS-0987 | B7: LC 02/18 Sent Survey Link | C7: TRUE | D7: LC 02/26: F/u for survey | E7: #114
A8: DBS-0798 | B8: LC 02/18 Sent Survey Link | D8: LC 02/26: F/u for survey | E8: #97 | H8: Unknown
A9: DBS-0876 | B9: LC 02/18 Sent Survey Link | E9: #8 | H9: Lenin Zepeda? | I9: #310 | J9: (both zepeda's already filled out by spouses), not for 0918 either
A10: DBS-1016 | B10: LC 02/18 Sent Survey Link | C10: FALSE | D10: 9/25 NC sent text; 8/21/26 NC sent text; 7/17/26 Email sent NC; 6/22/26 NC sent reminder text 1/28 JE Reminded and resent link at visit. ;; 1/26 NC Sent text 9/2 NC sent email NC 8/7 Sent text NC 7/9 Sent text NC 6/2: F/u for survey; LC 04/02: F/u for survey; LC 03/12: F/u for survey; LC 02/26: F/u for survey; | H10: Leticia Gaeta | I10: #314 | J10: 3/17 sent email, sent text
A11: DBS-0982 | B11: LC 02/18 Sent Survey Link | C11: TRUE | D11: LC 03/12: F/u for survey; LC 02/26: F/u for survey | E11: #85
A12: DBS-1019 | B12: GT 2/13 Sent Survey Link | C12: TRUE | D12: NC 6/2/25 Done | E12: #79 and #113 (filled out twice)
A13: DBS-0940 | B13: LC 02/18 Sent Survey Link | C13: FALSE | D13: 9/25 NC sent text; 8/21/26 NC sent text; 7/17/26 Email sent NC; 6/22/26 NC sent reminder text MJ 03/04: text sent w/ link 1/26 NC Sent text 9/16 NC sent email 8/18 NC sent follow up text NC 7/25 Sent text TB 6/25 Sent text NC 6/6: invalid email LC 04/02: F/u for survey; LC 03/12: F/u for survey; LC 02/26: F/u for survey
A14: DBS-1039 | B14: LC 02/18 Sent Survey Link | C14: TRUE | E14: #54 | G14: https://redcap.link/DiabetesBrainStudyPartner
A15: DBS-1030 | B15: LC 02/18 Sent Survey Link | C15: TRUE | D15: LC 03/12: F/u for survey; LC 02/26: F/u for survey | E15: #73
A16: DBS-0985 | B16: LC 02/18 Sent Survey Link | D16: 1/26 NC Sent text 9/2 NC sent email NC 8/7 Sent text NC 7/9 Sent text NC 6/6: F/u for survey; LC 04/02: F/u for survey; LC 03/12: F/u for survey; LC 02/26: F/u for survey
A17: DBS-0971 | B17: LC 02/18 Sent Survey Link | C17: TRUE | D17: LC 04/02: F/u for survey; LC 03/12: F/u for survey; LC 02/26: F/u for survey | E17: #153
A18: DBS-0969 | B18: LC 02/18 Sent Survey Link | C18: TRUE | D18: LC 02/26: F/u for survey | E18: #105
A19: DBS-1096 | B19: LC 02/18 Sent Survey Link | D19: 1/26 NC Sent text 9/2 NC sent email NC 8/7 Sent text, not delivered NC 7/9 Sent text NC 6/6: F/u for survey; LC 03/12: Text not working; LC 02/26: F/u for survey
A20: DBS-1000 | B20: LC 02/18 Sent Survey Link | C20: FALSE | D20: 9/25 NC sent text; 8/21/26 NC sent text; 7/17/26 Email sent NC; 6/22/26 NC sent reminder text IV 4/6: surverys not complete sent her each one to do, 1/26 NC Sent text 9/16 NC sent email 8/18 NC sent follow up text NC 7/25 Sent text TB: 6/25 Sent text NC 6/9: invalid email; LC 04/02: F/u for survey; LC 03/12: F/u for survey; LC 02/26: F/u for survey
A21: DBS-1071 | B21: LC 02/18 Sent Survey Link | C21: TRUE | D21: IV 3/11: said she'll have her husband complete today MJ 3/2: Link sent again to pt 1/26 NC Sent text 9/2 NC sent email NC 8/7 Sent text NC 7/9 Sent text NC 6/9: F/u for survey; LC 04/02: F/u for survey; LC 03/12: F/u for survey; LC 02/26: F/u for survey | E21: #349
A22: DBS-1012 | B22: LC 02/18 Sent Survey Link | C22: TRUE | D22: NC 7/9 Sent text NC 6/9: F/u for survey; LC 04/02: F/u for survey; LC 02/26: Out on vacation. F/u in two weeks | E22: #248
A23: DBS-1119 | B23: LC 02/18 Sent Survey Link | C23: TRUE | D23: LC 02/26: F/u for survey | E23: #98
A24: DBS-1053 | B24: LC 02/18 Sent Survey Link | D24: LC 04/02: F/u for survey; LC 02/26: F/u for survey
A25: DBS-1152 | B25: LC 02/18 Sent Survey Link | C25: TRUE | E25: #26
A26: DBS-1106 | B26: LC 02/18 Sent Survey Link | C26: TRUE | D26: LC 04/02: F/u for survey; LC 03/12: F/u for survey; LC 02/26: F/u for survey | E26: #122
A27: DBS-1009 | B27: LC 02/18 Sent Survey Link | C27: TRUE | D27: LC 03/12: F/u for survey; LC 02/26: F/u for survey | E27: #129
A28: DBS-1085 | B28: LC 02/18 Sent Survey Link | C28: TRUE | D28: LC 02/26: F/u for survey | E28: #100
A29: DBS-1004 | B29: LC 02/18 Sent Survey Link | C29: TRUE | D29: LC 04/02: F/u for survey; LC 03/12: F/u for survey; LC 02/26: F/u for survey | E29: #168
A30: DBS-1142 | B30: LC 02/18: Completed on redcap | C30: TRUE | E30: #11
A31: DBS-1199 | B31: LC 02/18: Completed on redcap
A32: DBS-1134 | B32: LC 02/19: Sent survey link | C32: TRUE | E32: #33
A33: DBS-1059 | B33: LC 02/19: Sent survey link | C33: TRUE | D33: NC 8/7 Sent text NC 7/9 Sent text NC 6/9: F/u for survey; LC 04/02: F/u for survey; LC 03/03: F/u for survey | E33: #259
A34: DBS-1143 | B34: LC 02/19: Sent survey link | C34: TRUE | D34: 7/17/26 Email sent NC; 6/22/26 NC sent reminder JE 4/6/25 Reminded at MRI. Is going to ask his daughter to complete soon. ;; 1/30/26 Text sent NC 9/2 NC sent email NC 8/7 Sent text NC 7/9 Sent text NC 6/9: F/u for survey; LC 03/03: F/u for survey | E34: #376
A35: DBS-1167 | B35: LC 02/19: Sent survey link | C35: TRUE | D35: 9/1/26 JE Sent link to her son. ;; 8/21/26 NC sent text; 7/17/26 Email sent NC; 6/22/26 NC sent reminder 5/6/26 Sent link again. Said her son would complete. JE ;; 1/30/26 Text sent NC 9/2 NC sent email IV 8/11: reminded at visit, said shed give to son NC 8/7 Sent text NC 7/9 Sent text NC 6/9: F/u for survey; LC 03/03: F/u for survey | E35: #387
A36: DBS-1160 | B36: LC 02/19: Sent survey link | C36: TRUE | D36: LC 02/25: Participant filled out their information under SP but SP filled out forms and consented | E36: #21
A37: DBS-1190 | B37: LC 02/19: Sent survey link | C37: TRUE | D37: 1/30/26 Text sent NC 9/2 NC sent email NC 8/7 Sent text NC 7/9 Sent text NC 6/9: F/u for survey; LC 03/03: F/u for survey NC 5/16: Only consent form completed | E37: #326
A38: DBS-1095 | B38: LC 02/19: Sent survey link | C38: TRUE | D38: LC 03/03: F/u for survey | E38: #164
A39: DBS-1241 | B39: LC 02/19: Sent survey link | C39: TRUE | D39: NC 8/7 Sent text NC 7/9 Sent text NC 6/9: F/u for survey; LC 03/03: F/u for survey | E39: #264
A40: DBS-1231 | B40: LC 02/19: Sent survey link | C40: TRUE | D40: LC 03/03: F/u for survey | E40: #139
A41: DBS-1263 | B41: LC 02/19: Sent survey link | C41: TRUE | D41: IV 4/21: reminded at visit, will resent link 1/30/26 Text sent NC 9/2 NC sent email NC 8/7 Sent text NC 7/9 Sent text NC 6/9: F/u for survey; LC 03/03: F/u for survey; will complete at end of month. Out of country. | E41: #352
A42: DBS-1276 | B42: LC 02/19: Sent survey link | C42: TRUE | E42: #35
A43: DBS-1202 | B43: LC 02/19: Sent survey link | C43: TRUE | D43: LC 03/03: F/u for survey | E43: #103
A44: DBS-1246 | B44: LC 02/19: Sent survey link | C44: TRUE | D44: LC 03/03: F/u for survey | E44: #90
A45: DBS-1133 | B45: LC 02/19: Sent survey link | C45: TRUE | E45: #46
A46: DBS-1303 | B46: LC 02/19: Sent survey link | E46: #76
A47: DBS-1315 | B47: LC 02/19: Sent survey link | D47: LC 03/03: F/u for survey | E47: #101
A48: DBS-1387 | B48: LC 02/19: Sent survey link | C48: TRUE | E48: #47
A49: DBS-1156 | B49: LC 03/13: Completed forms | C49: TRUE | D49: LC 03/03: F/u for survey | E49: #117
A50: DBS-1347 | B50: LC 02/19: Sent survey link | C50: TRUE | D50: LC 03/03: F/u for survey | E50: #92
A51: DBS-1608 | B51: GT 2/13 Sent Survey Link | C51: TRUE | D51: NC 8/7 Sent text NC 7/9 Sent text NC 6/9: F/u for survey; LC 03/03: Check to see if SP has been filled. Consent form signed NC 5/16: only consent form signed | E51: #184
A52: DBS-1662 | B52: GT 2/13 Sent Survey Link | C52: TRUE | D52: 7/17/26 Email sent NC; 6/22/26 NC sent reminder1/30/26 Text sent NC 9/2 NC sent email NC 8/7 Sent text NC 7/9 Sent text NC 6/9: F/u for survey;LC 03/03: F/u for survey | E52: #375
A53: DBS-1695 | B53: GT 2/13 Sent Survey Link | C53: FALSE | D53: 9/25/26 NC sent text; 9/1/26 JE Touching base with her co-worker. Will follow up. ;; 8/21/26 NC sent text; 7/17/26 Email sent NC; 6/22/26 NC sent reminder 1/30/26 Text sent NC 9/2 NC sent email NC 8/7 Sent text NC 7/9 Sent text NC 6/9: F/u for survey; NC 5/16: only consent form started
A54: DBS-1674 | B54: GT 2/13 Sent Survey Link | C54: TRUE | E54: #3
A55: DBS-1630 | B55: GT 2/13 Sent Survey Link | E55: #82
A56: DBS-1705 | B56: GT 2/13 Sent Survey Link | C56: TRUE | D56: LC 03/10: F/u for survey | E56: #111
A57: DBS-1734 | B57: GT 2/13 Sent Survey Link | C57: TRUE | D57: NC 8/7 Sent text NC 7/9 Sent text NC 6/9: F/u for survey; LC 03/10: F/u for survey | E57: #260, #261
A58: DBS-1677 | B58: GT 2/13 Sent Survey Link | D58: LC 03/10: F/u for survey
A59: DBS-1218 | B59: LC 02/20: Sent survey link | C59: FALSE | D59: 1/30/26 Text sent NC 9/2 NC sent email NC 8/7 Sent text NC 7/9 Sent text NC 6/9: F/u for survey; LC 03/10: F/u for survey
A60: DBS-1392 | B60: LC 02/20: Sent survey link | C60: TRUE | D60: LC 03/10: F/u for survey | E60: #123
A61: DBS-1415 | B61: LC 02/20: Sent survey link | D61: 1/30/26 Text sent NC (invalid) 9/16 NC sent email (invalid) 8/18 NC sent follow up text AG 7/23 message didnt send, NC 6/9: invalid email; LC 03/10: F/u for survey
A62: DBS-1418 | B62: LC 02/20: Sent survey link | C62: TRUE | D62: LC 03/10: F/u for survey | E62: #132
A63: DBS-1388 | B63: LC 02/20: Sent survey link | C63: TRUE | D63: LC 03/10: F/u for survey | E63: #128
A64: DBS-1187 | B64: LC 02/20: Sent survey link | C64: TRUE | E64: #27
A65: DBS-1063 | B65: LC 02/20: Sent survey link | C65: TRUE | E65: #24
A66: DBS-1462 | B66: LC 02/20: Sent survey link | D66: LC 03/10: F/u for survey
A67: DBS-1341 | B67: LC 02/20: Sent survey link | C67: TRUE | D67: AG 7/23/: sent follow up text, NC 7/9 Sent text NC 6/9: F/u for survey; LC 03/10: F/u for survey | E67: #240
A68: DBS-1335 | B68: LC 02/20: Sent survey link | C68: TRUE | D68: Iv 12/4: reminded at visit, said daughter will complete 9/16 NC sent email 8/18 NC sent follow up text AG 7/23/: sent follow up text, NC 7/9 Sent text NC 6/9: F/u for survey; LC 03/10: F/u for survey | E68: #323
A69: DBS-1385 | B69: LC 02/20: Sent survey link | D69: 6/22/26 NC sent reminder 1/30 NC sent text 9/16 NC sent email 8/18 NC sent follow up text AG 7/23/: sent follow up text, NC 7/9 Sent text NC 6/9: F/u for survey; LC 03/10: F/u for survey
A70: DBS-1396 | B70: LC 02/20: Sent survey link | C70: FALSE | D70: 9/25/26 NC sent text; 8/21/26 NC sent text; 7/17/26 Email sent NC; 6/22/26 NC sent reminder 1/30 NC sent text 9/16 NC sent email 8/18 NC sent follow up text AG 7/23/: sent follow up text, TB: 6/25 Sent text NC 6/9: invalid email; LC 03/10: F/u for survey
A71: DBS-1455 | B71: LC 02/20: Sent survey link | C71: FALSE | D71: IV 9/22: confirmed no study partner, opting out 8/21/26 NC sent text; 7/17/26 Email sent NC; 6/22/26 NC sent reminder 6/10 NC called, said will do. 1/30 NC sent text 9/16 NC sent email 8/18 NC sent follow up text AG 7/23/: sent follow up text, NC 7/9 Sent text NC 6/9: F/u for survey; LC 03/10: F/u for survey
A72: DBS-1480 | B72: LC 02/20: Sent survey link | C72: TRUE | D72: LC 03/10: F/u for survey | E72: #115
A73: DBS-1139 | B73: LC 02/20: Sent survey link | D73: LC 03/10: F/u for survey
A74: DBS-1491 | B74: LC 02/20: Sent survey link | C74: TRUE | D74: LC 03/10: F/u for survey | E74: #84
A75: DBS-1373 | B75: LC 02/20: Sent survey link | C75: TRUE | D75: NC 7/9 Sent text NC 6/9: F/u for survey; LC 03/10: F/u for survey | E75: #133
A76: DBS-1492 | B76: LC 02/20: Sent survey link | D76: LC 03/10: F/u for survey
A77: DBS-1505 | B77: LC 02/20: Sent survey link | D77: 6/22/26 NC sent reminder 1/30 NC sent text 9/16 NC sent email 8/18 NC sent follow up text AG 7/23/: sent follow up text, NC 7/9 Sent text NC 6/9: F/u for survey; LC 03/10: F/u for survey
A78: DBS-1530 | B78: LC 02/20: Sent survey link | C78: TRUE | D78: 7/17/26 Email sent NC; 6/22/26 NC sent reminder 6/10 NC Called, said will do. 1/30 NC sent text 10/3 JE Reminded to complete in person. ;; 9/16 NC sent email 8/18 NC sent follow up text AG 7/23/: sent follow up text, NC 7/9 Sent text NC 6/9: F/u for survey; LC 03/10: F/u for survey | E78: #371
A79: DBS-1497 | B79: LC 02/20: Sent survey link | D79: 6/22/26 NC sent reminder 1/30 NC sent text 9/16 NC sent email 8/18 NC sent follow up text AG 7/23/: sent follow up text, NC 7/9 Sent text NC 6/9: F/u for survey; LC 03/10: F/u for survey
A80: DBS-1368 | B80: LC 02/20: Sent survey link | C80: TRUE | E80: #25
A81: DBS-1523 | B81: LC 02/20: Sent survey link | C81: TRUE | D81: NC 6/29/26 missing all forms + consent; LC 03/12: Filled out the forms in-person, missing all forms + consent
A82: DBS-1521 | B82: LC 02/20: Sent survey link | C82: TRUE | D82: NC 9/25/26 sent text; 9/1/26 Wife will complete. Link shared. ;; 8/21/26 NC sent text; 7/17/26 Email sent NC; 6/22/26 NC sent reminder1/30 NC sent text 10/28 Ivett reminded in person, said wife will complete 9/16 NC sent email 9/2 NC sent email AG 7/23/: sent follow up text, AG 7/9 sent text; NC 6/9: F/u for survey; LC 03/12: F/u for survey | E82: #389
A83: DBS-1508 | B83: LC 02/21: Sent survey link | C83: TRUE | E83: #32
A84: DBS-1622 | B84: LC 02/21: Sent survey link | C84: TRUE | D84: LC 03/12: F/u for survey | E84: #169
A85: DBS-1605 | B85: LC 02/21: Sent survey link | C85: TRUE | D85: 6/22/26 NC sent reminder text 1/30 NC sent text IV 11/6: reminded at visit 9/16 NC sent email 8/18 NC sent follow up text AG 7/23/: sent follow up text, AG 7/9 sent text; NC 6/9: F/u for survey; LC 03/12: F/u for survey | E85: #363
A86: DBS-1575 | B86: LC 02/21: Sent survey link | C86: TRUE | D86: NC 6/23 Filled out names switched NC 6/9: F/u for survey; LC 03/12: F/u for survey | E86: #202
A87: DBS-1579 | B87: LC 02/21: Sent survey link | C87: TRUE | E87: #48
A88: DBS-1576 | B88: LC 02/21: Sent survey link | D88: LC 03/12: F/u for survey | E88: #134
A89: DBS-1625 | B89: LC 02/21: Sent survey link | D89: LC 03/12: F/u for survey
A90: DBS-1284 | B90: LC 02/21: Sent survey link | C90: TRUE | E90: #119
A91: DBS-1593 | B91: LC 02/21: Sent survey link | C91: FALSE | D91: 8/21/26 NC sent text; 7/17/26 Email sent NC; 1/30 NC sent text (invalid) IV 11/18: resent at visit 9/16 NC sent email 8/18 NC sent follow up text AG 7/23/: sent follow up text, AG 7/9 sent text; NC 6/9: F/u for survey; LC 03/12: F/u for survey
A92: DBS-1556 | B92: LC 02/21: Sent survey link | C92: TRUE | D92: 8/18 NC sent follow up text AG 7/23/: sent follow up text, AG 7/9 sent text; NC 6/9: F/u for survey; | E92: #267
A93: DBS-1601 | B93: LC 02/21: Sent survey link | C93: TRUE | D93: NC 6/9: F/u for survey; LC 03/03: F/u for survey | E93: #200
A94: DBS-1629 | B94: LC 02/21: Sent survey link | C94: TRUE | D94: IV 8/14: searched up number, foudn they were related AG 7/23/: sent follow up text, AG 7/9 sent text; NC 6/9: F/u for survey; LC 03/12: F/u for survey | E94: #130
A95: DBS-1645 | B95: LC 02/21: Sent survey link | D95: LC 03/12: F/u for survey
A96: DBS-1664 | B96: LC 02/21: Sent survey link | C96: TRUE | D96: 9/1/26 JE Daughter will complete. ;; 8/21/26 NC sent text; 7/17/26 Email sent NC; 6/22/26 NC sent reminder 1/30 NC sent text IV 11/2: reminded at visit, resent link 9/16 NC sent email 8/18 NC sent follow up text AG 7/23/: sent follow up text, AG 7/9 sent text; NC 6/9: F/u for survey; LC 03/13: F/u for survey | E96: #385
A97: DBS-1619 | B97: LC 02/21: Sent survey link | C97: FALSE | D97: 9/25/26 NC sent text; 9/2/26 JE Confirmed linked recived. Mentioend that the person did not live with him anymoe so I explained that he can share the link with anyone who he thinks would have isight on him despite location. ;; 8/21/26 NC sent text; 7/17/26 Email sent NC; 6/22/26 NC sent reminder 1/30 NC sent text, IV 12/8: reminded, sent link 9/16 NC sent email 8/18 NC sent follow up text AG 7/23/: sent follow up text,AG 7/9: sent text; NC 6/9: F/u for survey; LC 03/13: F/u for survey
A98: DBS-0908 | B98: IV 02/21: Done in person by spouse | C98: TRUE | E98: #28
A99: DBS-0978 | B99: IV 02/21: Done in person by spouse | C99: TRUE | E99: #29
A100: DBS-0028 | B100: LC 02/24 sent link | C100: FALSE | D100: 9/25/26 NC sent text; 8/21/26 NC sent text; 7/17/26 Email sent NC; 6/22/26 NC sent reminder text 1/30 NC sent text, 9/16 NC sent email 8/18 NC sent follow up text AG 7/23/: sent follow up text, AG 7/9: sent text; NC 6/9: F/u for survey; LC 03/13: F/u for survey
...

Sheet DropoutsNo longer eligible
A1: AN | B1: ID | C1: SV Date | D1: IV Site | E1: Initial Visit Date | F1: IV Notes | G1: BD Date | H1: BD Notes | I1: BD Scheduling Notes | J1: NP Date | K1: NP Scheduling Notes | L1: MRI Date | M1: MRI Scheduling Notes | N1: LP Date | O1: CV Date | P1: CV Scheduling Notes | Q1: CDR Date | R1: CDR Scheduling Notes | S1: Conference Date | T1: Notes
B2: DBS-0119 | C2: 44970 | D2: USC | E2: 45012 | F2: LC 03/27: Decided to no longer participate. Thought the study was to find preventions for diabetes. | G2: 45012
B3: DBS-0212 | C3: 45001 | D3: USC | E3: Enrolled | F3: LC 03/24: No longer elligble. Does not have a study partner | G3: 45009
B4: DBS-0128 | C4: 45002 | D4: USC | E4: 45020 | F4: LC 03/22: Call to schedule: LC 04/4: Call to r/s. No response from lead. Unable to reach after several attempts. | G4: 45020
B5: DBS-0075 | C5: 44932 | D5: USC | E5: RESCHEDULE | F5: Could not reach; LC 01/17: Left vm to schedule IV | G5: RESCHEDULE
B6: DBS-0345 | C6: 45084 | F6: 6/8 LC: During SV participant informed us about a stroke they had
B7: DBS-0339 | C7: 45076 | F7: LC 06/13: Unable to participate at this time
B8: DBS-0010 | C8: 45042 | F8: GT 6/21: No longer interested in the study; GT 5/24: Will call me back currently working; GT 5/16: Asked to be called tomorrow; GT 4/26: emailed ICF
B9: DBS-0131 | C9: 44987 | D9: USC | E9: 44998 | G9: 44998 | J9: LC 05/16: Left vm; LC 05/19: sent txt msg. Out of country. Call back on week of 06/12; LC 06/22: Left vm | M9: Opt Out
B10: DBS-0294 | F10: GT 6/21: Left vm; GT 6/15: Left vm and text at 10:47; GT 5/24: Left vm and text at 3:53; GT 5/16: Left vm at 2:09; GT 5/11: Left vm to schedule IV & emailed ICF
B11: DBS-0061 | D11: USC | E11: 45071 | F11: GT 6/21: Left vm at 4:47 PM; GT 5/25 Called left vm; GT 5/16: Left vm to schedule; GT 4/25: Left vm to schedule IV
B12: DBS-0612 | C12: 45154 | E12: 45163 | F12: LC 08/25: Scheduled for NP, BD, CV. No response from lead. Could not reach. | O12: 45163
B13: DBS-0545 | C13: 45148 | F13: LC 08/17: No longer proceeding with participant. No interest. SV BD done
B14: DBS-0254 | C14: Docusign | D14: 45118 | E14: Enrolled | F14: 45140 | G14: 45133 | I14: 45133 | K14: 45212 | L14: LC 10/25: MRI unsuccesful. Considered dropout | M14: 45141 | N14: LP unsuccessful | O14: 45133
B15: DBS-0539 | C15: USC | D15: 45161 | E15: Enrolled | G15: 45161 | I15: 45161 | L15: 45209 | M15: 45191 | O15: 45161
B16: DBS-0738 | C16: USC | D16: 45226 | E16: GT Enrolled | G16: 45226 | I16: 45226 | L16: LC 12/11: Participant has tumor stage 2 or 3; LC 12/06: Sent text; LC 12/04: Text sent to scheduled MRI | M16: Thinking | O16: 45226
B17: DBS-0085 | C17: Docusign | D17: 45161 | E17: LC Enrolled | G17: 45168 | I17: 45168 | K17: 45307 | L17: NO SHOW LC 12/04: Left vm @10:45am; GT 11/30: Left vm @1pm | M17: Opt Out | O17: 45168
B18: DBS-0778 | C18: USC | D18: 45232 | E18: LC Enrolled | G18: 45232 | I18: 45232 | K18: 45296 | L18: LC 01/05: Unable to complete 2-hour post glucose scan. Felt nauseous after glucose drink | M18: 45246 | O18: 45232
B19: DBS-0742 | C19: USC | D19: 45223 | E19: GT: Signed ICF | G19: 45273 | I19: 45223 | K19: 45331 | L19: MJ 02/09: Failed MRI, Participant got anxious//Baseline BD was done | M19: Reschedule for Jan | O19: 45223
B20: DBS-0844 | C20: USC | D20: 45273 | F20: 45265 | G20: 45273 | I20: 45273 | K20: 45342 | M20: 45317 | O20: 45273
B21: DBS-0672 | C21: USC | D21: 45217 | E21: GT: Signed ICF | G21: 45217 | J21: 01/24: Sent email; 12/5 GT: Left vm MJ 12/15: Left VM,sent text & email | K21: UNABLE TO CONTACT to schedule visits | P21: GT 11/30: Left vm @2:50pm MJ 12/15: Left VM,sent text & email
B22: DBS-0907 | C22: USC | D22: 45274 | E22: GT: Signed ICF | G22: 45274 | I22: 45278 | J22: LC 03/01: Sent text to schedule | L22: LC 03/01: Sent text to schedule | O22: 45274 | R22: LC 03/05: Cannot continue at this time
B23: DBS-0735 | C23: USC | D23: No show in 3/26/24 | E23: LC 02/27: F/U to schedule visits | G23: 45377 | I23: 45377 | O23: 45377
B24: DBS-0873 | C24: USC | D24: 45261 | E24: GT: Signed ICF | G24: 45261 | I24: 45261 | K24: RESCHEDULE | M24: Opt Out | O24: 45261
B25: DBS-1245 | C25: 45420 | E25: Could not continue bc health issues
B26: DBS-1132 | C26: USC | D26: 45463 | E26: NO Showed to IV | G26: 45463 | I26: 45463 | O26: 45463
B27: DBS-1404 | C27: 45481
B28: DBS-0910 | C28: 45460
B29: DBS-1233 | C29: USC | D29: 45419 | G29: 45419 | I29: 45419 | K29: 45495 | L29: Could not complete scan | M29: Opt Out | O29: 45419 | Q29: 9 | R29: 83
B30: DBS-0803 | C30: USC | D30: 45338 | E30: GT: Signed ICF | F30: 45338 | G30: 45338 | I30: 45358 | J30: LC 02/23: Sent text to schedule | K30: 45492 | L30: Could not complete scans | M30: Opt Out | O30: 45372 | P30: LC 02/23: Sent text to schedule | Q30: 7 | R30: 61
B31: DBS-1048 | C31: USC | D31: 45386 | E31: LC 02/08: pTau tube needed | F31: 45386 | G31: 45386 | I31: 45386 | K31: 45484 | L31: Could not complete scans | M31: Opt Out | O31: 45386 | Q31: 8 | R31: 70
B32: DBS-1314 | C32: USC | D32: 45496 | E32: No showed to visit; LC 06/19: Left vm and stated they will call back on Friday
B33: DBS-1174 | C33: USC | D33: 45383 | E33: GT ICF signed in person same day as SV | G33: 45383 | I33: 45425 | J33: GT 4/18 sent text to schedule | K33: 45513 | L33: Failed MRI | M33: Opt Out | O33: 45425 | Q33: 8 | R33: 75
B34: DBS-1306 | C34: USC | D34: 45519 | E34: GT 9/18 Unable to continue bc of work schedule; 9/17: Left vm + Text; LC 07/31: Left vm @9:47am; wants to know about this friday availability | G34: 45519 | I34: 45519 | O34: 45519 | Q34: 10 | R34: 99
B35: DBS-1473 | C35: USC | E35: Out of country, never could schedule IV
B36: DBS-1537 | I36: ^ ID's above include SV
A38: Noted on Redcap | C38: Dropout date | I38: :16 DQ (not "officially" enrolled but on RedCap)
A39: TRUE | B39: DBS-0542 | C39: 45405 | D39: 2nd year | E39: Works full time can no longer participate
A40: TRUE | B40: DBS-1053 | C40: 45779 | D40: Baseline | E40: Baseline MRI not done. Rescheduled April appointment, no more remaining dates
A41: TRUE | B41: DBS-1199 | C41: 45779 | D41: Baseline | E41: Baseline MRI not done. Rescheduled April appointment, no more remaining dates
A42: TRUE | B42: DBS-1630 | C42: 45777 | D42: Baseline | E42: Failed Baseline MRI. Scan did not start due to difficulty breathing (congestion).
A43: TRUE | B43: DBS-1677 | C43: 45779 | D43: Baseline | E43: Baseline MRI not done. Rescheduled April appointment, no more remaining dates
A44: TRUE | B44: DBS-1462 | C44: 45621 | D44: Baseline | E44: Failed Baseline MRI, could not start 1st scan
A45: TRUE | B45: DBS-1139 | C45: 45643 | D45: Baseline | E45: Failed Baseline MRI, could not comfortably fit inside
A46: TRUE | B46: DBS-1492 | C46: 45775 | D46: Baseline | E46: Baseline MRI not done. Did not show to appointment
A47: TRUE | B47: DBS-1625 | C47: 45702 | D47: Baseline | E47: Baseline MRI not done; Could not scan due to unknown metal in head
A48: TRUE | B48: DBS-1645 | C48: 45779 | D48: Baseline | E48: Baseline MRI not done. Rescheduled April appointment, no more remaining dates
A49: TRUE | B49: DBS-0268 | C49: 45386 | D49: 2nd Year | E49: Unable to get in contact with participant to schedule 2nd year visits.Called 8x, emailed, and mailed letter. No response
A50: TRUE | B50: DBS-0108 | C50: 45616 | D50: 2nd Year | E50: Cannot reach after multiple attempts of phone call, text, email, mailed letter | G50: f
A51: TRUE | B51: DBS-0808 | C51: 45716 | D51: 2nd Year | E51: Cannot reach after multiple outreach attempts | G51: f
A52: TRUE | B52: DBS-1092 | C52: 45810 | D52: 2nd Year | E52: Caring for a sick person. Can no longer participate. Requested to be removed. | G52: f
A53: TRUE | B53: DBS-0928 | C53: 45680 | D53: Baseline | E53: In Mexico, no longer wants to continue with study; Baseline MRI not done
A54: TRUE | B54: DBS-1515 | C54: 45672 | D54: Baseline | E54: Failed Baseline MRI: Only completed 1st scan MRI. Did not want to continue
A55: TRUE | B55: DBS-1554 | C55: 45680 | D55: Baseline | E55: Can't continue with study; Baseline MRI not done
A56: TRUE | B56: DBS-1684 | C56: 45772 | D56: Baseline | E56: Failed Baseline MRI. Scans did not start. The participant felt overwhelmed when going into the machine.
A57: TRUE | B57: DBS-0419 | C57: 45805 | D57: 3rd Year | E57: Lead messaged that she is moving to mexico and is no longer able to continue with study. 5/28/25 -JE | G57: f
A58: TRUE | B58: DBS-0382 | C58: 45861 | D58: 3rd Year | E58: Responded to email. He is in mex and does not anticipate returning till 3-4 yrs from now. No longer able to participate.
A59: TRUE | B59: DBS-0705 | C59: 45922 | D59: 2nd Year | E59: Sent check in message. Replied "stop". No reason given but had previously shared she was dealing with a lot of "household issues". 9/22/25 JE
A60: TRUE | B60: DBS-1576 | C60: 45951 | D60: 2nd Year | E60: IV 10/21: moving out of the country :(, can no longer come , interested if anything virtual arises
A61: TRUE | B61: DBS-0757 | C61: 45971 | D61: 3rd Year | E61: Spouse called in after receiving letter. Informed that participant passed Dec 2024 11/10/25 JE ;; Letter mailed out. All forms of contact exhausted. No answer 11/4/25 JE ;; MJ 10/28: Left VM + sent text IV 10/3: left vm, sent text IV 9/23: left vm, sent text
A62: FALSE | B62: DBS-1218 | C62: 45972 | D62: 3rd Year | E62: !! NOT DROPPED. ... No response, mailed letter sent back
A63: TRUE | B63: DBS-1415 | C63: 45972 | D63: 2nd Year | E63: No response, mailed letter sent back
A64: TRUE | B64: DBS-0414 | C64: 45982 | D64: 3rd Year | E64: Due to family matters not able to cont.
A65: TRUE | B65: DBS-0379 | C65: 45982 | D65: 3rd Year | E65: Due to family matters not able to cont.
A66: TRUE | B66: DBS-0183 | C66: 45792 | D66: 3rd Year | E66: Letter mailed out. All forms of contact exhausted. No answer 5/15/25 JE
A67: TRUE | B67: DBS-0013 | C67: 45994 | D67: 3rd Year | E67: DV 09/18: Mailed letter ;; Has not been answering. Left vm, text and email. 9/8/25 JE ;; MJ 07/28: Left VM MJ 07/24: Left VM + sent text Would like to combine visits if possible. Needs to ask for permision at work. But flexible.
A68: TRUE | B68: DBS-0219 | C68: 45994 | D68: 3rd Year | E68: Letter mailed out. All forms of contact exhausted. No answer. 11/4/25 JE ;; MJ 10/21: left vm + sent text IV 10/03: left vm sent text IV 9/23: left vm, sent text
A69: TRUE | B69: DBS-0781 | C69: 45993 | D69: 3rd Year | E69: MJ 12/02: Text message sent bc he's at work. Messaged he is moving to OK- no longer able to cont.
... A82: TRUE | B82: DBS-1303 | C82: 46168 | D82: 3rd Year | E82: Participant considered a dropout after unsuccessful contact attempts, including disconnected phone number, multiple follow-up emails, and mailed letter, with no response received. 5/26/26 JE

Sheet Dropouts Y1-4
A1: ID | B1: SV Date | C1: IV Site | D1: Initial Visit Date | E1: IV Notes | F1: BD Date | G1: BD Notes | H1: BD Scheduling Notes | I1: NP Date | J1: NP Scheduling Notes | K1: ID | L1: SV Date | M1: IV Site | N1: Initial Visit Date | O1: IV Notes | P1: BD Date | Q1: BD Notes | R1: BD Scheduling Notes | S1: NP Date | T1: NP Scheduling Notes
A2: DBS-0542 | B2: 45405 | C2: 2nd year | D2: Works full time can no longer participate
A3: DBS-0268 | B3: 45386 | C3: 2nd Year | D3: Unable to get in contact with participant to schedule 2nd year visits.Called 8x, emailed, and mailed letter. No response
A4: DBS-0108 | B4: 45616 | C4: 2nd Year | D4: Cannot reach after multiple attempts of phone call, text, email, mailed letter | F4: f
A5: DBS-0808 | B5: 45716 | C5: 2nd Year | D5: Cannot reach after multiple outreach attempts | F5: f
A6: DBS-1092 | B6: 45810 | C6: 2nd Year | D6: Caring for a sick person. Can no longer participate. Requested to be removed. | F6: f
A7: DBS-0705 | B7: 45922 | C7: 2nd Year | D7: Sent check in message. Replied "stop". No reason given but had previously shared she was dealing with a lot of "household issues". 9/22/25 JE
A8: DBS-1576 | B8: 45951 | C8: 2nd Year | D8: IV 10/21: moving out of the country :(, can no longer come , interested if anything virtual arises
A9: DBS-1415 | B9: 45972 | C9: 2nd Year | D9: No response, mailed letter sent back
A10: DBS-1497 | B10: 46013 | C10: 2nd Year | D10: IV 12/22: apologized he's no longer interested IV 12/1: left vm, sent text MJ 10/28:Left VM + sent text IV 9/23: left vm , sent text MJ 09/15: Left VM + sent text MJ 09/08: Left VM + Sent text + sent email IV 8/28: left vm, sent text IV 8/19: left vm, sent text
A11: DBS-1032 | B11: 46028 | C11: 2nd Year | D11: Call stright to operator. 1/6/26 JE ;; All forms of contact exhausted. Sent check in message. No response. 9/22/25 JE ;; IV 7/14: phone still doesnt ring 6/25 NC Mailed Letter 06/24:Call did not go through IV 6/23: call still wont go throught, sent email IV 4/23: doesnt go thru, I might be blocked, can someone else try IV 4/3: left vm, no longer answers IV 3/28: left vm, sent text, had sent 2 previous text messages IV 2/21: needs to figure out new day V 2/12: figuring out time for that say IV 2/04: texted me date, will drive LC 02/03: Left vm; IV 1/30: sent text, LC 01/28: Sent text; IV 1/27: left vm
A12: DBS-1096 | B12: 46028 | C12: 2nd Year | D12: Operator message. Phone no longer in service. 1/6/26 JE ;; All forms of contact exhausted. Straight to vm. Sent follow up check in message. No response. 9/22/25 JE ;; IV 8/28: not in service IV 7/14: straigh to vm, sent text 6/25 NC Mailed Letter IV 6/23: straight to vm, sent, sent email text IV 5/2: straight to vm, sent text IV 4/23: straight to vm, sent text IV 4/4: left vm sent text V 3/24: left vm, sent text
A13: DBS-0985 | B13: 46029 | C13: 2nd Year | D13: Does not wish to cont. 1/7/26 JE ;; IV 3/24: said she started working monday-fri, cant take days off right now, will call if she ever can? IV 2/25: texted asking for availability IV 2/13: need to reschedule, asked for dates IV 1/31: left vm @12:25pm IV 1/31: will drive
A14: DBS-1385 | B14: 46029 | C14: 2nd Year | D14: No answer. Left vm and sent text. Replied no longer able to cont. 1/7/25 JE ;; IV 9/2: texted me that he works 8-6 mon-sat, offered verterans day, or future contact IV 8/28: left vm, sent text IV 8/19: cancelled night before, left vm sent text IV 7/14: will drive
A15: DBS-1505 | B15: 46043 | C15: 2nd Year | D15: Unable to leave vm. No answer. All forms of contact exhausted. 1/21/26 JE ;; Unable to reach. Letter mailed out 1/15/26 JE. Sent text.1/14/26 JE ;; Vmb full. Sent text. 1/7/26 JE ;; MJ 01/02: St to vm + sent text IV 12/1: left vm, sent text, MJ 10/28: Left VM + sent text IV 9/23: left vm , sent text MJ 09/15: St to VM + sent text MJ 09/08: Left VM + sent text + sent email IV 8/28: left vm, sent text IV 8/19: left vm, sent text
A16: DBS-1315 | B16: 46108 | C16: 2nd Year | D16: Contact attempts have been frequent since May 2025, including calls, texts, voicemails, and a mailed letter. Early on, the individual expressed interest but had scheduling issues (e.g., vacation, oversleeping, feeling overwhelmed). By January 2026, she confirmed she was still interested in participating. However, since then, all follow-up attempts (January through March 2026) have received no response despite multiple messages and voicemails. Currently, the individual is unreachable, with no replies to recent outreach efforts.
A17: DBS-0419 | B17: 45805 | C17: 3rd Year | D17: Lead messaged that she is moving to mexico and is no longer able to continue with study. 5/28/25 -JE | F17: f
A18: DBS-0382 | B18: 45861 | C18: 3rd Year | D18: Responded to email. He is in mex and does not anticipate returning till 3-4 yrs from now. No longer able to participate.
A19: DBS-0757 | B19: 45971 | C19: 3rd Year | D19: Spouse called in after receiving letter. Informed that participant passed Dec 2024 11/10/25 JE ;; Letter mailed out. All forms of contact exhausted. No answer 11/4/25 JE ;; MJ 10/28: Left VM + sent text IV 10/3: left vm, sent text IV 9/23: left vm, sent text
A20: DBS-0414 | B20: 45982 | C20: 3rd Year | D20: Due to family matters not able to cont.
A21: DBS-0379 | B21: 45982 | C21: 3rd Year | D21: Due to family matters not able to cont.
A22: DBS-0183 | B22: 45792 | C22: 3rd Year | D22: Letter mailed out. All forms of contact exhausted. No answer 5/15/25 JE
A23: DBS-0013 | B23: 45994 | C23: 3rd Year | D23: DV 09/18: Mailed letter ;; Has not been answering. Left vm, text and email. 9/8/25 JE ;; MJ 07/28: Left VM MJ 07/24: Left VM + sent text Would like to combine visits if possible. Needs to ask for permision at work. But flexible.
A24: DBS-0219 | B24: 45994 | C24: 3rd Year | D24: Letter mailed out. All forms of contact exhausted. No answer. 11/4/25 JE ;; MJ 10/21: left vm + sent text IV 10/03: left vm sent text IV 9/23: left vm, sent text
A25: DBS-0781 | B25: 45993 | C25: 3rd Year | D25: MJ 12/02: Text message sent bc he's at work. Messaged he is moving to OK- no longer able to cont.
A26: DBS-0901 | B26: 46036 | C26: 3rd Year | D26: Called in to drop out. No time and too far. No longer interested. 1/14/26 JE ;; Called, left VM: CTS 01/5/26
A27: DBS-0352 | B27: 46051 | C27: 3rd Year | D27: Busy and not interested.
A28: DBS-0876 | B28: 46051 | C28: 3rd Year | D28: Not interested in doing a closed MRI again.
A29: DBS-0843 | B29: 46135 | C29: 3rd Year | D29: The patient has been difficult to reach, with no response to multiple contact attempts. A letter was sent on April 1, 2026. They previously opted out of an MRI on February 17. Several calls and messages were made between January and April to schedule or reschedule appointments, but the participant either did not respond, said they would call back, or canceled at the last minute.
... A44: DBS-1684 | B44: 45772 | C44: Baseline | D44: Failed Baseline MRI. Scans did not start. The participant felt overwhelmed when going into the machine.

Sheet Study Progress
A1: Year | B1: Enrolled | C1: Dropped Out/DQ | D1: Completed | E1: Remaining | F1: % Completed (of Total) | G1: % Completed (of Active)
A2: Baseline | B2: 200 | C2: 13 | D2: 187 | E2: 187 | F2: =SUM(D2/B2) -> 0.935 | G2: =SUM(D2/E2) -> 1 | H2: 2023 start | I2: year 1 close march/april 2026
A3: 2 | B3: 200 | C3: 15 | D3: 171 | E3: =B2 - (C2+C3) -> 172 | F3: =SUM(D3/B3) -> 0.855 | G3: =SUM(D3/E3) -> 0.99418605 | I3: year 2 close feb/march 2026
A4: 3 | B4: 200 | C4: 15 | D4: 123 | E4: =B2 - (C2+C3+C4) -> 157 | F4: =SUM(D4/B4) -> 0.615 | G4: =SUM(D4/E4) -> 0.78343949 | I4: year 3 closes jan/feb 2027
A5: 4 | B5: 200 | C5: 0 | D5: 28 | E5: =B2 - (C2+C3+C4+C5) -> 157 | F5: =SUM(D5/B5) -> 0.14 | G5: =SUM(D5/E5) -> 0.17834395 | I5: year 4 closes feb 2028
A6: 5 | B6: 200
B7: 200
B8: 200
B9: 200
E10: 1 2nd yr jumped to 3rd yr

Sheet 2nd Yr Scheduling Notes
B1: ID | C1: NP Date | D1: NP Scheduling Notes | E1: CV Date | F1: CV Scheduling Notes
A2: 45413 | B2: DBS-0007 | C2: 45413 | D2: MJ 04/04: Participant asked to be called back in 10 minutes | E2: 45413
A3: 45413 | B3: DBS-0180 | C3: 45415 | D3: MJ 04/04: Asked to split NP and CV visits | E3: 45422 | F3: MJ 04/04: MJ N/A,,will ask IV to cover
A4: 45413 | B4: DBS-0382 | C4: 45415 | D4: LC 04/09: Work schedule changed. Available after 4:30pm to schedule visits. Confirmed they can continue with study; IV 4/8: left vm @10am, IV 4/16: left vm, sent text | E4: 45415
A5: 45413 | B5: DBS-0322 | C5: 45418 | D5: IV 4/8: left vm @9:58am, IV 4/09: Scheduled for 5/06 | E5: 45418 | F5: IV 4/8: left vm @9:58am, IV 4/09: Scheduled for 5/06
A6: 45413 | B6: DBS-0044 | C6: 45425 | D6: MJ 04/04: Left VM @ 11:41 AM | E6: 45427
A7: 45413 | B7: DBS-0053 | C7: 45427 | D7: MJ 4/23: Needs uber | E7: 45427
A8: 45413 | B8: DBS-0183 | C8: 45429 | D8: IV 4/8: left vm @9:57am, IV 4/10: left vm sent text @11:43am, IV 4/16: will need uber , | E8: 45429
A9: 45413 | B9: DBS-0008 | C9: 45449 | D9: M 04/04: Asked for a call back after 3pm MJ 05/16: Had to cancel visit bc granddaughter was rushed to ER | E9: 45449
A10: 45413 | B10: DBS-0352 | C10: 45461 | D10: LC 05/30: Left vm & sent text; IV 4/8: left vm @10am, IV 4/10: scheduled 5/07, IV 5/7: particpant is sick needs tp reschdules IV5/8: left vm IV 5/14: left vm 5/22:scehduled 5/28 | E10: 45446 | F10: IV 4/8: left vm @10am, IV 4/10: scheduled 5/07
A11: 45413 | B11: DBS-0404 | C11: 45462 | D11: LC 05/30: Left vm to r/s; IV 4/4: scheduled particpant & wife, sent confirmation text , IV 5/7: husband and wife need to reschedule for june | E11: 45462 | F11: IV 4/4: scheduled particpant & wife, sent confirmation text
A12: 45413 | B12: DBS-0139 | C12: 45462 | D12: LC 05/30: Left vm to r/s; IV 4/4: scheduled particpant & wife, sent confirmation text , IV 5/7: husband and wife need to reschedule for june | E12: 45462 | F12: IV 4/4: scheduled particpant & wife, sent confirmation text
A13: 45413 | B13: DBS-0028 | C13: 45476 | D13: MJ 04/05: Will drive,MJ 05/13: Participant no-showed and I left two VMs MJ 05/23: Particiipant no showed again and is not responding to texts & VMs | E13: 45476
A14: 45413 | B14: DBS-0219 | C14: 45594 | D14: IV 4/4: left vm. IV 4/10: left vm sent @11:47am IV 4/16: left vm sent text IV 4/19: left vm IV 4/24: left vm sent text; LC 04/30: Mailed out a letter MJ 05/13: Left VM @ 8:40 AM; GT 10/21 Was able to get in contact, scheduled visit 10/29, new address | E14: 45594
A15: 45413 | B15: DBS-0268 | D15: DROPPED APRIL 2024;; IV 4/4: left vm, V 4/10: left vm sent @11:50 am Iv 4/19: left sent text, IV 4/24: left vm sent text; LC 04/30: Mailed out a letter MJ 05/13: Left VM; LC 05/30: Left vm and sent email; GT 10/21 Left vm, text, and letter
A16: 45444 | B16: DBS-0054 | C16: 45446 | D16: LC 05/06: Scheduled w/ Marlene | E16: 45446
A17: 45444 | B17: DBS-0381 | C17: 45446 | D17: IV 5/9: left vm sent text @12:09pm, IV 5/14: sent con firmation text will drive | E17: 45446
A18: 45444 | B18: DBS-0063 | C18: 45449 | D18: LC 05/06: Scheduled w/ Marlene; Left vm @11:35am | E18: 45449
A19: 45444 | B19: DBS-0299 | C19: 45449 | D19: IV 5/9: NP & CV scheduled | E19: 45449
A20: 45444 | B20: DBS-0419 | C20: 45450 | D20: IV 5/9: NP & CV scheduled | E20: 45450
A21: 45444 | B21: DBS-0154 | C21: 45460 | D21: MJ 05/13: Will drive | E21: 45460
A22: 45444 | B22: DBS-0360 | C22: 45461 | D22: IV 5/9: NP & CV scheduled with MJ | E22: 45461
A23: 45444 | B23: DBS-0221 | C23: 45468 | D23: IV 5/1: confirmed, will drive | E23: 45468
A24: 45444 | B24: DBS-0235 | C24: 45470 | D24: LC 06/20: Sent text; LC 05/30: Email sent; IV 5/14: left vm sent text, IV 5/17: left cm sent text, IV 5/22: might have a new number sent email Iv 5/31; sent text message | E24: 45470
A25: 45444 | B25: DBS-0073 | C25: 45471 | D25: MJ 05/13: Wife and husband (0169) scheduled for 06/19..need new clincards | E25: 45471
A26: 45444 | B26: DBS-0169 | C26: 45471 | D26: Mj 05/13: Scheculed w/ wife (he was in the background) | E26: 45471
A27: 45444 | B27: DBS-0013 | C27: 45516 | D27: LC 05/06: Scheduled w/ Marlene | E27: 45516 | F27: MJ 06/04: Rescheduled for 08/05//bc he had just gotten out of the hospital
A28: 45444 | B28: DBS-0108 | D28: DROPPED NOV 2024 ;; LC 06/20: Sent text; LC 05/30: Email sent to schedule; MJ 05/13: # is no longer in service,,will send email, Iv 10/18: phone # not in service; LC 10/29: Sent text & email; GT 11/20 Sent text, mailed letter
A29: 45474 | B29: DBS-0379 | C29: 45474 | D29: IV 5/31: scheduled siblings together, needs uber | E29: 45474
A30: 45474 | B30: DBS-0414 | C30: 45474 | D30: IV 5/31: scheduled siblings together, needs uber | E30: 45474
A31: 45474 | B31: DBS-0349 | C31: 45475 | D31: IV 5/31: sent confirmation text, will drive | E31: 45475
A32: 45474 | B32: DBS-0432 | C32: 45502 | D32: IV 5/31: sent confrimation text, will drive | E32: 45502
A33: 45474 | B33: DBS-0430 | C33: 45504 | D33: IV 5/31: sent confirmation text, needs uber | E33: 45504
A34: 45474 | B34: DBS-0055 | C34: 45566 | D34: IV 5/31: going to text me dates IV 6/27: asked to call back in an hr, did not answer; LC 07/10: Left vm @9:42am. Sent text. IV 7/15: sent reminder text IV 7/24: left vm, sent text @1:48pm | E34: 45566
A35: 45505 | B35: DBS-0450 | C35: 45505 | D35: IV 6/27: needs uber | E35: 45505
A36: 45505 | B36: DBS-0512 | C36: 45505 | D36: IV 6/27: needs uber | E36: 45505
A37: 45505 | B37: DBS-0199 | C37: 45511 | D37: IV 6/27: left vm sent text IV 7/1: will drive | E37: 45511
A38: 45505 | B38: DBS-0429 | C38: 45512 | D38: LC 08/01: Sent text to r/s; IV 6/27: left vm sent text | E38: 45512
A39: 45505 | B39: DBS-0586 | C39: 45516 | D39: IV 6/27: left vm sent text; LC 07/10: Left vm @9:46am. Sent text | E39: 45516
A40: 45505 | B40: DBS-0499 | C40: 45526 | E40: 45526
A41: 45505 | B41: DBS-0502 | C41: 45531 | D41: IV 6/27: left vm sent text | E41: 45531
A42: 45505 | B42: DBS-0418 | C42: 45595 | D42: IV 6/27: leaving the country next week, not sure when he'll be back ,call in august IV 8/8: participant says he works full time now 7am-5pm, can no longer participate, gio said give him a call end of october to see if he has veterans day off to come in ; GT 10/17 texted to ask about Veteran's day, GT 10/21: Asked me id he could come in on 11/11 around 3 | E42: 45595
A43: 45536 | B43: DBS-0442 | C43: 45520 | D43: IV 7/25: left vm sent text IV 8/14: left vm sent text, scheudled for 8/16 | E43: 45520
A44: 45536 | B44: DBS-0620 | C44: 45539 | D44: IV 7/25: left vm sent text IV 8/2: scheduled, needs uber | E44: 45539
A45: 45536 | B45: DBS-0613 | C45: 45540 | D45: IV 7/25: scheduled, needs uber | E45: 45540
A46: 45536 | B46: DBS-0676 | C46: 45544 | D46: IV 7/25:scheduled, will drive, needs study partner consent form | E46: 45544
A47: 45566 | B47: DBS-0745 | C47: 45566 | D47: IV 8/26: will drive | E47: 45566
A48: 45566 | B48: DBS-0772 | C48: 45567 | D48: IV 8/26: needs uber | E48: 45567
A49: 45566 | B49: DBS-0216 | C49: 45568 | D49: IV 8/26: will drive | E49: 45568
A50: 45566 | B50: DBS-0597 | C50: 45574 | D50: IV 8/26: could not leave vm, sent text 2:44pm, texted back she'll call tmr IV 8/28: texted her if she was available to call | E50: 45574
A51: 45566 | B51: DBS-0599 | C51: 45579 | D51: IV 8/26: needs uber | E51: 45579
A52: 45566 | B52: DBS-0757 | C52: 45580 | D52: IV 8/26: needs uber | E52: 45580
... A56: 45566 | B56: DBS-0658 | C56: 45603 | D56: IV 8/26: left vm sent text @1:28pm IV 8/28: might need uber, confirm before, Iv 10/18: rescheduled | E56: 45603
A57: 45566 | B57: DBS-0705 | D57: DROPPED SEP 2025 ;; Sent check in message. Replied "stop". No reason given. 9/22/25 JE ;; IV 6/23: said shes dealing with household issues, will reach out when available IV 4/23: left vm, sent text IV 8/26: left vm sent text @1:31pm IV 8/28: left vm @12:32pm IV9/12: left vm sent text @1:42pm IV 9/18: VM full, sent text, sent email, IV 10/18: vm full, sent text; LC 10/29: Email sent; LC 10/31: Sent text; LC 12/18: Unable to leave vm;
A58: 45566 | B58: DBS-0542 | D58: DROPPED APRIL 2024 ;; IV 4/23: DROP OUT, says too busy with work will not be able to continue any visits .IV 3/28: sent text IV 8/26: participant says only has sundays off, works 7-6pm, gio said give her a call end of october to see if she has veterans day off to come in; GT 10/17 texted to ask about Veteran's day
A59: 45566 | B59: DBS-0498 | C59: 45848 | D59: IV 6/30: emailed me, working to scheudle 6/25 NC Mailed Letter IV 6/23: sent email, vm not set up IV 4/23: VM not set up, sent text , SENT EMAIL IV 4/23: VM not set up, sent text IV 3/28: sent text IV 8/26: left vm sent text @1:06pm IV 8/28: left vm @12:22pm IV 9/12: left vm sent text @1:39pm IV 9/18: left vm sent text @11:04am, sent email; LC 10/16: left vm. sent text: LC 10/17: Schedule for December | E59: 45848 | F59: reproductive History missing
A60: 45597 | B60: DBS-0652 | C60: 45604 | D60: IV 10/16: will drive | E60: 45604
A61: 45597 | B61: DBS-0693 | C61: 45607 | D61: IV 10/16: said she was going to contact us about dropping out, she is doing a weight loss study with medication and has a lot of visits for it, cannot take more days off for our study, she is receiving a larger compensation | E61: 45607
A62: 45597 | B62: DBS-0741 | C62: 45608 | D62: IV 10/16: left vm, sent text (might not deliver) | E62: 45608
A63: 45597 | B63: DBS-0855 | C63: 45609 | D63: IV 10/16: will drive | E63: 45609
A64: 45597 | B64: DBS-0790 | C64: 45611 | D64: IV 10/16: needs to review schedule, will text me dates or call back friday, IV 10/18: left vm , IV 10/21: will drive, but offer uber again | E64: 45611
A65: 45597 | B65: DBS-0614 | C65: 45622 | D65: IV 10/16: left vm, sent text (might not deliver), IV 10/18: left vm sent text @1:32pm IV 10/21: will drive, IV 11/01: needs to reschedule, thought it was 11/5, didnt trxt back new date, IV 11/04: left vm IV 11/6: sent text IV 11/08: left vm IV 11/12: texted me back asking about 11/25, trying to schedule | E65: 45622
A66: 45597 | B66: DBS-0800 | C66: 45622 | D66: IV 10/16: call back in 30 mins , IV 10/18: said to call back in 15, called back no answer, left vm, confirmed, will driv e | E66: 45622
A67: 45597 | B67: DBS-0756 | C67: 45631 | D67: IV 10/16: left vm, sent text (might not deliver) IV 10/18: left vm IV 10/22: left vm, sent text , IV 10/29: left vm, LC 10/31: Email sent, IV 11/12: left vm sent text @2:28pm, he said call back the 19th when hes back IV 11/22: needs uber | E67: 45631
A68: 45597 | B68: DBS-0771 | C68: 45699 | D68: IV 10/16: will send me availabilty later, had an appointment Iv 11/16: needs to reschedule , IV 12/04: sent remidner to send dates IV 12/11: sent message Iv 12/13: scheduled IV 1/13: sent message to reschedule IV 1/16: left vm IV 1/30: contacted, said shes been busy will send me dates | E68: 45699
A69: 45597 | B69: DBS-0715 | C69: 45722 | D69: IV 2/28: sent a text, asking for avaiablity to come, scheduled IV 10/16: left vm, sent text (might not deliver) IV 10/18: will drive IV 11/26: 4th cancel, needs to reschedule, lorena will callI | E69: 45722 | F69: IV 3/6: Dr. Harrington injured knee had to cancel, she had trouble with availability to come and lives far only day she can come, not sure if she'll be able to come back for the CV , no changes to medical history
A70: 45627 | B70: DBS-0763 | C70: 45617 | D70: IV 11/08: vm not set up, sent text, IV 11/11: set up time to call today at 2, NP & CV scheduled diff days | E70: 45614
A71: 45627 | B71: DBS-0824 | C71: 45629 | D71: LC 11/07: will call back | E71: 45629
A72: 45627 | B72: DBS-0884 | C72: 45629 | E72: 45629
A73: 45627 | B73: DBS-0818 | C73: 45632 | D73: IV 11/11: will drive | E73: 45632
A74: 45627 | B74: DBS-0805 | C74: 45635 | D74: IV 11/08: left vm sent text @2:55pm IV 11/21: could not leave vm, sent text , needs uber | E74: 45635
A75: 45627 | B75: DBS-0653 | C75: 45636 | D75: IV 11/08: vm full sent text @2:45pm IV 11/12: needs uber | E75: 45636
A76: 45627 | B76: DBS-0617 | C76: 45637 | D76: IV 11/08: left vm, sent text @2:41pm, IV 11/12: left sent text @2:33pm IV 11/15, new number needs, uber | E76: 45637
A77: 45627 | B77: DBS-0781 | C77: 45637 | D77: IV 11/08: answered hanged up, sent text , IV 11/19: replied to text, sending over dates to choose from IV 12/4: rs 12/11 | E77: 45637
A78: 45627 | B78: DBS-0879 | C78: 45637 | D78: LC 12/04: r/s for different day | E78: 45637
A79: 45627 | B79: DBS-0838 | C79: 45685 | D79: LC 11/07: Left vm, IV 11/22: left vm sent text | E79: 45685
A80: 45627 | B80: DBS-0822 | C80: 45733 | D80: IV 11/11: needs uber IV 12/13: needs to move IV 1/27: mom is sick, going to visit, will return march | E80: 45733
A81: 45627 | B81: DBS-0830 | C81: skip | D81: JE 9/24: NP good to schedule...@ 4-4:30 mon-wed...works 7-3pm in BH. May be open to holidays ;; Sent check in message. Open conversation through text is open. Requesting afternoon. Working on setting up date. 9/22/25 JE ;; IV 7/14: said she'll call me back later, not sure if she will IV 6/23: said to call back after 5pm IV 4/23: left vm, sent text IV 4/4: IV 3/28: sent text LC 11/07: Got appendix surgery. Call back mid December to schedule for January; Left vm | E81: skip | F81: came a year late, treating as a 3rd year
A82: 45658 | B82: DBS-0935 | C82: 45670 | D82: IV 12/18: will drive | E82: 45670
A83: 45658 | B83: DBS-0981 | C83: 45671 | D83: IV 12/18: will drive | E83: 45671
A84: 45658 | B84: DBS-0770 | C84: 45672 | D84: 12/15: will drive | E84: 45672 | F84: 12/15: will drive
A85: 45658 | B85: DBS-0916 | C85: 45674 | D85: IV 12/18: could not leave vm, sent text , IV 12/19: sent text , will drive | E85: 45674
A86: 45658 | B86: DBS-0956 | C86: 45678 | D86: IV 12/18: old & new # not in service, sent email , IV 1/6: phone # not in service | E86: 45678
A87: 45658 | B87: DBS-0843 | C87: 45680 | D87: IV 12/19: left vm, sent text IV 1/6: will drive | E87: 45680
A88: 45658 | B88: DBS-0918 | C88: 45686 | D88: IV 12/18: call back tmr afternoon IV 1/6: call after 4 | E88: 45686
A89: 45658 | B89: DBS-0878 | C89: 45687 | D89: IV 12/16: left vm Iv 12/19: left vm sent text , will drive | E89: 45687
A90: 45658 | B90: DBS-0924 | C90: 45687 | D90: IV 12/18: will drive IV 1/13: sent message to reschule IV 1/16: left vm | E90: 45687
A91: 45658 | B91: DBS-0789 | C91: 45688 | D91: IV 12/16: left vm, IV 12/19: left vm , sent text, IV 1/6: will drive | E91: 45688
A92: 45658 | B92: DBS-0908 | C92: 45709 | D92: IV 12/16: will send me avaialble dates IV 12/18: scheduled for her and husband Iv 1/07: needs to rescheduel her and husband, will send me dates IV 1/13: sent message to reschedule for her and hsuband IV 1/22: out of town, schedule for february | E92: 45849 | F92: IV 6/30: called me responding to the letter, will drive 6/25 NC Mailed Letter MJ 06/23: LEFT VM @ 11:13 AM IV 4/03: followed up to check if avaialble this month IV 3/12: need to rescheldule bc of work, will let me know a new date, both their schedule changes often, have cancelled a few times
A93: 45658 | B93: DBS-0978 | C93: 45709 | D93: IV 12/18: scheduled with wife IV 1/07: will reschedule with wife, will send dates IV 1/22: out of town, schedule for february | E93: 45849 | F93: IV 6/30: called me responding to the letter, will drive 6/25 NC Mailed Letter MJ 06/23: LEFT VM @ 11:13 AM IV 4/23: texted the husband, since wife didnt answer IV 3/12: need to rescheldule bc of work, will let me know a new date, both their schedule changes often, have cancelled a few times
A94: 45658 | B94: DBS-0808 | D94: DROPPED FEB 2025 ;; IV 12/16: phone # not in service, sent email , IV 1/6: not in service, mot likely wont come back, gave us trouble last year; LC 02/28: F/u via text
A95: 45689 | B95: DBS-0987 | C95: 45671 | D95: LC 01/14: Left vm | E95: 45671 | F95: LC 01/14: Left vm
A96: 45689 | B96: DBS-1019 | C96: 45701 | E96: 45701
A97: 45689 | B97: DBS-1039 | C97: 45714 | D97: IV 1/27: was working, asked to to text her and she'll send dates IV 1/28: will drive | E97: 45714
A98: 45689 | B98: DBS-0940 | C98: 45720 | D98: LC 02/25: Sent text to r/s | E98: 45720
A99: 45689 | B99: DBS-0982 | C99: 45691 | D99: IV 1/27: left vm | E99: 45691
A100: 45689 | B100: DBS-1016 | C100: 45691 | D100: LC 01/28: Sent text; IV 1/27: left vm Iv 1/28: sent confirmation text. | E100: 45691
A101: 45689 | B101: DBS-0971 | C101: 45694 | D101: IV 1/31: left vm @12:23pm, will drive | E101: 45694
A102: 45689 | B102: DBS-0901 | C102: 45695 | D102: IV 1/27: will drive | E102: 45695
A103: 45689 | B103: DBS-1030 | C103: 45700 | E103: 45700
...

Sheet Baseline Scheduling Notes
B1: IV Site | C1: Initial Visit Date | D1: IV Notes | E1: Study Partner ICF signed | F1: BD Date | G1: BD Scheduling Notes | H1: NP Date | I1: NP Scheduling Notes | J1: MRI | K1: MRI Scheduling Notes | L1: LP Date | M1: LP Notes | N1: CV Date | O1: CV Scheduling Notes | P1: Cabinet Location | Q1: Binder # | R1: IPAD
A2: DBS-0044 | B2: USC | C2: 45001 | E2: 45090 | F2: 03/16/23; 04/21/23 | G2: LC 04/14: Need to redo BD | H2: 45051 | J2: 45085 | K2: LC 05/23: Call back tomorrow | L2: Opt Out | N2: 45037 | P2: 1 | Q2: 6 | R2: 2 ENGLISH
A3: DBS-0053 | B3: USC | C3: 45005 | E3: 45091 | F3: 45005 | H3: 45064 | J3: 45089 | L3: Opt Out | N3: 45064 | P3: 1 | Q3: 7 | R3: 1 SPANISH
A4: DBS-0219 | B4: USC | C4: 45023 | D4: LC 03/22: Call to schedule; LC 03/28: Left vm | E4: LC 02/24 sent link | F4: 45023 | H4: 45055 | J4: 45114 | L4: Opt Out | N4: 45055 | P4: 2 | Q4: 11 | R4: 2 SPANISH
A5: DBS-0349 | B5: USC | C5: 45118 | E5: 45126 | F5: 45126 | H5: 45126 | J5: 45119 | L5: Opt Out | N5: 45126 | P5: 2 | Q5: 17 | R5: 1 SPANISH
A6: DBS-0008 | B6: USC | C6: 45019 | E6: 45140 | F6: 45019 | H6: 45071 | J6: 45124 | L6: 45077 | N6: 45071 | P6: 1 | Q6: 3 | R6: 1 SPANISH (2024) and 2 SPANISH (2024)
A7: DBS-0299 | B7: Docusign | C7: 45063 | D7: GT 5/16: rescheduled for 5/17; GT 4/25: Scheduled IV Docusign for 5/1 @ 12pm | E7: Mailed on 2/27/24 | F7: 45086 | G7: GT 6/8: Confirmed will drive | H7: 45086 | I7: GT 6/8: Confirmed will drive | J7: 45124 | L7: Opt Out | N7: 45086 | O7: GT 6/8: Confirmed will drive | P7: 2 | Q7: 15 | R7: 1 SPANISH
